Workbook

Sheet 01_Visao_Geral
A1: ARQUITETURA INICIAL DA PLATAFORMA HUB
A3: Primeiro dimensionamento funcional para, no segundo momento, transformar escopo em custo real de produto, tecnologia, dados e operação.
A5: Código | B5: Frente / módulo | C5: Público | D5: Modelo | E5: Standalone? | F5: O que resolve | G5: Integrações | H5: Leitura | I5: MOD (Tecnica)
A6: CORE | B6: Core / Plataforma | C6: Transversal | D6: Base comum | E6: Sim | F6: Autenticação, perfis, permissões, consentimentos, integrações, notificações, analytics e administração. | G6: Todas as frentes usam o Core. | H6: Obrigatório para qualquer implantação. | I6: MOD-01
A7: ED | B7: Estratégia & Dados | C7: Empresas | D7: Produto independente | E7: Sim | F7: Conecta dados internos de pessoas e negócio para diagnóstico, prioridades, planos de ação e ROI. | G7: Pode receber dados de RH/ERP/BI sem usar candidatos, fornecedores, acadêmico ou eventos. | H7: Pode ser vendido sozinho. | I7: MOD-08
A8: COL | B8: Colaboradores / Meu Time | C8: Empresas | D8: Independente ou conectado a ED | E8: Sim | F8: Desempenho, competências, desenvolvimento, liderança, saúde do time e talentos internos. | G8: Alimenta ED com sinais de pessoas e recebe prioridades/planos. | H8: Pode operar sem marketplace externo. | I8: MOD-02/03
A9: CAN | B9: Candidatos & Carreira | C9: Pessoas + Empresas | D9: Marketplace / jornada | E9: Sim | F9: Perfil, competências, capacitação, oportunidades, candidatura, match e acompanhamento. | G9: Conversa com Acadêmico, Empresas, Eventos e Core. | H9: Vertical de empregabilidade. | I9: MOD-03
A10: FOR | B10: Fornecedores & Negócios | C10: Fornecedores + Compradores | D10: Marketplace B2B | E10: Sim | F10: Maturidade, demandas, desenvolvimento, match, negociação e conversão. | G10: Conversa com Eventos, ED e Core. | H10: Pode operar sozinho para acesso a mercado. | I10: MOD-05
A11: ACA | B11: Acadêmico / Universidades | C11: Alunos + Universidades + Empresas | D11: Educação-mercado | E11: Sim | F11: Projetos, bolsas, pesquisa aplicada, estágio, carreira, formação e conexão com empresas. | G11: Conversa fortemente com Candidatos e Empresas; opcionalmente Eventos. | H11: Pode ser vendido sozinho para universidade. | I11: MOD-06
A12: EVT | B12: Eventos | C12: Organizadores + Público + Empresas | D12: Orquestrador transversal | E12: Parcial | F12: Talentos, fornecedores, pesquisa, patrocínios, acessibilidade, segurança/assédio e ROI. | G12: Consome Candidatos, Fornecedores e Dados; pode ativar Acadêmico. | H12: Pode começar standalone, mas ganha valor com outros módulos. | I12: MOD-07
A13: COM | B13: Comunidades / Eu & Eu / Cultura | C13: Pessoas | D13: Jornada individual | E13: Sim | F13: Perfil, objetivos, plano, preparação, mentoria, cuidado, eventos e conexões. | G13: Pode alimentar Candidatos, Acadêmico e Eventos com consentimento. | H13: Camada B2C; não é pré-requisito B2B. | I13: MOD-07
A14: CUST | B14: Clientes & Receita | C14: Empresas/CS | D14: Independente ou conectado a ED | E14: Sim | F14: Contas, contratos, NPS, churn, receita e margem por cliente. | G14: CRM/ERP; alimenta ED/HUB Impact. | H14: Novo — MOD-04 Tecnica (MVP). | I14: MOD-04
A16: PRINCÍPIO DE ARQUITETURA

Sheet 02_Inventario_Paginas
A1: INVENTÁRIO DE PÁGINAS / TELAS
A5: ID | B5: Código | C5: Frente | D5: Página / tela | E5: Canal | F5: Fase | G5: Complexidade | H5: Compartilhável? | I5: Dependência | J5: Observação | K5: MOD (Tecnica) | L5: Fase Tecnica | M5: Ref Tecnica
A6: 1 | B6: CORE | C6: Core / Plataforma | D6: Login / SSO | E6: Web | F6: MVP | G6: Baixa | H6: Sim | I6: - | J6: Autenticação | K6: MOD-01 | L6: MVP (F0/MVP1) | M6: INT-08/BL-001
A7: 2 | B7: CORE | C7: Core / Plataforma | D7: Cadastro / onboarding | E7: Web/Mobile | F7: MVP | G7: Média | H7: Sim | I7: - | J7: Entrada por tipo | K7: MOD-01 | L7: MVP (F0/MVP1) | M7: BL-001
A8: 3 | B8: CORE | C8: Core / Plataforma | D8: Perfis e organizações | E8: Web | F8: MVP | G8: Média | H8: Sim | I8: - | J8: Entidades | K8: MOD-01 | L8: MVP (F0/MVP1) | M8: BL-001
A9: 4 | B9: CORE | C9: Core / Plataforma | D9: Papéis e permissões | E9: Admin | F9: MVP | G9: Alta | H9: Sim | I9: - | J9: RBAC | K9: MOD-01 | L9: MVP (F0/MVP1) | M9: GOV-03/BL-016
A10: 5 | B10: CORE | C10: Core / Plataforma | D10: Consentimentos / LGPD | E10: Web/Admin | F10: MVP | G10: Alta | H10: Sim | I10: - | J10: Privacidade | K10: MOD-01 | L10: MVP (F0/MVP1) | M10: GOV-01/GOV-04
A11: 6 | B11: CORE | C11: Core / Plataforma | D11: Central de integrações | E11: Admin | F11: MVP | G11: Alta | H11: Sim | I11: - | J11: APIs/RHIS/ERP/CRM/LMS | K11: MOD-01 | L11: MVP (F0/MVP1) | M11: INT-01..06/BL-002..005
A12: 7 | B12: CORE | C12: Core / Plataforma | D12: Notificações | E12: Web/Mobile | F12: MVP | G12: Média | H12: Sim | I12: - | J12: Gatilhos | K12: MOD-01 | L12: MVP (F0/MVP1) | M12: BL-010
A13: 8 | B13: CORE | C13: Core / Plataforma | D13: Mensagens | E13: Web/Mobile | F13: Fase 2 | G13: Alta | H13: Sim | I13: - | J13: Conversas | K13: MOD-01 | L13: Fase 2 | M13: sem ref direta (Fase 2)
A14: 9 | B14: CORE | C14: Core / Plataforma | D14: Busca global | E14: Web | F14: Fase 2 | G14: Média | H14: Sim | I14: - | J14: Busca | K14: MOD-01 | L14: Fase 2 | M14: sem ref direta (Fase 2)
A15: 10 | B15: CORE | C15: Core / Plataforma | D15: Analytics de uso | E15: Admin | F15: MVP | G15: Média | H15: Sim | I15: - | J15: Adoção | K15: MOD-01 | L15: MVP (F0/MVP1) | M15: KPI-HUB-01/BL-014
A16: 11 | B16: CORE | C16: Core / Plataforma | D16: Administração | E16: Admin | F16: MVP | G16: Alta | H16: Sim | I16: - | J16: Configurações | K16: MOD-01 | L16: MVP (F0/MVP1) | M16: BL-001
A17: 12 | B17: CORE | C17: Core / Plataforma | D17: Auditoria e logs | E17: Admin | F17: MVP | G17: Alta | H17: Sim | I17: - | J17: Rastreabilidade | K17: MOD-01 | L17: MVP (F0/MVP1) | M17: GOV-09/SRC-12
... A116: 111 | B116: CUST | C116: Clientes & Receita | D116: Expansão e rentabilidade | E116: Web | F116: MVP | G116: Alta | H116: Não | I116: CORE | J116: Upsell e mix | K116: MOD-04 | L116: MVP (MVP1) | M116: SCR-01

Sheet 03_Resumo_Modulos
A1: RESUMO DE ESCOPO POR MÓDULO
A5: Código | B5: Módulo | C5: Total telas | D5: MVP | E5: Fase 2 | F5: Alta/Muito alta | G5: Standalone? | H5: Leitura | I5: MVP+1
A6: CORE | B6: Core / Plataforma | C6: =COUNTIF('02_Inventario_Paginas'!$B$6:$B$200,A6) | D6: =COUNTIFS('02_Inventario_Paginas'!$B$6:$B$200,A6,'02_Inventario_Paginas'!$F$6:$F$200,"MVP") | E6: =COUNTIFS('02_Inventario_Paginas'!$B$6:$B$200,A6,'02_Inventario_Paginas'!$F$6:$F$200,"Fase 2") | F6: =COUNTIFS('02_Inventario_Paginas'!$B$6:$B$200,A6,'02_Inventario_Paginas'!$G$6:$G$200,"Alta")+COUNTIFS('02_Inventario_Paginas'!$B$6:$B$200,A6,'02_Inventario_Paginas'!$G$6:$G$200,"Muito alta") | G6: Sim | H6: Obrigatório para qualquer implantação. | I6: =COUNTIFS('02_Inventario_Paginas'!$B$6:$B$200,A6,'02_Inventario_Paginas'!$F$6:$F$200,"MVP+1")
A7: ED | B7: Estratégia & Dados | C7: =COUNTIF('02_Inventario_Paginas'!$B$6:$B$200,A7) | D7: =COUNTIFS('02_Inventario_Paginas'!$B$6:$B$200,A7,'02_Inventario_Paginas'!$F$6:$F$200,"MVP") | E7: =COUNTIFS('02_Inventario_Paginas'!$B$6:$B$200,A7,'02_Inventario_Paginas'!$F$6:$F$200,"Fase 2") | F7: =COUNTIFS('02_Inventario_Paginas'!$B$6:$B$200,A7,'02_Inventario_Paginas'!$G$6:$G$200,"Alta")+COUNTIFS('02_Inventario_Paginas'!$B$6:$B$200,A7,'02_Inventario_Paginas'!$G$6:$G$200,"Muito alta") | G7: Sim | H7: Pode ser vendido sozinho. | I7: =COUNTIFS('02_Inventario_Paginas'!$B$6:$B$200,A7,'02_Inventario_Paginas'!$F$6:$F$200,"MVP+1")
A8: COL | B8: Colaboradores / Meu Time | C8: =COUNTIF('02_Inventario_Paginas'!$B$6:$B$200,A8) | D8: =COUNTIFS('02_Inventario_Paginas'!$B$6:$B$200,A8,'02_Inventario_Paginas'!$F$6:$F$200,"MVP") | E8: =COUNTIFS('02_Inventario_Paginas'!$B$6:$B$200,A8,'02_Inventario_Paginas'!$F$6:$F$200,"Fase 2") | F8: =COUNTIFS('02_Inventario_Paginas'!$B$6:$B$200,A8,'02_Inventario_Paginas'!$G$6:$G$200,"Alta")+COUNTIFS('02_Inventario_Paginas'!$B$6:$B$200,A8,'02_Inventario_Paginas'!$G$6:$G$200,"Muito alta") | G8: Sim | H8: Pode operar sem marketplace externo. | I8: =COUNTIFS('02_Inventario_Paginas'!$B$6:$B$200,A8,'02_Inventario_Paginas'!$F$6:$F$200,"MVP+1")
A9: CAN | B9: Candidatos & Carreira | C9: =COUNTIF('02_Inventario_Paginas'!$B$6:$B$200,A9) | D9: =COUNTIFS('02_Inventario_Paginas'!$B$6:$B$200,A9,'02_Inventario_Paginas'!$F$6:$F$200,"MVP") | E9: =COUNTIFS('02_Inventario_Paginas'!$B$6:$B$200,A9,'02_Inventario_Paginas'!$F$6:$F$200,"Fase 2") | F9: =COUNTIFS('02_Inventario_Paginas'!$B$6:$B$200,A9,'02_Inventario_Paginas'!$G$6:$G$200,"Alta")+COUNTIFS('02_Inventario_Paginas'!$B$6:$B$200,A9,'02_Inventario_Paginas'!$G$6:$G$200,"Muito alta") | G9: Sim | H9: Vertical de empregabilidade. | I9: =COUNTIFS('02_Inventario_Paginas'!$B$6:$B$200,A9,'02_Inventario_Paginas'!$F$6:$F$200,"MVP+1")
A10: FOR | B10: Fornecedores & Negócios | C10: =COUNTIF('02_Inventario_Paginas'!$B$6:$B$200,A10) | D10: =COUNTIFS('02_Inventario_Paginas'!$B$6:$B$200,A10,'02_Inventario_Paginas'!$F$6:$F$200,"MVP") | E10: =COUNTIFS('02_Inventario_Paginas'!$B$6:$B$200,A10,'02_Inventario_Paginas'!$F$6:$F$200,"Fase 2") | F10: =COUNTIFS('02_Inventario_Paginas'!$B$6:$B$200,A10,'02_Inventario_Paginas'!$G$6:$G$200,"Alta")+COUNTIFS('02_Inventario_Paginas'!$B$6:$B$200,A10,'02_Inventario_Paginas'!$G$6:$G$200,"Muito alta") | G10: Sim | H10: Pode operar sozinho para acesso a mercado. | I10: =COUNTIFS('02_Inventario_Paginas'!$B$6:$B$200,A10,'02_Inventario_Paginas'!$F$6:$F$200,"MVP+1")
A11: ACA | B11: Acadêmico / Universidades | C11: =COUNTIF('02_Inventario_Paginas'!$B$6:$B$200,A11) | D11: =COUNTIFS('02_Inventario_Paginas'!$B$6:$B$200,A11,'02_Inventario_Paginas'!$F$6:$F$200,"MVP") | E11: =COUNTIFS('02_Inventario_Paginas'!$B$6:$B$200,A11,'02_Inventario_Paginas'!$F$6:$F$200,"Fase 2") | F11: =COUNTIFS('02_Inventario_Paginas'!$B$6:$B$200,A11,'02_Inventario_Paginas'!$G$6:$G$200,"Alta")+COUNTIFS('02_Inventario_Paginas'!$B$6:$B$200,A11,'02_Inventario_Paginas'!$G$6:$G$200,"Muito alta") | G11: Sim | H11: Pode ser vendido sozinho para universidade. | I11: =COUNTIFS('02_Inventario_Paginas'!$B$6:$B$200,A11,'02_Inventario_Paginas'!$F$6:$F$200,"MVP+1")
A12: EVT | B12: Eventos | C12: =COUNTIF('02_Inventario_Paginas'!$B$6:$B$200,A12) | D12: =COUNTIFS('02_Inventario_Paginas'!$B$6:$B$200,A12,'02_Inventario_Paginas'!$F$6:$F$200,"MVP") | E12: =COUNTIFS('02_Inventario_Paginas'!$B$6:$B$200,A12,'02_Inventario_Paginas'!$F$6:$F$200,"Fase 2") | F12: =COUNTIFS('02_Inventario_Paginas'!$B$6:$B$200,A12,'02_Inventario_Paginas'!$G$6:$G$200,"Alta")+COUNTIFS('02_Inventario_Paginas'!$B$6:$B$200,A12,'02_Inventario_Paginas'!$G$6:$G$200,"Muito alta") | G12: Parcial | H12: Pode começar standalone, mas ganha valor com outros módulos. | I12: =COUNTIFS('02_Inventario_Paginas'!$B$6:$B$200,A12,'02_Inventario_Paginas'!$F$6:$F$200,"MVP+1")
A13: COM | B13: Comunidades / Eu & Eu / Cultura | C13: =COUNTIF('02_Inventario_Paginas'!$B$6:$B$200,A13) | D13: =COUNTIFS('02_Inventario_Paginas'!$B$6:$B$200,A13,'02_Inventario_Paginas'!$F$6:$F$200,"MVP") | E13: =COUNTIFS('02_Inventario_Paginas'!$B$6:$B$200,A13,'02_Inventario_Paginas'!$F$6:$F$200,"Fase 2") | F13: =COUNTIFS('02_Inventario_Paginas'!$B$6:$B$200,A13,'02_Inventario_Paginas'!$G$6:$G$200,"Alta")+COUNTIFS('02_Inventario_Paginas'!$B$6:$B$200,A13,'02_Inventario_Paginas'!$G$6:$G$200,"Muito alta") | G13: Sim | H13: Camada B2C; não é pré-requisito B2B. | I13: =COUNTIFS('02_Inventario_Paginas'!$B$6:$B$200,A13,'02_Inventario_Paginas'!$F$6:$F$200,"MVP+1")
A14: CUST | B14: Clientes & Receita | C14: =COUNTIF('02_Inventario_Paginas'!$B$6:$B$200,A14) | D14: =COUNTIFS('02_Inventario_Paginas'!$B$6:$B$200,A14,'02_Inventario_Paginas'!$F$6:$F$200,"MVP") | E14: =COUNTIFS('02_Inventario_Paginas'!$B$6:$B$200,A14,'02_Inventario_Paginas'!$F$6:$F$200,"Fase 2") | F14: =COUNTIFS('02_Inventario_Paginas'!$B$6:$B$200,A14,'02_Inventario_Paginas'!$G$6:$G$200,"Alta")+COUNTIFS('02_Inventario_Paginas'!$B$6:$B$200,A14,'02_Inventario_Paginas'!$G$6:$G$200,"Muito alta") | G14: Sim | H14: Novo — MOD-04 Tecnica (MVP); CRM/NPS/churn. | I14: =COUNTIFS('02_Inventario_Paginas'!$B$6:$B$200,A14,'02_Inventario_Paginas'!$F$6:$F$200,"MVP+1")

Sheet 04_Matriz_Integracoes
A1: MATRIZ DE INTEGRAÇÃO ENTRE FRENTES
A3: 3 = mesmo módulo | 2 = integração direta/forte | 1 = opcional/troca de dados | 0 = não precisa conversar diretamente
A5: Código | B5: Módulo | C5: MOD-01 | D5: MOD-02 | E5: MOD-03 | F5: MOD-04 | G5: MOD-05 | H5: MOD-06 | I5: MOD-07 | J5: MOD-08
A6: MOD-01 | B6: HUB Core | C6: 3 | D6: 2 | E6: 2 | F6: 2 | G6: 2 | H6: 2 | I6: 2 | J6: 2
A7: MOD-02 | B7: Performance | C7: 2 | D7: 3 | E7: 2 | F7: 2 | G7: 0 | H7: 0 | I7: 0 | J7: 2
A8: MOD-03 | B8: Pessoas e Talentos | C8: 2 | D8: 2 | E8: 3 | F8: 1 | G8: 0 | H8: 2 | I8: 1 | J8: 2
A9: MOD-04 | B9: Clientes e Receita | C9: 2 | D9: 2 | E9: 1 | F9: 3 | G9: 1 | H9: 0 | I9: 1 | J9: 2
A10: MOD-05 | B10: Fornecedores e Compras | C10: 2 | D10: 0 | E10: 0 | F10: 1 | G10: 3 | H10: 0 | I10: 2 | J10: 1
A11: MOD-06 | B11: Acadêmico | C11: 2 | D11: 0 | E11: 2 | F11: 0 | G11: 0 | H11: 3 | I11: 2 | J11: 1
A12: MOD-07 | B12: Comunidades e Eventos | C12: 2 | D12: 0 | E12: 1 | F12: 1 | G12: 2 | H12: 2 | I12: 3 | J12: 1
A13: MOD-08 | B13: HUB Impact | C13: 2 | D13: 2 | E13: 2 | F13: 2 | G13: 1 | H13: 1 | I13: 1 | J13: 3

Sheet 05_Fluxos_Diretos
A1: O QUE CONVERSA DIRETAMENTE — E O QUE NÃO PRECISA
A5: Origem | B5: Destino | C5: Tipo | D5: Dado compartilhado | E5: Por que integrar | F5: Obrigatória? | G5: Funciona sem? | H5: Exemplo
A6: MOD-08 HUB Impact | B6: MOD-02 Performance | C6: Direta | D6: KPIs, skills, desempenho, liderança | E6: Enriquece pessoas x negócio | F6: Não | G6: Sim | H6: ED pode usar RHIS/ERP/BI sem COL.
A7: MOD-08 HUB Impact | B7: MOD-07 | C7: Direta | D7: Pesquisa, receita, custos, fornecedores, equipes | E7: Conecta operação ao ROI | F7: Não | G7: Sim | H7: EVT pode enviar dados agregados.
A8: MOD-08 HUB Impact | B8: MOD-05 | C8: Opcional | D8: Spend, conversão, impacto | E8: Analisa cadeia e negócios | F8: Não | G8: Sim | H8: ED não depende do marketplace B2B.
A9: MOD-08 HUB Impact | B9: MOD-03 | C9: Opcional | D9: Funil, contratação, skills | E9: Relaciona atração e performance | F9: Não | G9: Sim | H9: Pode usar ATS existente.
A10: MOD-03 | B10: MOD-06 | C10: Direta | D10: Perfil, skills, formação, projetos, estágio | E10: Formação -> empregabilidade | F10: Não | G10: Sim | H10: ACA pode ter oportunidades próprias.
A11: MOD-03 | B11: MOD-07 | C11: Direta | D11: Talentos temporários e vagas | E11: Contratação para eventos | F11: Não | G11: Sim | H11: EVT pode integrar ATS externo.
A12: MOD-05 | B12: MOD-07 | C12: Direta | D12: Fornecedores, demandas, docs, contratos | E12: Compras do evento | F12: Não | G12: Sim | H12: EVT pode cadastrar base própria.
A13: MOD-06 | B13: Empresas/MOD-03 | C13: Direta | D13: Projetos, bolsas, estágios, pesquisa | E13: Universidade -> mercado | F13: Não | G13: Sim | H13: ACA pode começar isolado.
A14: MOD-07 | B14: MOD-03 | C14: Direta c/ consentimento | D14: Perfil, objetivos, preparação | E14: Evita recadastro | F14: Não | G14: Sim | H14: CAN pode ter onboarding próprio.
A15: MOD-07 | B15: MOD-07 | C15: Direta c/ consentimento | D15: Interesses, presença, pesquisa | E15: Personaliza experiência | F15: Não | G15: Sim | H15: EVT pode operar com base própria.
A16: MOD-03 | B16: MOD-05 | C16: Sem integração direta | D16: - | E16: Marketplaces diferentes | F16: Não | G16: Sim | H16: Cruza apenas em casos via Core/Eventos.
... A18: MOD-02 Performance | B18: MOD-04 Clientes e Receita | C18: Direta | D18: Metas e entrega por conta | E18: Liga esforço a resultado do cliente | F18: Não | G18: Sim | H18: SCR-01

Sheet 06_Cenarios_Implantacao
A1: CENÁRIOS DE IMPLANTAÇÃO MODULAR
A5: Cenário | B5: MOD-01 | C5: MOD-02 | D5: MOD-03 | E5: MOD-04 | F5: MOD-05 | G5: MOD-06 | H5: MOD-07 | I5: MOD-08 | J5: Leitura
A6: Estratégia & Dados standalone | B6: ✓ | C6: — | D6: — | E6: — | F6: — | G6: — | H6: — | I6: ✓ | J6: Dados do cliente via INT-01..06; sem marketplaces.
A7: Gestão de pessoas completa | B7: ✓ | C7: ✓ | D7: Opcional (MVP+1) | E7: — | F7: — | G7: — | H7: — | I7: ✓ | J7: MOD-02 no MVP; MOD-03 em MVP+1.
A8: Empregabilidade | B8: ✓ | C8: — | D8: ✓ | E8: — | F8: — | G8: — | H8: Opcional | I8: — | J8: Formação + matching; MOD-07 apoia preparação.
A9: Fornecedores | B9: ✓ | C9: — | D9: — | E9: — | F9: ✓ | G9: — | H9: Opcional | I9: Opcional | J9: Match B2B; MOD-08 mede impacto.
A10: Universidade | B10: ✓ | C10: — | D10: ✓ | E10: — | F10: — | G10: ✓ | H10: Opcional | I10: Opcional | J10: MOD-06 Fase 2; MOD-03 amplia carreira.
A11: HUB Eventos | B11: ✓ | C11: — | D11: ✓ | E11: — | F11: ✓ | G11: — | H11: ✓ | I11: Opcional | J11: Orquestra talentos, fornecedores e ROI.
A12: Ecossistema completo | B12: ✓ | C12: ✓ | D12: ✓ | E12: ✓ | F12: ✓ | G12: ✓ | H12: ✓ | I12: ✓ | J12: Máxima inteligência de rede, com consentimento e governança.
A13: Piloto Monks (MVP) | B13: ✓ | C13: ✓ | D13: — | E13: ✓ | F13: — | G13: — | H13: — | I13: ✓ | J13: PIL-01..05; SCR-01..07; decisão Tecnica #3.
A14: Motor de dados + Performance (híbrido) | B14: ✓ | C14: ✓ | D14: — | E14: Opcional | F14: — | G14: — | H14: — | I14: ✓ | J14: Decisão Tecnica #3: híbrido.

Sheet 07_Base_Para_Precificacao
A1: BASE PARA A PRÓXIMA ETAPA DE PRECIFICAÇÃO
A3: Sem valores ainda: drivers que serão convertidos em horas, equipe, infraestrutura, licenças e custos recorrentes.
A5: Código | B5: Módulo | C5: Telas | D5: Complexas | E5: Integrações diretas | F5: IA/matching | G5: Dados/BI | H5: Mensageria | I5: Mobile | J5: Compliance | K5: Operação humana | L5: Observação
A6: CORE | B6: Core / Plataforma | C6: =COUNTIF('02_Inventario_Paginas'!$B$6:$B$200,A6) | D6: =COUNTIFS('02_Inventario_Paginas'!$B$6:$B$200,A6,'02_Inventario_Paginas'!$G$6:$G$200,"Alta")+COUNTIFS('02_Inventario_Paginas'!$B$6:$B$200,A6,'02_Inventario_Paginas'!$G$6:$G$200,"Muito alta") | E6: 7 | F6: Não | G6: Média | H6: Alta | I6: Sim | J6: Muito alta | K6: Média | L6: Infraestrutura transversal
A7: ED | B7: Estratégia & Dados | C7: =COUNTIF('02_Inventario_Paginas'!$B$6:$B$200,A7) | D7: =COUNTIFS('02_Inventario_Paginas'!$B$6:$B$200,A7,'02_Inventario_Paginas'!$G$6:$G$200,"Alta")+COUNTIFS('02_Inventario_Paginas'!$B$6:$B$200,A7,'02_Inventario_Paginas'!$G$6:$G$200,"Muito alta") | E7: 3 | F7: Alta | G7: Muito alta | H7: Baixa | I7: Não | J7: Alta | K7: Baixa | L7: Peso em dados, integrações e analytics
A8: COL | B8: Colaboradores / Meu Time | C8: =COUNTIF('02_Inventario_Paginas'!$B$6:$B$200,A8) | D8: =COUNTIFS('02_Inventario_Paginas'!$B$6:$B$200,A8,'02_Inventario_Paginas'!$G$6:$G$200,"Alta")+COUNTIFS('02_Inventario_Paginas'!$B$6:$B$200,A8,'02_Inventario_Paginas'!$G$6:$G$200,"Muito alta") | E8: 2 | F8: Média | G8: Alta | H8: Média | I8: Sim | J8: Alta | K8: Média | L8: Dados sensíveis e ciclos internos
A9: CAN | B9: Candidatos & Carreira | C9: =COUNTIF('02_Inventario_Paginas'!$B$6:$B$200,A9) | D9: =COUNTIFS('02_Inventario_Paginas'!$B$6:$B$200,A9,'02_Inventario_Paginas'!$G$6:$G$200,"Alta")+COUNTIFS('02_Inventario_Paginas'!$B$6:$B$200,A9,'02_Inventario_Paginas'!$G$6:$G$200,"Muito alta") | E9: 4 | F9: Muito alta | G9: Alta | H9: Alta | I9: Sim | J9: Alta | K9: Alta | L9: Marketplace, matching e alto volume
A10: FOR | B10: Fornecedores & Negócios | C10: =COUNTIF('02_Inventario_Paginas'!$B$6:$B$200,A10) | D10: =COUNTIFS('02_Inventario_Paginas'!$B$6:$B$200,A10,'02_Inventario_Paginas'!$G$6:$G$200,"Alta")+COUNTIFS('02_Inventario_Paginas'!$B$6:$B$200,A10,'02_Inventario_Paginas'!$G$6:$G$200,"Muito alta") | E10: 2 | F10: Muito alta | G10: Alta | H10: Alta | I10: Responsivo | J10: Alta | K10: Alta | L10: B2B, documentos e negociação
A11: ACA | B11: Acadêmico / Universidades | C11: =COUNTIF('02_Inventario_Paginas'!$B$6:$B$200,A11) | D11: =COUNTIFS('02_Inventario_Paginas'!$B$6:$B$200,A11,'02_Inventario_Paginas'!$G$6:$G$200,"Alta")+COUNTIFS('02_Inventario_Paginas'!$B$6:$B$200,A11,'02_Inventario_Paginas'!$G$6:$G$200,"Muito alta") | E11: 3 | F11: Alta | G11: Alta | H11: Média | I11: Sim | J11: Alta | K11: Média | L11: Entidades acadêmicas e matching
A12: EVT | B12: Eventos | C12: =COUNTIF('02_Inventario_Paginas'!$B$6:$B$200,A12) | D12: =COUNTIFS('02_Inventario_Paginas'!$B$6:$B$200,A12,'02_Inventario_Paginas'!$G$6:$G$200,"Alta")+COUNTIFS('02_Inventario_Paginas'!$B$6:$B$200,A12,'02_Inventario_Paginas'!$G$6:$G$200,"Muito alta") | E12: 5 | F12: Alta | G12: Muito alta | H12: Alta | I12: Sim | J12: Muito alta | K12: Muito alta | L12: Tempo real, pesquisa e operação
A13: COM | B13: Comunidades / Eu & Eu / Cultura | C13: =COUNTIF('02_Inventario_Paginas'!$B$6:$B$200,A13) | D13: =COUNTIFS('02_Inventario_Paginas'!$B$6:$B$200,A13,'02_Inventario_Paginas'!$G$6:$G$200,"Alta")+COUNTIFS('02_Inventario_Paginas'!$B$6:$B$200,A13,'02_Inventario_Paginas'!$G$6:$G$200,"Muito alta") | E13: 4 | F13: Média | G13: Média | H13: Alta | I13: Sim | J13: Alta | K13: Alta | L13: B2C e engajamento
A14: CUST | B14: Clientes & Receita | C14: =COUNTIF('02_Inventario_Paginas'!$B$6:$B$200,A14) | D14: =COUNTIFS('02_Inventario_Paginas'!$B$6:$B$200,A14,'02_Inventario_Paginas'!$G$6:$G$200,"Alta")+COUNTIFS('02_Inventario_Paginas'!$B$6:$B$200,A14,'02_Inventario_Paginas'!$G$6:$G$200,"Muito alta") | E14: 2 | F14: Alta | G14: Muito alta | H14: Baixa | I14: Não | J14: Alta | K14: Baixa | L14: CRM/NPS/churn; alimenta HUB Impact.

Sheet 08_Premissas_Custos
A1: PREMISSAS PARA DIMENSIONAMENTO DE CUSTO
A3: Premissas iniciais editáveis. Não são orçamento de fornecedor: servem para transformar as 111 telas do escopo em uma primeira ordem de grandeza e depois calibrar com cotações reais.
A5: Complexidade da tela | B5: Multiplicador | C5: Uso | E5: Premissa geral | F5: Valor
A6: Baixa | B6: 0.65 | C6: Tela simples / leitura / formulário básico | E6: Contingência desenvolvimento | F6: 0.15
A7: Média | B7: 1 | C7: Fluxo padrão | E7: Gestão/arquitetura sobre build | F7: 0.12
A8: Alta | B8: 1.55 | C8: Regras, integrações ou visualizações complexas | E8: Meses de construção | F8: 9
A9: Muito alta | B9: 2.2 | C9: Matching, analytics avançado, simulação ou lógica intensa | E9: Meses de operação/ano | F9: 12
E10: Fator Fase 2 vs. MVP | F10: 0.9
E11: Reuso parcial de tela | F11: 0.55
A12: Disciplina | B12: Horas base / tela média | C12: Rate R$/h | D12: Mensalidade base R$ | E12: Driver mensal | F12: Observação
A13: UX/UI | B13: 22 | C13: 180 | D13: 0 | E13: Build | F13: Pesquisa, fluxo, wireframe, design e handoff
A14: Front-end | B14: 48 | C14: 220 | D14: 0 | E14: Build | F14: Web responsivo; mobile dedicado é driver adicional
A15: Back-end | B15: 54 | C15: 240 | D15: 0 | E15: Build | F15: APIs, regras e persistência
A16: Dados/BI | B16: 18 | C16: 260 | D16: 0 | E16: Build | F16: Modelagem, indicadores e pipelines leves
A17: IA/Matching | B17: 10 | C17: 320 | D17: 0 | E17: Build | F17: Aplicado apenas quando a tela tem driver de IA
A18: QA | B18: 20 | C18: 170 | D18: 0 | E18: Build | F18: Testes funcionais, regressão e automação gradual
A19: DevOps | B19: 8 | C19: 260 | D19: 0 | E19: Build | F19: CI/CD, ambientes e observabilidade
A20: Segurança | B20: 6 | C20: 320 | D20: 0 | E20: Build | F20: Threat modeling, hardening e revisão
A23: Custo mensal recorrente | B23: Base R$/mês | C23: Escala | D23: Observação
A24: Cloud / infraestrutura | B24: 18000 | C24: 1 | D24: Ambientes, banco, storage, observabilidade; recalibrar por volume
A25: Dados / pipelines / BI | B25: 14000 | C25: 1 | D25: Orquestração, processamento e monitoramento
A26: IA / modelos / APIs | B26: 12000 | C26: 1 | D26: Uso variável; depende de volume e arquitetura
A27: DevOps / SRE | B27: 22000 | C27: 1 | D27: Sustentação de plataforma
A28: Segurança / compliance | B28: 14000 | C28: 1 | D28: Monitoramento, scans, LGPD e auditoria
A29: QA / releases | B29: 16000 | C29: 1 | D29: Regressão e qualidade contínua
A30: Produto / operação técnica | B30: 28000 | C30: 1 | D30: Gestão de backlog, incidentes e evolução
A31: Suporte / CS técnico | B31: 18000 | C31: 1 | D31: Atendimento B2B e operação
A33: MVP+1: custo integral (fator 1, como MVP) — escopo near-term alinhado à Tecnica. Desconto de 0,9 aplica-se apenas a Fase 2. | E33: Fase Tecnica | F33: MVP / MVP+1 / Fase 2 + roadmap F0/MVP1..3

Sheet 09_Estimativa_96_Telas
A1: ESTIMATIVA DE BUILD POR TELA — 111 TELAS
A3: Horas são calculadas a partir da complexidade, disciplina e drivers específicos. A coluna 'Componente compartilhado' evita duplicar custo quando a mesma capacidade é reutilizada entre verticais.
A5: ID | B5: Código | C5: Frente | D5: Tela | E5: Fase | F5: Complexidade | G5: Componente compartilhado | H5: Reuso % | I5: Driver IA | J5: Driver Dados | K5: Driver Segurança | L5: Driver Mobile | M5: Mult. complex. | N5: UX h | O5: Front h | P5: Back h | Q5: Dados h | R5: IA h | S5: QA h | T5: DevOps h | U5: Segurança h | V5: Horas brutas | W5: Horas líquidas | X5: Custo build R$ | Y5: Gestão/arquitetura R$ | Z5: Contingência R$ | AA5: CAPEX tela R$ | AB5: Observação
A6: 1 | B6: CORE | C6: Core / Plataforma | D6: Login / SSO | E6: MVP | F6: Baixa | G6: CORE compartilhado | H6: 0.8 | I6: Não | J6: Não | K6: Sim | L6: Não | M6: =IF(F6="Baixa",'08_Premissas_Custos'!$B$6,IF(F6="Média",'08_Premissas_Custos'!$B$7,IF(F6="Alta",'08_Premissas_Custos'!$B$8,'08_Premissas_Custos'!$B$9))) | N6: ='08_Premissas_Custos'!$B$13*M6 | O6: ='08_Premissas_Custos'!$B$14*M6*(1+IF(L6="Sim",0.25,0)) | P6: ='08_Premissas_Custos'!$B$15*M6*(1+IF(I6="Sim",0.20,0)+IF(K6="Sim",0.15,0)) | Q6: ='08_Premissas_Custos'!$B$16*M6*IF(J6="Sim",1.6,0.55) | R6: ='08_Premissas_Custos'!$B$17*M6*IF(I6="Sim",1.8,0.15) | S6: ='08_Premissas_Custos'!$B$18*M6*(1+IF(I6="Sim",0.15)+IF(L6="Sim",0.10)) | T6: ='08_Premissas_Custos'!$B$19*M6*(1+IF(J6="Sim",0.15)) | U6: ='08_Premissas_Custos'!$B$20*M6*IF(K6="Sim",1.8,0.7) | V6: =SUM(N6:U6) | W6: =V6*(1-H6)*IF(E6="Fase 2",'08_Premissas_Custos'!$F$10,1) | X6: =(N6*'08_Premissas_Custos'!$C$13+O6*'08_Premissas_Custos'!$C$14+P6*'08_Premissas_Custos'!$C$15+Q6*'08_Premissas_Custos'!$C$16+R6*'08_Premissas_Custos'!$C$17+S6*'08_Premissas_Custos'!$C$18+T6*'08_Premissas_Custos'!$C$19+U6*'08_Premissas_Custos'!$C$20)*(1-H6)*IF(E6="Fase 2",'08_Premissas_Custos'!$F$10,1) | Y6: =X6*'08_Premissas_Custos'!$F$7 | Z6: =(X6+Y6)*'08_Premissas_Custos'!$F$6 | AA6: =SUM(X6:Z6) | AB6: Autenticação
A7: 2 | B7: CORE | C7: Core / Plataforma | D7: Cadastro / onboarding | E7: MVP | F7: Média | G7: CORE compartilhado | H7: 0.8 | I7: Não | J7: Não | K7: Sim | L7: Sim | M7: =IF(F7="Baixa",'08_Premissas_Custos'!$B$6,IF(F7="Média",'08_Premissas_Custos'!$B$7,IF(F7="Alta",'08_Premissas_Custos'!$B$8,'08_Premissas_Custos'!$B$9))) | N7: ='08_Premissas_Custos'!$B$13*M7 | O7: ='08_Premissas_Custos'!$B$14*M7*(1+IF(L7="Sim",0.25,0)) | P7: ='08_Premissas_Custos'!$B$15*M7*(1+IF(I7="Sim",0.20,0)+IF(K7="Sim",0.15,0)) | Q7: ='08_Premissas_Custos'!$B$16*M7*IF(J7="Sim",1.6,0.55) | R7: ='08_Premissas_Custos'!$B$17*M7*IF(I7="Sim",1.8,0.15) | S7: ='08_Premissas_Custos'!$B$18*M7*(1+IF(I7="Sim",0.15)+IF(L7="Sim",0.10)) | T7: ='08_Premissas_Custos'!$B$19*M7*(1+IF(J7="Sim",0.15)) | U7: ='08_Premissas_Custos'!$B$20*M7*IF(K7="Sim",1.8,0.7) | V7: =SUM(N7:U7) | W7: =V7*(1-H7)*IF(E7="Fase 2",'08_Premissas_Custos'!$F$10,1) | X7: =(N7*'08_Premissas_Custos'!$C$13+O7*'08_Premissas_Custos'!$C$14+P7*'08_Premissas_Custos'!$C$15+Q7*'08_Premissas_Custos'!$C$16+R7*'08_Premissas_Custos'!$C$17+S7*'08_Premissas_Custos'!$C$18+T7*'08_Premissas_Custos'!$C$19+U7*'08_Premissas_Custos'!$C$20)*(1-H7)*IF(E7="Fase 2",'08_Premissas_Custos'!$F$10,1) | Y7: =X7*'08_Premissas_Custos'!$F$7 | Z7: =(X7+Y7)*'08_Premissas_Custos'!$F$6 | AA7: =SUM(X7:Z7) | AB7: Entrada por tipo
A8: 3 | B8: CORE | C8: Core / Plataforma | D8: Perfis e organizações | E8: MVP | F8: Média | G8: CORE compartilhado | H8: 0.8 | I8: Não | J8: Não | K8: Sim | L8: Não | M8: =IF(F8="Baixa",'08_Premissas_Custos'!$B$6,IF(F8="Média",'08_Premissas_Custos'!$B$7,IF(F8="Alta",'08_Premissas_Custos'!$B$8,'08_Premissas_Custos'!$B$9))) | N8: ='08_Premissas_Custos'!$B$13*M8 | O8: ='08_Premissas_Custos'!$B$14*M8*(1+IF(L8="Sim",0.25,0)) | P8: ='08_Premissas_Custos'!$B$15*M8*(1+IF(I8="Sim",0.20,0)+IF(K8="Sim",0.15,0)) | Q8: ='08_Premissas_Custos'!$B$16*M8*IF(J8="Sim",1.6,0.55) | R8: ='08_Premissas_Custos'!$B$17*M8*IF(I8="Sim",1.8,0.15) | S8: ='08_Premissas_Custos'!$B$18*M8*(1+IF(I8="Sim",0.15)+IF(L8="Sim",0.10)) | T8: ='08_Premissas_Custos'!$B$19*M8*(1+IF(J8="Sim",0.15)) | U8: ='08_Premissas_Custos'!$B$20*M8*IF(K8="Sim",1.8,0.7) | V8: =SUM(N8:U8) | W8: =V8*(1-H8)*IF(E8="Fase 2",'08_Premissas_Custos'!$F$10,1) | X8: =(N8*'08_Premissas_Custos'!$C$13+O8*'08_Premissas_Custos'!$C$14+P8*'08_Premissas_Custos'!$C$15+Q8*'08_Premissas_Custos'!$C$16+R8*'08_Premissas_Custos'!$C$17+S8*'08_Premissas_Custos'!$C$18+T8*'08_Premissas_Custos'!$C$19+U8*'08_Premissas_Custos'!$C$20)*(1-H8)*IF(E8="Fase 2",'08_Premissas_Custos'!$F$10,1) | Y8: =X8*'08_Premissas_Custos'!$F$7 | Z8: =(X8+Y8)*'08_Premissas_Custos'!$F$6 | AA8: =SUM(X8:Z8) | AB8: Entidades
A9: 4 | B9: CORE | C9: Core / Plataforma | D9: Papéis e permissões | E9: MVP | F9: Alta | G9: CORE compartilhado | H9: 0.8 | I9: Não | J9: Não | K9: Sim | L9: Não | M9: =IF(F9="Baixa",'08_Premissas_Custos'!$B$6,IF(F9="Média",'08_Premissas_Custos'!$B$7,IF(F9="Alta",'08_Premissas_Custos'!$B$8,'08_Premissas_Custos'!$B$9))) | N9: ='08_Premissas_Custos'!$B$13*M9 | O9: ='08_Premissas_Custos'!$B$14*M9*(1+IF(L9="Sim",0.25,0)) | P9: ='08_Premissas_Custos'!$B$15*M9*(1+IF(I9="Sim",0.20,0)+IF(K9="Sim",0.15,0)) | Q9: ='08_Premissas_Custos'!$B$16*M9*IF(J9="Sim",1.6,0.55) | R9: ='08_Premissas_Custos'!$B$17*M9*IF(I9="Sim",1.8,0.15) | S9: ='08_Premissas_Custos'!$B$18*M9*(1+IF(I9="Sim",0.15)+IF(L9="Sim",0.10)) | T9: ='08_Premissas_Custos'!$B$19*M9*(1+IF(J9="Sim",0.15)) | U9: ='08_Premissas_Custos'!$B$20*M9*IF(K9="Sim",1.8,0.7) | V9: =SUM(N9:U9) | W9: =V9*(1-H9)*IF(E9="Fase 2",'08_Premissas_Custos'!$F$10,1) | X9: =(N9*'08_Premissas_Custos'!$C$13+O9*'08_Premissas_Custos'!$C$14+P9*'08_Premissas_Custos'!$C$15+Q9*'08_Premissas_Custos'!$C$16+R9*'08_Premissas_Custos'!$C$17+S9*'08_Premissas_Custos'!$C$18+T9*'08_Premissas_Custos'!$C$19+U9*'08_Premissas_Custos'!$C$20)*(1-H9)*IF(E9="Fase 2",'08_Premissas_Custos'!$F$10,1) | Y9: =X9*'08_Premissas_Custos'!$F$7 | Z9: =(X9+Y9)*'08_Premissas_Custos'!$F$6 | AA9: =SUM(X9:Z9) | AB9: RBAC
A10: 5 | B10: CORE | C10: Core / Plataforma | D10: Consentimentos / LGPD | E10: MVP | F10: Alta | G10: CORE compartilhado | H10: 0.8 | I10: Não | J10: Não | K10: Sim | L10: Não | M10: =IF(F10="Baixa",'08_Premissas_Custos'!$B$6,IF(F10="Média",'08_Premissas_Custos'!$B$7,IF(F10="Alta",'08_Premissas_Custos'!$B$8,'08_Premissas_Custos'!$B$9))) | N10: ='08_Premissas_Custos'!$B$13*M10 | O10: ='08_Premissas_Custos'!$B$14*M10*(1+IF(L10="Sim",0.25,0)) | P10: ='08_Premissas_Custos'!$B$15*M10*(1+IF(I10="Sim",0.20,0)+IF(K10="Sim",0.15,0)) | Q10: ='08_Premissas_Custos'!$B$16*M10*IF(J10="Sim",1.6,0.55) | R10: ='08_Premissas_Custos'!$B$17*M10*IF(I10="Sim",1.8,0.15) | S10: ='08_Premissas_Custos'!$B$18*M10*(1+IF(I10="Sim",0.15)+IF(L10="Sim",0.10)) | T10: ='08_Premissas_Custos'!$B$19*M10*(1+IF(J10="Sim",0.15)) | U10: ='08_Premissas_Custos'!$B$20*M10*IF(K10="Sim",1.8,0.7) | V10: =SUM(N10:U10) | W10: =V10*(1-H10)*IF(E10="Fase 2",'08_Premissas_Custos'!$F$10,1) | X10: =(N10*'08_Premissas_Custos'!$C$13+O10*'08_Premissas_Custos'!$C$14+P10*'08_Premissas_Custos'!$C$15+Q10*'08_Premissas_Custos'!$C$16+R10*'08_Premissas_Custos'!$C$17+S10*'08_Premissas_Custos'!$C$18+T10*'08_Premissas_Custos'!$C$19+U10*'08_Premissas_Custos'!$C$20)*(1-H10)*IF(E10="Fase 2",'08_Premissas_Custos'!$F$10,1) | Y10: =X10*'08_Premissas_Custos'!$F$7 | Z10: =(X10+Y10)*'08_Premissas_Custos'!$F$6 | AA10: =SUM(X10:Z10) | AB10: Privacidade
A11: 6 | B11: CORE | C11: Core / Plataforma | D11: Central de integrações | E11: MVP | F11: Alta | G11: CORE compartilhado | H11: 0.8 | I11: Não | J11: Não | K11: Sim | L11: Não | M11: =IF(F11="Baixa",'08_Premissas_Custos'!$B$6,IF(F11="Média",'08_Premissas_Custos'!$B$7,IF(F11="Alta",'08_Premissas_Custos'!$B$8,'08_Premissas_Custos'!$B$9))) | N11: ='08_Premissas_Custos'!$B$13*M11 | O11: ='08_Premissas_Custos'!$B$14*M11*(1+IF(L11="Sim",0.25,0)) | P11: ='08_Premissas_Custos'!$B$15*M11*(1+IF(I11="Sim",0.20,0)+IF(K11="Sim",0.15,0)) | Q11: ='08_Premissas_Custos'!$B$16*M11*IF(J11="Sim",1.6,0.55) | R11: ='08_Premissas_Custos'!$B$17*M11*IF(I11="Sim",1.8,0.15) | S11: ='08_Premissas_Custos'!$B$18*M11*(1+IF(I11="Sim",0.15)+IF(L11="Sim",0.10)) | T11: ='08_Premissas_Custos'!$B$19*M11*(1+IF(J11="Sim",0.15)) | U11: ='08_Premissas_Custos'!$B$20*M11*IF(K11="Sim",1.8,0.7) | V11: =SUM(N11:U11) | W11: =V11*(1-H11)*IF(E11="Fase 2",'08_Premissas_Custos'!$F$10,1) | X11: =(N11*'08_Premissas_Custos'!$C$13+O11*'08_Premissas_Custos'!$C$14+P11*'08_Premissas_Custos'!$C$15+Q11*'08_Premissas_Custos'!$C$16+R11*'08_Premissas_Custos'!$C$17+S11*'08_Premissas_Custos'!$C$18+T11*'08_Premissas_Custos'!$C$19+U11*'08_Premissas_Custos'!$C$20)*(1-H11)*IF(E11="Fase 2",'08_Premissas_Custos'!$F$10,1) | Y11: =X11*'08_Premissas_Custos'!$F$7 | Z11: =(X11+Y11)*'08_Premissas_Custos'!$F$6 | AA11: =SUM(X11:Z11) | AB11: APIs/RHIS/ERP/CRM/LMS
A12: 7 | B12: CORE | C12: Core / Plataforma | D12: Notificações | E12: MVP | F12: Média | G12: CORE compartilhado | H12: 0.8 | I12: Não | J12: Não | K12: Sim | L12: Sim | M12: =IF(F12="Baixa",'08_Premissas_Custos'!$B$6,IF(F12="Média",'08_Premissas_Custos'!$B$7,IF(F12="Alta",'08_Premissas_Custos'!$B$8,'08_Premissas_Custos'!$B$9))) | N12: ='08_Premissas_Custos'!$B$13*M12 | O12: ='08_Premissas_Custos'!$B$14*M12*(1+IF(L12="Sim",0.25,0)) | P12: ='08_Premissas_Custos'!$B$15*M12*(1+IF(I12="Sim",0.20,0)+IF(K12="Sim",0.15,0)) | Q12: ='08_Premissas_Custos'!$B$16*M12*IF(J12="Sim",1.6,0.55) | R12: ='08_Premissas_Custos'!$B$17*M12*IF(I12="Sim",1.8,0.15) | S12: ='08_Premissas_Custos'!$B$18*M12*(1+IF(I12="Sim",0.15)+IF(L12="Sim",0.10)) | T12: ='08_Premissas_Custos'!$B$19*M12*(1+IF(J12="Sim",0.15)) | U12: ='08_Premissas_Custos'!$B$20*M12*IF(K12="Sim",1.8,0.7) | V12: =SUM(N12:U12) | W12: =V12*(1-H12)*IF(E12="Fase 2",'08_Premissas_Custos'!$F$10,1) | X12: =(N12*'08_Premissas_Custos'!$C$13+O12*'08_Premissas_Custos'!$C$14+P12*'08_Premissas_Custos'!$C$15+Q12*'08_Premissas_Custos'!$C$16+R12*'08_Premissas_Custos'!$C$17+S12*'08_Premissas_Custos'!$C$18+T12*'08_Premissas_Custos'!$C$19+U12*'08_Premissas_Custos'!$C$20)*(1-H12)*IF(E12="Fase 2",'08_Premissas_Custos'!$F$10,1) | Y12: =X12*'08_Premissas_Custos'!$F$7 | Z12: =(X12+Y12)*'08_Premissas_Custos'!$F$6 | AA12: =SUM(X12:Z12) | AB12: Gatilhos
A13: 8 | B13: CORE | C13: Core / Plataforma | D13: Mensagens | E13: Fase 2 | F13: Alta | G13: CORE compartilhado | H13: 0.8 | I13: Não | J13: Não | K13: Sim | L13: Sim | M13: =IF(F13="Baixa",'08_Premissas_Custos'!$B$6,IF(F13="Média",'08_Premissas_Custos'!$B$7,IF(F13="Alta",'08_Premissas_Custos'!$B$8,'08_Premissas_Custos'!$B$9))) | N13: ='08_Premissas_Custos'!$B$13*M13 | O13: ='08_Premissas_Custos'!$B$14*M13*(1+IF(L13="Sim",0.25,0)) | P13: ='08_Premissas_Custos'!$B$15*M13*(1+IF(I13="Sim",0.20,0)+IF(K13="Sim",0.15,0)) | Q13: ='08_Premissas_Custos'!$B$16*M13*IF(J13="Sim",1.6,0.55) | R13: ='08_Premissas_Custos'!$B$17*M13*IF(I13="Sim",1.8,0.15) | S13: ='08_Premissas_Custos'!$B$18*M13*(1+IF(I13="Sim",0.15)+IF(L13="Sim",0.10)) | T13: ='08_Premissas_Custos'!$B$19*M13*(1+IF(J13="Sim",0.15)) | U13: ='08_Premissas_Custos'!$B$20*M13*IF(K13="Sim",1.8,0.7) | V13: =SUM(N13:U13) | W13: =V13*(1-H13)*IF(E13="Fase 2",'08_Premissas_Custos'!$F$10,1) | X13: =(N13*'08_Premissas_Custos'!$C$13+O13*'08_Premissas_Custos'!$C$14+P13*'08_Premissas_Custos'!$C$15+Q13*'08_Premissas_Custos'!$C$16+R13*'08_Premissas_Custos'!$C$17+S13*'08_Premissas_Custos'!$C$18+T13*'08_Premissas_Custos'!$C$19+U13*'08_Premissas_Custos'!$C$20)*(1-H13)*IF(E13="Fase 2",'08_Premissas_Custos'!$F$10,1) | Y13: =X13*'08_Premissas_Custos'!$F$7 | Z13: =(X13+Y13)*'08_Premissas_Custos'!$F$6 | AA13: =SUM(X13:Z13) | AB13: Conversas
A14: 9 | B14: CORE | C14: Core / Plataforma | D14: Busca global | E14: Fase 2 | F14: Média | G14: CORE compartilhado | H14: 0.8 | I14: Não | J14: Não | K14: Sim | L14: Não | M14: =IF(F14="Baixa",'08_Premissas_Custos'!$B$6,IF(F14="Média",'08_Premissas_Custos'!$B$7,IF(F14="Alta",'08_Premissas_Custos'!$B$8,'08_Premissas_Custos'!$B$9))) | N14: ='08_Premissas_Custos'!$B$13*M14 | O14: ='08_Premissas_Custos'!$B$14*M14*(1+IF(L14="Sim",0.25,0)) | P14: ='08_Premissas_Custos'!$B$15*M14*(1+IF(I14="Sim",0.20,0)+IF(K14="Sim",0.15,0)) | Q14: ='08_Premissas_Custos'!$B$16*M14*IF(J14="Sim",1.6,0.55) | R14: ='08_Premissas_Custos'!$B$17*M14*IF(I14="Sim",1.8,0.15) | S14: ='08_Premissas_Custos'!$B$18*M14*(1+IF(I14="Sim",0.15)+IF(L14="Sim",0.10)) | T14: ='08_Premissas_Custos'!$B$19*M14*(1+IF(J14="Sim",0.15)) | U14: ='08_Premissas_Custos'!$B$20*M14*IF(K14="Sim",1.8,0.7) | V14: =SUM(N14:U14) | W14: =V14*(1-H14)*IF(E14="Fase 2",'08_Premissas_Custos'!$F$10,1) | X14: =(N14*'08_Premissas_Custos'!$C$13+O14*'08_Premissas_Custos'!$C$14+P14*'08_Premissas_Custos'!$C$15+Q14*'08_Premissas_Custos'!$C$16+R14*'08_Premissas_Custos'!$C$17+S14*'08_Premissas_Custos'!$C$18+T14*'08_Premissas_Custos'!$C$19+U14*'08_Premissas_Custos'!$C$20)*(1-H14)*IF(E14="Fase 2",'08_Premissas_Custos'!$F$10,1) | Y14: =X14*'08_Premissas_Custos'!$F$7 | Z14: =(X14+Y14)*'08_Premissas_Custos'!$F$6 | AA14: =SUM(X14:Z14) | AB14: Busca
A15: 10 | B15: CORE | C15: Core / Plataforma | D15: Analytics de uso | E15: MVP | F15: Média | G15: CORE compartilhado | H15: 0.8 | I15: Não | J15: Sim | K15: Sim | L15: Não | M15: =IF(F15="Baixa",'08_Premissas_Custos'!$B$6,IF(F15="Média",'08_Premissas_Custos'!$B$7,IF(F15="Alta",'08_Premissas_Custos'!$B$8,'08_Premissas_Custos'!$B$9))) | N15: ='08_Premissas_Custos'!$B$13*M15 | O15: ='08_Premissas_Custos'!$B$14*M15*(1+IF(L15="Sim",0.25,0)) | P15: ='08_Premissas_Custos'!$B$15*M15*(1+IF(I15="Sim",0.20,0)+IF(K15="Sim",0.15,0)) | Q15: ='08_Premissas_Custos'!$B$16*M15*IF(J15="Sim",1.6,0.55) | R15: ='08_Premissas_Custos'!$B$17*M15*IF(I15="Sim",1.8,0.15) | S15: ='08_Premissas_Custos'!$B$18*M15*(1+IF(I15="Sim",0.15)+IF(L15="Sim",0.10)) | T15: ='08_Premissas_Custos'!$B$19*M15*(1+IF(J15="Sim",0.15)) | U15: ='08_Premissas_Custos'!$B$20*M15*IF(K15="Sim",1.8,0.7) | V15: =SUM(N15:U15) | W15: =V15*(1-H15)*IF(E15="Fase 2",'08_Premissas_Custos'!$F$10,1) | X15: =(N15*'08_Premissas_Custos'!$C$13+O15*'08_Premissas_Custos'!$C$14+P15*'08_Premissas_Custos'!$C$15+Q15*'08_Premissas_Custos'!$C$16+R15*'08_Premissas_Custos'!$C$17+S15*'08_Premissas_Custos'!$C$18+T15*'08_Premissas_Custos'!$C$19+U15*'08_Premissas_Custos'!$C$20)*(1-H15)*IF(E15="Fase 2",'08_Premissas_Custos'!$F$10,1) | Y15: =X15*'08_Premissas_Custos'!$F$7 | Z15: =(X15+Y15)*'08_Premissas_Custos'!$F$6 | AA15: =SUM(X15:Z15) | AB15: Adoção
A16: 11 | B16: CORE | C16: Core / Plataforma | D16: Administração | E16: MVP | F16: Alta | G16: CORE compartilhado | H16: 0.8 | I16: Não | J16: Não | K16: Sim | L16: Não | M16: =IF(F16="Baixa",'08_Premissas_Custos'!$B$6,IF(F16="Média",'08_Premissas_Custos'!$B$7,IF(F16="Alta",'08_Premissas_Custos'!$B$8,'08_Premissas_Custos'!$B$9))) | N16: ='08_Premissas_Custos'!$B$13*M16 | O16: ='08_Premissas_Custos'!$B$14*M16*(1+IF(L16="Sim",0.25,0)) | P16: ='08_Premissas_Custos'!$B$15*M16*(1+IF(I16="Sim",0.20,0)+IF(K16="Sim",0.15,0)) | Q16: ='08_Premissas_Custos'!$B$16*M16*IF(J16="Sim",1.6,0.55) | R16: ='08_Premissas_Custos'!$B$17*M16*IF(I16="Sim",1.8,0.15) | S16: ='08_Premissas_Custos'!$B$18*M16*(1+IF(I16="Sim",0.15)+IF(L16="Sim",0.10)) | T16: ='08_Premissas_Custos'!$B$19*M16*(1+IF(J16="Sim",0.15)) | U16: ='08_Premissas_Custos'!$B$20*M16*IF(K16="Sim",1.8,0.7) | V16: =SUM(N16:U16) | W16: =V16*(1-H16)*IF(E16="Fase 2",'08_Premissas_Custos'!$F$10,1) | X16: =(N16*'08_Premissas_Custos'!$C$13+O16*'08_Premissas_Custos'!$C$14+P16*'08_Premissas_Custos'!$C$15+Q16*'08_Premissas_Custos'!$C$16+R16*'08_Premissas_Custos'!$C$17+S16*'08_Premissas_Custos'!$C$18+T16*'08_Premissas_Custos'!$C$19+U16*'08_Premissas_Custos'!$C$20)*(1-H16)*IF(E16="Fase 2",'08_Premissas_Custos'!$F$10,1) | Y16: =X16*'08_Premissas_Custos'!$F$7 | Z16: =(X16+Y16)*'08_Premissas_Custos'!$F$6 | AA16: =SUM(X16:Z16) | AB16: Configurações
A17: 12 | B17: CORE | C17: Core / Plataforma | D17: Auditoria e logs | E17: MVP | F17: Alta | G17: CORE compartilhado | H17: 0.8 | I17: Não | J17: Não | K17: Sim | L17: Não | M17: =IF(F17="Baixa",'08_Premissas_Custos'!$B$6,IF(F17="Média",'08_Premissas_Custos'!$B$7,IF(F17="Alta",'08_Premissas_Custos'!$B$8,'08_Premissas_Custos'!$B$9))) | N17: ='08_Premissas_Custos'!$B$13*M17 | O17: ='08_Premissas_Custos'!$B$14*M17*(1+IF(L17="Sim",0.25,0)) | P17: ='08_Premissas_Custos'!$B$15*M17*(1+IF(I17="Sim",0.20,0)+IF(K17="Sim",0.15,0)) | Q17: ='08_Premissas_Custos'!$B$16*M17*IF(J17="Sim",1.6,0.55) | R17: ='08_Premissas_Custos'!$B$17*M17*IF(I17="Sim",1.8,0.15) | S17: ='08_Premissas_Custos'!$B$18*M17*(1+IF(I17="Sim",0.15)+IF(L17="Sim",0.10)) | T17: ='08_Premissas_Custos'!$B$19*M17*(1+IF(J17="Sim",0.15)) | U17: ='08_Premissas_Custos'!$B$20*M17*IF(K17="Sim",1.8,0.7) | V17: =SUM(N17:U17) | W17: =V17*(1-H17)*IF(E17="Fase 2",'08_Premissas_Custos'!$F$10,1) | X17: =(N17*'08_Premissas_Custos'!$C$13+O17*'08_Premissas_Custos'!$C$14+P17*'08_Premissas_Custos'!$C$15+Q17*'08_Premissas_Custos'!$C$16+R17*'08_Premissas_Custos'!$C$17+S17*'08_Premissas_Custos'!$C$18+T17*'08_Premissas_Custos'!$C$19+U17*'08_Premissas_Custos'!$C$20)*(1-H17)*IF(E17="Fase 2",'08_Premissas_Custos'!$F$10,1) | Y17: =X17*'08_Premissas_Custos'!$F$7 | Z17: =(X17+Y17)*'08_Premissas_Custos'!$F$6 | AA17: =SUM(X17:Z17) | AB17: Rastreabilidade
A18: 13 | B18: ED | C18: Estratégia & Dados | D18: Visão executiva | E18: MVP | F18: Alta | H18: 0 | I18: Não | J18: Sim | K18: Não | L18: Não | M18: =IF(F18="Baixa",'08_Premissas_Custos'!$B$6,IF(F18="Média",'08_Premissas_Custos'!$B$7,IF(F18="Alta",'08_Premissas_Custos'!$B$8,'08_Premissas_Custos'!$B$9))) | N18: ='08_Premissas_Custos'!$B$13*M18 | O18: ='08_Premissas_Custos'!$B$14*M18*(1+IF(L18="Sim",0.25,0)) | P18: ='08_Premissas_Custos'!$B$15*M18*(1+IF(I18="Sim",0.20,0)+IF(K18="Sim",0.15,0)) | Q18: ='08_Premissas_Custos'!$B$16*M18*IF(J18="Sim",1.6,0.55) | R18: ='08_Premissas_Custos'!$B$17*M18*IF(I18="Sim",1.8,0.15) | S18: ='08_Premissas_Custos'!$B$18*M18*(1+IF(I18="Sim",0.15)+IF(L18="Sim",0.10)) | T18: ='08_Premissas_Custos'!$B$19*M18*(1+IF(J18="Sim",0.15)) | U18: ='08_Premissas_Custos'!$B$20*M18*IF(K18="Sim",1.8,0.7) | V18: =SUM(N18:U18) | W18: =V18*(1-H18)*IF(E18="Fase 2",'08_Premissas_Custos'!$F$10,1) | X18: =(N18*'08_Premissas_Custos'!$C$13+O18*'08_Premissas_Custos'!$C$14+P18*'08_Premissas_Custos'!$C$15+Q18*'08_Premissas_Custos'!$C$16+R18*'08_Premissas_Custos'!$C$17+S18*'08_Premissas_Custos'!$C$18+T18*'08_Premissas_Custos'!$C$19+U18*'08_Premissas_Custos'!$C$20)*(1-H18)*IF(E18="Fase 2",'08_Premissas_Custos'!$F$10,1) | Y18: =X18*'08_Premissas_Custos'!$F$7 | Z18: =(X18+Y18)*'08_Premissas_Custos'!$F$6 | AA18: =SUM(X18:Z18) | AB18: KPIs pessoas x negócio
A19: 14 | B19: ED | C19: Estratégia & Dados | D19: Conectores de dados | E19: MVP | F19: Alta | H19: 0 | I19: Não | J19: Sim | K19: Não | L19: Não | M19: =IF(F19="Baixa",'08_Premissas_Custos'!$B$6,IF(F19="Média",'08_Premissas_Custos'!$B$7,IF(F19="Alta",'08_Premissas_Custos'!$B$8,'08_Premissas_Custos'!$B$9))) | N19: ='08_Premissas_Custos'!$B$13*M19 | O19: ='08_Premissas_Custos'!$B$14*M19*(1+IF(L19="Sim",0.25,0)) | P19: ='08_Premissas_Custos'!$B$15*M19*(1+IF(I19="Sim",0.20,0)+IF(K19="Sim",0.15,0)) | Q19: ='08_Premissas_Custos'!$B$16*M19*IF(J19="Sim",1.6,0.55) | R19: ='08_Premissas_Custos'!$B$17*M19*IF(I19="Sim",1.8,0.15) | S19: ='08_Premissas_Custos'!$B$18*M19*(1+IF(I19="Sim",0.15)+IF(L19="Sim",0.10)) | T19: ='08_Premissas_Custos'!$B$19*M19*(1+IF(J19="Sim",0.15)) | U19: ='08_Premissas_Custos'!$B$20*M19*IF(K19="Sim",1.8,0.7) | V19: =SUM(N19:U19) | W19: =V19*(1-H19)*IF(E19="Fase 2",'08_Premissas_Custos'!$F$10,1) | X19: =(N19*'08_Premissas_Custos'!$C$13+O19*'08_Premissas_Custos'!$C$14+P19*'08_Premissas_Custos'!$C$15+Q19*'08_Premissas_Custos'!$C$16+R19*'08_Premissas_Custos'!$C$17+S19*'08_Premissas_Custos'!$C$18+T19*'08_Premissas_Custos'!$C$19+U19*'08_Premissas_Custos'!$C$20)*(1-H19)*IF(E19="Fase 2",'08_Premissas_Custos'!$F$10,1) | Y19: =X19*'08_Premissas_Custos'!$F$7 | Z19: =(X19+Y19)*'08_Premissas_Custos'!$F$6 | AA19: =SUM(X19:Z19) | AB19: Dados existentes
A20: 15 | B20: ED | C20: Estratégia & Dados | D20: Mapeamento de indicadores | E20: MVP | F20: Alta | H20: 0 | I20: Não | J20: Sim | K20: Não | L20: Não | M20: =IF(F20="Baixa",'08_Premissas_Custos'!$B$6,IF(F20="Média",'08_Premissas_Custos'!$B$7,IF(F20="Alta",'08_Premissas_Custos'!$B$8,'08_Premissas_Custos'!$B$9))) | N20: ='08_Premissas_Custos'!$B$13*M20 | O20: ='08_Premissas_Custos'!$B$14*M20*(1+IF(L20="Sim",0.25,0)) | P20: ='08_Premissas_Custos'!$B$15*M20*(1+IF(I20="Sim",0.20,0)+IF(K20="Sim",0.15,0)) | Q20: ='08_Premissas_Custos'!$B$16*M20*IF(J20="Sim",1.6,0.55) | R20: ='08_Premissas_Custos'!$B$17*M20*IF(I20="Sim",1.8,0.15) | S20: ='08_Premissas_Custos'!$B$18*M20*(1+IF(I20="Sim",0.15)+IF(L20="Sim",0.10)) | T20: ='08_Premissas_Custos'!$B$19*M20*(1+IF(J20="Sim",0.15)) | U20: ='08_Premissas_Custos'!$B$20*M20*IF(K20="Sim",1.8,0.7) | V20: =SUM(N20:U20) | W20: =V20*(1-H20)*IF(E20="Fase 2",'08_Premissas_Custos'!$F$10,1) | X20: =(N20*'08_Premissas_Custos'!$C$13+O20*'08_Premissas_Custos'!$C$14+P20*'08_Premissas_Custos'!$C$15+Q20*'08_Premissas_Custos'!$C$16+R20*'08_Premissas_Custos'!$C$17+S20*'08_Premissas_Custos'!$C$18+T20*'08_Premissas_Custos'!$C$19+U20*'08_Premissas_Custos'!$C$20)*(1-H20)*IF(E20="Fase 2",'08_Premissas_Custos'!$F$10,1) | Y20: =X20*'08_Premissas_Custos'!$F$7 | Z20: =(X20+Y20)*'08_Premissas_Custos'!$F$6 | AA20: =SUM(X20:Z20) | AB20: Dicionário
A21: 16 | B21: ED | C21: Estratégia & Dados | D21: Diagnóstico | E21: MVP | F21: Alta | H21: 0 | I21: Não | J21: Sim | K21: Não | L21: Não | M21: =IF(F21="Baixa",'08_Premissas_Custos'!$B$6,IF(F21="Média",'08_Premissas_Custos'!$B$7,IF(F21="Alta",'08_Premissas_Custos'!$B$8,'08_Premissas_Custos'!$B$9))) | N21: ='08_Premissas_Custos'!$B$13*M21 | O21: ='08_Premissas_Custos'!$B$14*M21*(1+IF(L21="Sim",0.25,0)) | P21: ='08_Premissas_Custos'!$B$15*M21*(1+IF(I21="Sim",0.20,0)+IF(K21="Sim",0.15,0)) | Q21: ='08_Premissas_Custos'!$B$16*M21*IF(J21="Sim",1.6,0.55) | R21: ='08_Premissas_Custos'!$B$17*M21*IF(I21="Sim",1.8,0.15) | S21: ='08_Premissas_Custos'!$B$18*M21*(1+IF(I21="Sim",0.15)+IF(L21="Sim",0.10)) | T21: ='08_Premissas_Custos'!$B$19*M21*(1+IF(J21="Sim",0.15)) | U21: ='08_Premissas_Custos'!$B$20*M21*IF(K21="Sim",1.8,0.7) | V21: =SUM(N21:U21) | W21: =V21*(1-H21)*IF(E21="Fase 2",'08_Premissas_Custos'!$F$10,1) | X21: =(N21*'08_Premissas_Custos'!$C$13+O21*'08_Premissas_Custos'!$C$14+P21*'08_Premissas_Custos'!$C$15+Q21*'08_Premissas_Custos'!$C$16+R21*'08_Premissas_Custos'!$C$17+S21*'08_Premissas_Custos'!$C$18+T21*'08_Premissas_Custos'!$C$19+U21*'08_Premissas_Custos'!$C$20)*(1-H21)*IF(E21="Fase 2",'08_Premissas_Custos'!$F$10,1) | Y21: =X21*'08_Premissas_Custos'!$F$7 | Z21: =(X21+Y21)*'08_Premissas_Custos'!$F$6 | AA21: =SUM(X21:Z21) | AB21: Contexto
A22: 17 | B22: ED | C22: Estratégia & Dados | D22: Análises e correlações | E22: MVP | F22: Muito alta | H22: 0 | I22: Sim | J22: Sim | K22: Não | L22: Não | M22: =IF(F22="Baixa",'08_Premissas_Custos'!$B$6,IF(F22="Média",'08_Premissas_Custos'!$B$7,IF(F22="Alta",'08_Premissas_Custos'!$B$8,'08_Premissas_Custos'!$B$9))) | N22: ='08_Premissas_Custos'!$B$13*M22 | O22: ='08_Premissas_Custos'!$B$14*M22*(1+IF(L22="Sim",0.25,0)) | P22: ='08_Premissas_Custos'!$B$15*M22*(1+IF(I22="Sim",0.20,0)+IF(K22="Sim",0.15,0)) | Q22: ='08_Premissas_Custos'!$B$16*M22*IF(J22="Sim",1.6,0.55) | R22: ='08_Premissas_Custos'!$B$17*M22*IF(I22="Sim",1.8,0.15) | S22: ='08_Premissas_Custos'!$B$18*M22*(1+IF(I22="Sim",0.15)+IF(L22="Sim",0.10)) | T22: ='08_Premissas_Custos'!$B$19*M22*(1+IF(J22="Sim",0.15)) | U22: ='08_Premissas_Custos'!$B$20*M22*IF(K22="Sim",1.8,0.7) | V22: =SUM(N22:U22) | W22: =V22*(1-H22)*IF(E22="Fase 2",'08_Premissas_Custos'!$F$10,1) | X22: =(N22*'08_Premissas_Custos'!$C$13+O22*'08_Premissas_Custos'!$C$14+P22*'08_Premissas_Custos'!$C$15+Q22*'08_Premissas_Custos'!$C$16+R22*'08_Premissas_Custos'!$C$17+S22*'08_Premissas_Custos'!$C$18+T22*'08_Premissas_Custos'!$C$19+U22*'08_Premissas_Custos'!$C$20)*(1-H22)*IF(E22="Fase 2",'08_Premissas_Custos'!$F$10,1) | Y22: =X22*'08_Premissas_Custos'!$F$7 | Z22: =(X22+Y22)*'08_Premissas_Custos'!$F$6 | AA22: =SUM(X22:Z22) | AB22: Padrões
A23: 18 | B23: ED | C23: Estratégia & Dados | D23: Prioridades | E23: MVP | F23: Alta | H23: 0 | I23: Não | J23: Sim | K23: Não | L23: Não | M23: =IF(F23="Baixa",'08_Premissas_Custos'!$B$6,IF(F23="Média",'08_Premissas_Custos'!$B$7,IF(F23="Alta",'08_Premissas_Custos'!$B$8,'08_Premissas_Custos'!$B$9))) | N23: ='08_Premissas_Custos'!$B$13*M23 | O23: ='08_Premissas_Custos'!$B$14*M23*(1+IF(L23="Sim",0.25,0)) | P23: ='08_Premissas_Custos'!$B$15*M23*(1+IF(I23="Sim",0.20,0)+IF(K23="Sim",0.15,0)) | Q23: ='08_Premissas_Custos'!$B$16*M23*IF(J23="Sim",1.6,0.55) | R23: ='08_Premissas_Custos'!$B$17*M23*IF(I23="Sim",1.8,0.15) | S23: ='08_Premissas_Custos'!$B$18*M23*(1+IF(I23="Sim",0.15)+IF(L23="Sim",0.10)) | T23: ='08_Premissas_Custos'!$B$19*M23*(1+IF(J23="Sim",0.15)) | U23: ='08_Premissas_Custos'!$B$20*M23*IF(K23="Sim",1.8,0.7) | V23: =SUM(N23:U23) | W23: =V23*(1-H23)*IF(E23="Fase 2",'08_Premissas_Custos'!$F$10,1) | X23: =(N23*'08_Premissas_Custos'!$C$13+O23*'08_Premissas_Custos'!$C$14+P23*'08_Premissas_Custos'!$C$15+Q23*'08_Premissas_Custos'!$C$16+R23*'08_Premissas_Custos'!$C$17+S23*'08_Premissas_Custos'!$C$18+T23*'08_Premissas_Custos'!$C$19+U23*'08_Premissas_Custos'!$C$20)*(1-H23)*IF(E23="Fase 2",'08_Premissas_Custos'!$F$10,1) | Y23: =X23*'08_Premissas_Custos'!$F$7 | Z23: =(X23+Y23)*'08_Premissas_Custos'!$F$6 | AA23: =SUM(X23:Z23) | AB23: Riscos/oportunidades
A24: 19 | B24: ED | C24: Estratégia & Dados | D24: Planos de ação | E24: MVP | F24: Média | H24: 0 | I24: Não | J24: Sim | K24: Não | L24: Não | M24: =IF(F24="Baixa",'08_Premissas_Custos'!$B$6,IF(F24="Média",'08_Premissas_Custos'!$B$7,IF(F24="Alta",'08_Premissas_Custos'!$B$8,'08_Premissas_Custos'!$B$9))) | N24: ='08_Premissas_Custos'!$B$13*M24 | O24: ='08_Premissas_Custos'!$B$14*M24*(1+IF(L24="Sim",0.25,0)) | P24: ='08_Premissas_Custos'!$B$15*M24*(1+IF(I24="Sim",0.20,0)+IF(K24="Sim",0.15,0)) | Q24: ='08_Premissas_Custos'!$B$16*M24*IF(J24="Sim",1.6,0.55) | R24: ='08_Premissas_Custos'!$B$17*M24*IF(I24="Sim",1.8,0.15) | S24: ='08_Premissas_Custos'!$B$18*M24*(1+IF(I24="Sim",0.15)+IF(L24="Sim",0.10)) | T24: ='08_Premissas_Custos'!$B$19*M24*(1+IF(J24="Sim",0.15)) | U24: ='08_Premissas_Custos'!$B$20*M24*IF(K24="Sim",1.8,0.7) | V24: =SUM(N24:U24) | W24: =V24*(1-H24)*IF(E24="Fase 2",'08_Premissas_Custos'!$F$10,1) | X24: =(N24*'08_Premissas_Custos'!$C$13+O24*'08_Premissas_Custos'!$C$14+P24*'08_Premissas_Custos'!$C$15+Q24*'08_Premissas_Custos'!$C$16+R24*'08_Premissas_Custos'!$C$17+S24*'08_Premissas_Custos'!$C$18+T24*'08_Premissas_Custos'!$C$19+U24*'08_Premissas_Custos'!$C$20)*(1-H24)*IF(E24="Fase 2",'08_Premissas_Custos'!$F$10,1) | Y24: =X24*'08_Premissas_Custos'!$F$7 | Z24: =(X24+Y24)*'08_Premissas_Custos'!$F$6 | AA24: =SUM(X24:Z24) | AB24: Ações
A25: 20 | B25: ED | C25: Estratégia & Dados | D25: Cenários / simulações | E25: Fase 2 | F25: Muito alta | H25: 0 | I25: Sim | J25: Sim | K25: Não | L25: Não | M25: =IF(F25="Baixa",'08_Premissas_Custos'!$B$6,IF(F25="Média",'08_Premissas_Custos'!$B$7,IF(F25="Alta",'08_Premissas_Custos'!$B$8,'08_Premissas_Custos'!$B$9))) | N25: ='08_Premissas_Custos'!$B$13*M25 | O25: ='08_Premissas_Custos'!$B$14*M25*(1+IF(L25="Sim",0.25,0)) | P25: ='08_Premissas_Custos'!$B$15*M25*(1+IF(I25="Sim",0.20,0)+IF(K25="Sim",0.15,0)) | Q25: ='08_Premissas_Custos'!$B$16*M25*IF(J25="Sim",1.6,0.55) | R25: ='08_Premissas_Custos'!$B$17*M25*IF(I25="Sim",1.8,0.15) | S25: ='08_Premissas_Custos'!$B$18*M25*(1+IF(I25="Sim",0.15)+IF(L25="Sim",0.10)) | T25: ='08_Premissas_Custos'!$B$19*M25*(1+IF(J25="Sim",0.15)) | U25: ='08_Premissas_Custos'!$B$20*M25*IF(K25="Sim",1.8,0.7) | V25: =SUM(N25:U25) | W25: =V25*(1-H25)*IF(E25="Fase 2",'08_Premissas_Custos'!$F$10,1) | X25: =(N25*'08_Premissas_Custos'!$C$13+O25*'08_Premissas_Custos'!$C$14+P25*'08_Premissas_Custos'!$C$15+Q25*'08_Premissas_Custos'!$C$16+R25*'08_Premissas_Custos'!$C$17+S25*'08_Premissas_Custos'!$C$18+T25*'08_Premissas_Custos'!$C$19+U25*'08_Premissas_Custos'!$C$20)*(1-H25)*IF(E25="Fase 2",'08_Premissas_Custos'!$F$10,1) | Y25: =X25*'08_Premissas_Custos'!$F$7 | Z25: =(X25+Y25)*'08_Premissas_Custos'!$F$6 | AA25: =SUM(X25:Z25) | AB25: Projeções
A26: 21 | B26: ED | C26: Estratégia & Dados | D26: ROI / valor capturado | E26: MVP | F26: Alta | H26: 0 | I26: Não | J26: Sim | K26: Não | L26: Não | M26: =IF(F26="Baixa",'08_Premissas_Custos'!$B$6,IF(F26="Média",'08_Premissas_Custos'!$B$7,IF(F26="Alta",'08_Premissas_Custos'!$B$8,'08_Premissas_Custos'!$B$9))) | N26: ='08_Premissas_Custos'!$B$13*M26 | O26: ='08_Premissas_Custos'!$B$14*M26*(1+IF(L26="Sim",0.25,0)) | P26: ='08_Premissas_Custos'!$B$15*M26*(1+IF(I26="Sim",0.20,0)+IF(K26="Sim",0.15,0)) | Q26: ='08_Premissas_Custos'!$B$16*M26*IF(J26="Sim",1.6,0.55) | R26: ='08_Premissas_Custos'!$B$17*M26*IF(I26="Sim",1.8,0.15) | S26: ='08_Premissas_Custos'!$B$18*M26*(1+IF(I26="Sim",0.15)+IF(L26="Sim",0.10)) | T26: ='08_Premissas_Custos'!$B$19*M26*(1+IF(J26="Sim",0.15)) | U26: ='08_Premissas_Custos'!$B$20*M26*IF(K26="Sim",1.8,0.7) | V26: =SUM(N26:U26) | W26: =V26*(1-H26)*IF(E26="Fase 2",'08_Premissas_Custos'!$F$10,1) | X26: =(N26*'08_Premissas_Custos'!$C$13+O26*'08_Premissas_Custos'!$C$14+P26*'08_Premissas_Custos'!$C$15+Q26*'08_Premissas_Custos'!$C$16+R26*'08_Premissas_Custos'!$C$17+S26*'08_Premissas_Custos'!$C$18+T26*'08_Premissas_Custos'!$C$19+U26*'08_Premissas_Custos'!$C$20)*(1-H26)*IF(E26="Fase 2",'08_Premissas_Custos'!$F$10,1) | Y26: =X26*'08_Premissas_Custos'!$F$7 | Z26: =(X26+Y26)*'08_Premissas_Custos'!$F$6 | AA26: =SUM(X26:Z26) | AB26: Financeiro
A27: 22 | B27: ED | C27: Estratégia & Dados | D27: Relatórios executivos | E27: MVP | F27: Média | H27: 0 | I27: Não | J27: Sim | K27: Não | L27: Não | M27: =IF(F27="Baixa",'08_Premissas_Custos'!$B$6,IF(F27="Média",'08_Premissas_Custos'!$B$7,IF(F27="Alta",'08_Premissas_Custos'!$B$8,'08_Premissas_Custos'!$B$9))) | N27: ='08_Premissas_Custos'!$B$13*M27 | O27: ='08_Premissas_Custos'!$B$14*M27*(1+IF(L27="Sim",0.25,0)) | P27: ='08_Premissas_Custos'!$B$15*M27*(1+IF(I27="Sim",0.20,0)+IF(K27="Sim",0.15,0)) | Q27: ='08_Premissas_Custos'!$B$16*M27*IF(J27="Sim",1.6,0.55) | R27: ='08_Premissas_Custos'!$B$17*M27*IF(I27="Sim",1.8,0.15) | S27: ='08_Premissas_Custos'!$B$18*M27*(1+IF(I27="Sim",0.15)+IF(L27="Sim",0.10)) | T27: ='08_Premissas_Custos'!$B$19*M27*(1+IF(J27="Sim",0.15)) | U27: ='08_Premissas_Custos'!$B$20*M27*IF(K27="Sim",1.8,0.7) | V27: =SUM(N27:U27) | W27: =V27*(1-H27)*IF(E27="Fase 2",'08_Premissas_Custos'!$F$10,1) | X27: =(N27*'08_Premissas_Custos'!$C$13+O27*'08_Premissas_Custos'!$C$14+P27*'08_Premissas_Custos'!$C$15+Q27*'08_Premissas_Custos'!$C$16+R27*'08_Premissas_Custos'!$C$17+S27*'08_Premissas_Custos'!$C$18+T27*'08_Premissas_Custos'!$C$19+U27*'08_Premissas_Custos'!$C$20)*(1-H27)*IF(E27="Fase 2",'08_Premissas_Custos'!$F$10,1) | Y27: =X27*'08_Premissas_Custos'!$F$7 | Z27: =(X27+Y27)*'08_Premissas_Custos'!$F$6 | AA27: =SUM(X27:Z27) | AB27: Exportação
A28: 23 | B28: ED | C28: Estratégia & Dados | D28: Alertas estratégicos | E28: MVP | F28: Alta | H28: 0 | I28: Não | J28: Sim | K28: Não | L28: Não | M28: =IF(F28="Baixa",'08_Premissas_Custos'!$B$6,IF(F28="Média",'08_Premissas_Custos'!$B$7,IF(F28="Alta",'08_Premissas_Custos'!$B$8,'08_Premissas_Custos'!$B$9))) | N28: ='08_Premissas_Custos'!$B$13*M28 | O28: ='08_Premissas_Custos'!$B$14*M28*(1+IF(L28="Sim",0.25,0)) | P28: ='08_Premissas_Custos'!$B$15*M28*(1+IF(I28="Sim",0.20,0)+IF(K28="Sim",0.15,0)) | Q28: ='08_Premissas_Custos'!$B$16*M28*IF(J28="Sim",1.6,0.55) | R28: ='08_Premissas_Custos'!$B$17*M28*IF(I28="Sim",1.8,0.15) | S28: ='08_Premissas_Custos'!$B$18*M28*(1+IF(I28="Sim",0.15)+IF(L28="Sim",0.10)) | T28: ='08_Premissas_Custos'!$B$19*M28*(1+IF(J28="Sim",0.15)) | U28: ='08_Premissas_Custos'!$B$20*M28*IF(K28="Sim",1.8,0.7) | V28: =SUM(N28:U28) | W28: =V28*(1-H28)*IF(E28="Fase 2",'08_Premissas_Custos'!$F$10,1) | X28: =(N28*'08_Premissas_Custos'!$C$13+O28*'08_Premissas_Custos'!$C$14+P28*'08_Premissas_Custos'!$C$15+Q28*'08_Premissas_Custos'!$C$16+R28*'08_Premissas_Custos'!$C$17+S28*'08_Premissas_Custos'!$C$18+T28*'08_Premissas_Custos'!$C$19+U28*'08_Premissas_Custos'!$C$20)*(1-H28)*IF(E28="Fase 2",'08_Premissas_Custos'!$F$10,1) | Y28: =X28*'08_Premissas_Custos'!$F$7 | Z28: =(X28+Y28)*'08_Premissas_Custos'!$F$6 | AA28: =SUM(X28:Z28) | AB28: Sinais
A29: 24 | B29: COL | C29: Colaboradores / Meu Time | D29: Meu time | E29: MVP | F29: Alta | H29: 0 | I29: Não | J29: Não | K29: Não | L29: Não | M29: =IF(F29="Baixa",'08_Premissas_Custos'!$B$6,IF(F29="Média",'08_Premissas_Custos'!$B$7,IF(F29="Alta",'08_Premissas_Custos'!$B$8,'08_Premissas_Custos'!$B$9))) | N29: ='08_Premissas_Custos'!$B$13*M29 | O29: ='08_Premissas_Custos'!$B$14*M29*(1+IF(L29="Sim",0.25,0)) | P29: ='08_Premissas_Custos'!$B$15*M29*(1+IF(I29="Sim",0.20,0)+IF(K29="Sim",0.15,0)) | Q29: ='08_Premissas_Custos'!$B$16*M29*IF(J29="Sim",1.6,0.55) | R29: ='08_Premissas_Custos'!$B$17*M29*IF(I29="Sim",1.8,0.15) | S29: ='08_Premissas_Custos'!$B$18*M29*(1+IF(I29="Sim",0.15)+IF(L29="Sim",0.10)) | T29: ='08_Premissas_Custos'!$B$19*M29*(1+IF(J29="Sim",0.15)) | U29: ='08_Premissas_Custos'!$B$20*M29*IF(K29="Sim",1.8,0.7) | V29: =SUM(N29:U29) | W29: =V29*(1-H29)*IF(E29="Fase 2",'08_Premissas_Custos'!$F$10,1) | X29: =(N29*'08_Premissas_Custos'!$C$13+O29*'08_Premissas_Custos'!$C$14+P29*'08_Premissas_Custos'!$C$15+Q29*'08_Premissas_Custos'!$C$16+R29*'08_Premissas_Custos'!$C$17+S29*'08_Premissas_Custos'!$C$18+T29*'08_Premissas_Custos'!$C$19+U29*'08_Premissas_Custos'!$C$20)*(1-H29)*IF(E29="Fase 2",'08_Premissas_Custos'!$F$10,1) | Y29: =X29*'08_Premissas_Custos'!$F$7 | Z29: =(X29+Y29)*'08_Premissas_Custos'!$F$6 | AA29: =SUM(X29:Z29) | AB29: Mapa
A30: 25 | B30: COL | C30: Colaboradores / Meu Time | D30: Perfil do colaborador | E30: MVP | F30: Média | G30: Perfil do colaborador | H30: 0.45 | I30: Não | J30: Não | K30: Não | L30: Não | M30: =IF(F30="Baixa",'08_Premissas_Custos'!$B$6,IF(F30="Média",'08_Premissas_Custos'!$B$7,IF(F30="Alta",'08_Premissas_Custos'!$B$8,'08_Premissas_Custos'!$B$9))) | N30: ='08_Premissas_Custos'!$B$13*M30 | O30: ='08_Premissas_Custos'!$B$14*M30*(1+IF(L30="Sim",0.25,0)) | P30: ='08_Premissas_Custos'!$B$15*M30*(1+IF(I30="Sim",0.20,0)+IF(K30="Sim",0.15,0)) | Q30: ='08_Premissas_Custos'!$B$16*M30*IF(J30="Sim",1.6,0.55) | R30: ='08_Premissas_Custos'!$B$17*M30*IF(I30="Sim",1.8,0.15) | S30: ='08_Premissas_Custos'!$B$18*M30*(1+IF(I30="Sim",0.15)+IF(L30="Sim",0.10)) | T30: ='08_Premissas_Custos'!$B$19*M30*(1+IF(J30="Sim",0.15)) | U30: ='08_Premissas_Custos'!$B$20*M30*IF(K30="Sim",1.8,0.7) | V30: =SUM(N30:U30) | W30: =V30*(1-H30)*IF(E30="Fase 2",'08_Premissas_Custos'!$F$10,1) | X30: =(N30*'08_Premissas_Custos'!$C$13+O30*'08_Premissas_Custos'!$C$14+P30*'08_Premissas_Custos'!$C$15+Q30*'08_Premissas_Custos'!$C$16+R30*'08_Premissas_Custos'!$C$17+S30*'08_Premissas_Custos'!$C$18+T30*'08_Premissas_Custos'!$C$19+U30*'08_Premissas_Custos'!$C$20)*(1-H30)*IF(E30="Fase 2",'08_Premissas_Custos'!$F$10,1) | Y30: =X30*'08_Premissas_Custos'!$F$7 | Z30: =(X30+Y30)*'08_Premissas_Custos'!$F$6 | AA30: =SUM(X30:Z30) | AB30: 360
A31: 26 | B31: COL | C31: Colaboradores / Meu Time | D31: Objetivos e combinados | E31: MVP | F31: Média | H31: 0 | I31: Não | J31: Não | K31: Não | L31: Não | M31: =IF(F31="Baixa",'08_Premissas_Custos'!$B$6,IF(F31="Média",'08_Premissas_Custos'!$B$7,IF(F31="Alta",'08_Premissas_Custos'!$B$8,'08_Premissas_Custos'!$B$9))) | N31: ='08_Premissas_Custos'!$B$13*M31 | O31: ='08_Premissas_Custos'!$B$14*M31*(1+IF(L31="Sim",0.25,0)) | P31: ='08_Premissas_Custos'!$B$15*M31*(1+IF(I31="Sim",0.20,0)+IF(K31="Sim",0.15,0)) | Q31: ='08_Premissas_Custos'!$B$16*M31*IF(J31="Sim",1.6,0.55) | R31: ='08_Premissas_Custos'!$B$17*M31*IF(I31="Sim",1.8,0.15) | S31: ='08_Premissas_Custos'!$B$18*M31*(1+IF(I31="Sim",0.15)+IF(L31="Sim",0.10)) | T31: ='08_Premissas_Custos'!$B$19*M31*(1+IF(J31="Sim",0.15)) | U31: ='08_Premissas_Custos'!$B$20*M31*IF(K31="Sim",1.8,0.7) | V31: =SUM(N31:U31) | W31: =V31*(1-H31)*IF(E31="Fase 2",'08_Premissas_Custos'!$F$10,1) | X31: =(N31*'08_Premissas_Custos'!$C$13+O31*'08_Premissas_Custos'!$C$14+P31*'08_Premissas_Custos'!$C$15+Q31*'08_Premissas_Custos'!$C$16+R31*'08_Premissas_Custos'!$C$17+S31*'08_Premissas_Custos'!$C$18+T31*'08_Premissas_Custos'!$C$19+U31*'08_Premissas_Custos'!$C$20)*(1-H31)*IF(E31="Fase 2",'08_Premissas_Custos'!$F$10,1) | Y31: =X31*'08_Premissas_Custos'!$F$7 | Z31: =(X31+Y31)*'08_Premissas_Custos'!$F$6 | AA31: =SUM(X31:Z31) | AB31: Metas
A32: 27 | B32: COL | C32: Colaboradores / Meu Time | D32: Competências | E32: MVP | F32: Média | H32: 0 | I32: Não | J32: Não | K32: Não | L32: Não | M32: =IF(F32="Baixa",'08_Premissas_Custos'!$B$6,IF(F32="Média",'08_Premissas_Custos'!$B$7,IF(F32="Alta",'08_Premissas_Custos'!$B$8,'08_Premissas_Custos'!$B$9))) | N32: ='08_Premissas_Custos'!$B$13*M32 | O32: ='08_Premissas_Custos'!$B$14*M32*(1+IF(L32="Sim",0.25,0)) | P32: ='08_Premissas_Custos'!$B$15*M32*(1+IF(I32="Sim",0.20,0)+IF(K32="Sim",0.15,0)) | Q32: ='08_Premissas_Custos'!$B$16*M32*IF(J32="Sim",1.6,0.55) | R32: ='08_Premissas_Custos'!$B$17*M32*IF(I32="Sim",1.8,0.15) | S32: ='08_Premissas_Custos'!$B$18*M32*(1+IF(I32="Sim",0.15)+IF(L32="Sim",0.10)) | T32: ='08_Premissas_Custos'!$B$19*M32*(1+IF(J32="Sim",0.15)) | U32: ='08_Premissas_Custos'!$B$20*M32*IF(K32="Sim",1.8,0.7) | V32: =SUM(N32:U32) | W32: =V32*(1-H32)*IF(E32="Fase 2",'08_Premissas_Custos'!$F$10,1) | X32: =(N32*'08_Premissas_Custos'!$C$13+O32*'08_Premissas_Custos'!$C$14+P32*'08_Premissas_Custos'!$C$15+Q32*'08_Premissas_Custos'!$C$16+R32*'08_Premissas_Custos'!$C$17+S32*'08_Premissas_Custos'!$C$18+T32*'08_Premissas_Custos'!$C$19+U32*'08_Premissas_Custos'!$C$20)*(1-H32)*IF(E32="Fase 2",'08_Premissas_Custos'!$F$10,1) | Y32: =X32*'08_Premissas_Custos'!$F$7 | Z32: =(X32+Y32)*'08_Premissas_Custos'!$F$6 | AA32: =SUM(X32:Z32) | AB32: Skills
A33: 28 | B33: COL | C33: Colaboradores / Meu Time | D33: Feedbacks / check-ins | E33: MVP | F33: Média | H33: 0 | I33: Não | J33: Não | K33: Não | L33: Sim | M33: =IF(F33="Baixa",'08_Premissas_Custos'!$B$6,IF(F33="Média",'08_Premissas_Custos'!$B$7,IF(F33="Alta",'08_Premissas_Custos'!$B$8,'08_Premissas_Custos'!$B$9))) | N33: ='08_Premissas_Custos'!$B$13*M33 | O33: ='08_Premissas_Custos'!$B$14*M33*(1+IF(L33="Sim",0.25,0)) | P33: ='08_Premissas_Custos'!$B$15*M33*(1+IF(I33="Sim",0.20,0)+IF(K33="Sim",0.15,0)) | Q33: ='08_Premissas_Custos'!$B$16*M33*IF(J33="Sim",1.6,0.55) | R33: ='08_Premissas_Custos'!$B$17*M33*IF(I33="Sim",1.8,0.15) | S33: ='08_Premissas_Custos'!$B$18*M33*(1+IF(I33="Sim",0.15)+IF(L33="Sim",0.10)) | T33: ='08_Premissas_Custos'!$B$19*M33*(1+IF(J33="Sim",0.15)) | U33: ='08_Premissas_Custos'!$B$20*M33*IF(K33="Sim",1.8,0.7) | V33: =SUM(N33:U33) | W33: =V33*(1-H33)*IF(E33="Fase 2",'08_Premissas_Custos'!$F$10,1) | X33: =(N33*'08_Premissas_Custos'!$C$13+O33*'08_Premissas_Custos'!$C$14+P33*'08_Premissas_Custos'!$C$15+Q33*'08_Premissas_Custos'!$C$16+R33*'08_Premissas_Custos'!$C$17+S33*'08_Premissas_Custos'!$C$18+T33*'08_Premissas_Custos'!$C$19+U33*'08_Premissas_Custos'!$C$20)*(1-H33)*IF(E33="Fase 2",'08_Premissas_Custos'!$F$10,1) | Y33: =X33*'08_Premissas_Custos'!$F$7 | Z33: =(X33+Y33)*'08_Premissas_Custos'!$F$6 | AA33: =SUM(X33:Z33) | AB33: Ciclo
A34: 29 | B34: COL | C34: Colaboradores / Meu Time | D34: Plano de desenvolvimento | E34: MVP | F34: Média | G34: Plano de desenvolvimento | H34: 0.45 | I34: Não | J34: Não | K34: Não | L34: Não | M34: =IF(F34="Baixa",'08_Premissas_Custos'!$B$6,IF(F34="Média",'08_Premissas_Custos'!$B$7,IF(F34="Alta",'08_Premissas_Custos'!$B$8,'08_Premissas_Custos'!$B$9))) | N34: ='08_Premissas_Custos'!$B$13*M34 | O34: ='08_Premissas_Custos'!$B$14*M34*(1+IF(L34="Sim",0.25,0)) | P34: ='08_Premissas_Custos'!$B$15*M34*(1+IF(I34="Sim",0.20,0)+IF(K34="Sim",0.15,0)) | Q34: ='08_Premissas_Custos'!$B$16*M34*IF(J34="Sim",1.6,0.55) | R34: ='08_Premissas_Custos'!$B$17*M34*IF(I34="Sim",1.8,0.15) | S34: ='08_Premissas_Custos'!$B$18*M34*(1+IF(I34="Sim",0.15)+IF(L34="Sim",0.10)) | T34: ='08_Premissas_Custos'!$B$19*M34*(1+IF(J34="Sim",0.15)) | U34: ='08_Premissas_Custos'!$B$20*M34*IF(K34="Sim",1.8,0.7) | V34: =SUM(N34:U34) | W34: =V34*(1-H34)*IF(E34="Fase 2",'08_Premissas_Custos'!$F$10,1) | X34: =(N34*'08_Premissas_Custos'!$C$13+O34*'08_Premissas_Custos'!$C$14+P34*'08_Premissas_Custos'!$C$15+Q34*'08_Premissas_Custos'!$C$16+R34*'08_Premissas_Custos'!$C$17+S34*'08_Premissas_Custos'!$C$18+T34*'08_Premissas_Custos'!$C$19+U34*'08_Premissas_Custos'!$C$20)*(1-H34)*IF(E34="Fase 2",'08_Premissas_Custos'!$F$10,1) | Y34: =X34*'08_Premissas_Custos'!$F$7 | Z34: =(X34+Y34)*'08_Premissas_Custos'!$F$6 | AA34: =SUM(X34:Z34) | AB34: PDI
A35: 30 | B35: COL | C35: Colaboradores / Meu Time | D35: Mentorias | E35: MVP+1 | F35: Média | H35: 0 | I35: Não | J35: Não | K35: Não | L35: Não | M35: =IF(F35="Baixa",'08_Premissas_Custos'!$B$6,IF(F35="Média",'08_Premissas_Custos'!$B$7,IF(F35="Alta",'08_Premissas_Custos'!$B$8,'08_Premissas_Custos'!$B$9))) | N35: ='08_Premissas_Custos'!$B$13*M35 | O35: ='08_Premissas_Custos'!$B$14*M35*(1+IF(L35="Sim",0.25,0)) | P35: ='08_Premissas_Custos'!$B$15*M35*(1+IF(I35="Sim",0.20,0)+IF(K35="Sim",0.15,0)) | Q35: ='08_Premissas_Custos'!$B$16*M35*IF(J35="Sim",1.6,0.55) | R35: ='08_Premissas_Custos'!$B$17*M35*IF(I35="Sim",1.8,0.15) | S35: ='08_Premissas_Custos'!$B$18*M35*(1+IF(I35="Sim",0.15)+IF(L35="Sim",0.10)) | T35: ='08_Premissas_Custos'!$B$19*M35*(1+IF(J35="Sim",0.15)) | U35: ='08_Premissas_Custos'!$B$20*M35*IF(K35="Sim",1.8,0.7) | V35: =SUM(N35:U35) | W35: =V35*(1-H35)*IF(E35="Fase 2",'08_Premissas_Custos'!$F$10,1) | X35: =(N35*'08_Premissas_Custos'!$C$13+O35*'08_Premissas_Custos'!$C$14+P35*'08_Premissas_Custos'!$C$15+Q35*'08_Premissas_Custos'!$C$16+R35*'08_Premissas_Custos'!$C$17+S35*'08_Premissas_Custos'!$C$18+T35*'08_Premissas_Custos'!$C$19+U35*'08_Premissas_Custos'!$C$20)*(1-H35)*IF(E35="Fase 2",'08_Premissas_Custos'!$F$10,1) | Y35: =X35*'08_Premissas_Custos'!$F$7 | Z35: =(X35+Y35)*'08_Premissas_Custos'!$F$6 | AA35: =SUM(X35:Z35) | AB35: Matching
A36: 31 | B36: COL | C36: Colaboradores / Meu Time | D36: Aprendizagem / trilhas | E36: MVP+1 | F36: Média | H36: 0 | I36: Não | J36: Não | K36: Não | L36: Não | M36: =IF(F36="Baixa",'08_Premissas_Custos'!$B$6,IF(F36="Média",'08_Premissas_Custos'!$B$7,IF(F36="Alta",'08_Premissas_Custos'!$B$8,'08_Premissas_Custos'!$B$9))) | N36: ='08_Premissas_Custos'!$B$13*M36 | O36: ='08_Premissas_Custos'!$B$14*M36*(1+IF(L36="Sim",0.25,0)) | P36: ='08_Premissas_Custos'!$B$15*M36*(1+IF(I36="Sim",0.20,0)+IF(K36="Sim",0.15,0)) | Q36: ='08_Premissas_Custos'!$B$16*M36*IF(J36="Sim",1.6,0.55) | R36: ='08_Premissas_Custos'!$B$17*M36*IF(I36="Sim",1.8,0.15) | S36: ='08_Premissas_Custos'!$B$18*M36*(1+IF(I36="Sim",0.15)+IF(L36="Sim",0.10)) | T36: ='08_Premissas_Custos'!$B$19*M36*(1+IF(J36="Sim",0.15)) | U36: ='08_Premissas_Custos'!$B$20*M36*IF(K36="Sim",1.8,0.7) | V36: =SUM(N36:U36) | W36: =V36*(1-H36)*IF(E36="Fase 2",'08_Premissas_Custos'!$F$10,1) | X36: =(N36*'08_Premissas_Custos'!$C$13+O36*'08_Premissas_Custos'!$C$14+P36*'08_Premissas_Custos'!$C$15+Q36*'08_Premissas_Custos'!$C$16+R36*'08_Premissas_Custos'!$C$17+S36*'08_Premissas_Custos'!$C$18+T36*'08_Premissas_Custos'!$C$19+U36*'08_Premissas_Custos'!$C$20)*(1-H36)*IF(E36="Fase 2",'08_Premissas_Custos'!$F$10,1) | Y36: =X36*'08_Premissas_Custos'!$F$7 | Z36: =(X36+Y36)*'08_Premissas_Custos'!$F$6 | AA36: =SUM(X36:Z36) | AB36: Conteúdo
A37: 32 | B37: COL | C37: Colaboradores / Meu Time | D37: Talentos internos / mobilidade | E37: MVP+1 | F37: Alta | H37: 0 | I37: Não | J37: Não | K37: Não | L37: Não | M37: =IF(F37="Baixa",'08_Premissas_Custos'!$B$6,IF(F37="Média",'08_Premissas_Custos'!$B$7,IF(F37="Alta",'08_Premissas_Custos'!$B$8,'08_Premissas_Custos'!$B$9))) | N37: ='08_Premissas_Custos'!$B$13*M37 | O37: ='08_Premissas_Custos'!$B$14*M37*(1+IF(L37="Sim",0.25,0)) | P37: ='08_Premissas_Custos'!$B$15*M37*(1+IF(I37="Sim",0.20,0)+IF(K37="Sim",0.15,0)) | Q37: ='08_Premissas_Custos'!$B$16*M37*IF(J37="Sim",1.6,0.55) | R37: ='08_Premissas_Custos'!$B$17*M37*IF(I37="Sim",1.8,0.15) | S37: ='08_Premissas_Custos'!$B$18*M37*(1+IF(I37="Sim",0.15)+IF(L37="Sim",0.10)) | T37: ='08_Premissas_Custos'!$B$19*M37*(1+IF(J37="Sim",0.15)) | U37: ='08_Premissas_Custos'!$B$20*M37*IF(K37="Sim",1.8,0.7) | V37: =SUM(N37:U37) | W37: =V37*(1-H37)*IF(E37="Fase 2",'08_Premissas_Custos'!$F$10,1) | X37: =(N37*'08_Premissas_Custos'!$C$13+O37*'08_Premissas_Custos'!$C$14+P37*'08_Premissas_Custos'!$C$15+Q37*'08_Premissas_Custos'!$C$16+R37*'08_Premissas_Custos'!$C$17+S37*'08_Premissas_Custos'!$C$18+T37*'08_Premissas_Custos'!$C$19+U37*'08_Premissas_Custos'!$C$20)*(1-H37)*IF(E37="Fase 2",'08_Premissas_Custos'!$F$10,1) | Y37: =X37*'08_Premissas_Custos'!$F$7 | Z37: =(X37+Y37)*'08_Premissas_Custos'!$F$6 | AA37: =SUM(X37:Z37) | AB37: Oportunidades
A38: 33 | B38: COL | C38: Colaboradores / Meu Time | D38: Sucessão | E38: MVP+1 | F38: Alta | H38: 0 | I38: Não | J38: Não | K38: Não | L38: Não | M38: =IF(F38="Baixa",'08_Premissas_Custos'!$B$6,IF(F38="Média",'08_Premissas_Custos'!$B$7,IF(F38="Alta",'08_Premissas_Custos'!$B$8,'08_Premissas_Custos'!$B$9))) | N38: ='08_Premissas_Custos'!$B$13*M38 | O38: ='08_Premissas_Custos'!$B$14*M38*(1+IF(L38="Sim",0.25,0)) | P38: ='08_Premissas_Custos'!$B$15*M38*(1+IF(I38="Sim",0.20,0)+IF(K38="Sim",0.15,0)) | Q38: ='08_Premissas_Custos'!$B$16*M38*IF(J38="Sim",1.6,0.55) | R38: ='08_Premissas_Custos'!$B$17*M38*IF(I38="Sim",1.8,0.15) | S38: ='08_Premissas_Custos'!$B$18*M38*(1+IF(I38="Sim",0.15)+IF(L38="Sim",0.10)) | T38: ='08_Premissas_Custos'!$B$19*M38*(1+IF(J38="Sim",0.15)) | U38: ='08_Premissas_Custos'!$B$20*M38*IF(K38="Sim",1.8,0.7) | V38: =SUM(N38:U38) | W38: =V38*(1-H38)*IF(E38="Fase 2",'08_Premissas_Custos'!$F$10,1) | X38: =(N38*'08_Premissas_Custos'!$C$13+O38*'08_Premissas_Custos'!$C$14+P38*'08_Premissas_Custos'!$C$15+Q38*'08_Premissas_Custos'!$C$16+R38*'08_Premissas_Custos'!$C$17+S38*'08_Premissas_Custos'!$C$18+T38*'08_Premissas_Custos'!$C$19+U38*'08_Premissas_Custos'!$C$20)*(1-H38)*IF(E38="Fase 2",'08_Premissas_Custos'!$F$10,1) | Y38: =X38*'08_Premissas_Custos'!$F$7 | Z38: =(X38+Y38)*'08_Premissas_Custos'!$F$6 | AA38: =SUM(X38:Z38) | AB38: Prontidão
A39: 34 | B39: COL | C39: Colaboradores / Meu Time | D39: Saúde do time / alertas | E39: MVP | F39: Alta | H39: 0 | I39: Não | J39: Sim | K39: Não | L39: Não | M39: =IF(F39="Baixa",'08_Premissas_Custos'!$B$6,IF(F39="Média",'08_Premissas_Custos'!$B$7,IF(F39="Alta",'08_Premissas_Custos'!$B$8,'08_Premissas_Custos'!$B$9))) | N39: ='08_Premissas_Custos'!$B$13*M39 | O39: ='08_Premissas_Custos'!$B$14*M39*(1+IF(L39="Sim",0.25,0)) | P39: ='08_Premissas_Custos'!$B$15*M39*(1+IF(I39="Sim",0.20,0)+IF(K39="Sim",0.15,0)) | Q39: ='08_Premissas_Custos'!$B$16*M39*IF(J39="Sim",1.6,0.55) | R39: ='08_Premissas_Custos'!$B$17*M39*IF(I39="Sim",1.8,0.15) | S39: ='08_Premissas_Custos'!$B$18*M39*(1+IF(I39="Sim",0.15)+IF(L39="Sim",0.10)) | T39: ='08_Premissas_Custos'!$B$19*M39*(1+IF(J39="Sim",0.15)) | U39: ='08_Premissas_Custos'!$B$20*M39*IF(K39="Sim",1.8,0.7) | V39: =SUM(N39:U39) | W39: =V39*(1-H39)*IF(E39="Fase 2",'08_Premissas_Custos'!$F$10,1) | X39: =(N39*'08_Premissas_Custos'!$C$13+O39*'08_Premissas_Custos'!$C$14+P39*'08_Premissas_Custos'!$C$15+Q39*'08_Premissas_Custos'!$C$16+R39*'08_Premissas_Custos'!$C$17+S39*'08_Premissas_Custos'!$C$18+T39*'08_Premissas_Custos'!$C$19+U39*'08_Premissas_Custos'!$C$20)*(1-H39)*IF(E39="Fase 2",'08_Premissas_Custos'!$F$10,1) | Y39: =X39*'08_Premissas_Custos'!$F$7 | Z39: =(X39+Y39)*'08_Premissas_Custos'!$F$6 | AA39: =SUM(X39:Z39) | AB39: Risco
A40: 35 | B40: CAN | C40: Candidatos & Carreira | D40: Perfil do candidato | E40: MVP+1 | F40: Média | G40: Perfil do candidato | H40: 0.45 | I40: Não | J40: Não | K40: Não | L40: Sim | M40: =IF(F40="Baixa",'08_Premissas_Custos'!$B$6,IF(F40="Média",'08_Premissas_Custos'!$B$7,IF(F40="Alta",'08_Premissas_Custos'!$B$8,'08_Premissas_Custos'!$B$9))) | N40: ='08_Premissas_Custos'!$B$13*M40 | O40: ='08_Premissas_Custos'!$B$14*M40*(1+IF(L40="Sim",0.25,0)) | P40: ='08_Premissas_Custos'!$B$15*M40*(1+IF(I40="Sim",0.20,0)+IF(K40="Sim",0.15,0)) | Q40: ='08_Premissas_Custos'!$B$16*M40*IF(J40="Sim",1.6,0.55) | R40: ='08_Premissas_Custos'!$B$17*M40*IF(I40="Sim",1.8,0.15) | S40: ='08_Premissas_Custos'!$B$18*M40*(1+IF(I40="Sim",0.15)+IF(L40="Sim",0.10)) | T40: ='08_Premissas_Custos'!$B$19*M40*(1+IF(J40="Sim",0.15)) | U40: ='08_Premissas_Custos'!$B$20*M40*IF(K40="Sim",1.8,0.7) | V40: =SUM(N40:U40) | W40: =V40*(1-H40)*IF(E40="Fase 2",'08_Premissas_Custos'!$F$10,1) | X40: =(N40*'08_Premissas_Custos'!$C$13+O40*'08_Premissas_Custos'!$C$14+P40*'08_Premissas_Custos'!$C$15+Q40*'08_Premissas_Custos'!$C$16+R40*'08_Premissas_Custos'!$C$17+S40*'08_Premissas_Custos'!$C$18+T40*'08_Premissas_Custos'!$C$19+U40*'08_Premissas_Custos'!$C$20)*(1-H40)*IF(E40="Fase 2",'08_Premissas_Custos'!$F$10,1) | Y40: =X40*'08_Premissas_Custos'!$F$7 | Z40: =(X40+Y40)*'08_Premissas_Custos'!$F$6 | AA40: =SUM(X40:Z40) | AB40: Perfil
A41: 36 | B41: CAN | C41: Candidatos & Carreira | D41: Currículo / portfólio | E41: MVP+1 | F41: Média | H41: 0 | I41: Não | J41: Não | K41: Não | L41: Sim | M41: =IF(F41="Baixa",'08_Premissas_Custos'!$B$6,IF(F41="Média",'08_Premissas_Custos'!$B$7,IF(F41="Alta",'08_Premissas_Custos'!$B$8,'08_Premissas_Custos'!$B$9))) | N41: ='08_Premissas_Custos'!$B$13*M41 | O41: ='08_Premissas_Custos'!$B$14*M41*(1+IF(L41="Sim",0.25,0)) | P41: ='08_Premissas_Custos'!$B$15*M41*(1+IF(I41="Sim",0.20,0)+IF(K41="Sim",0.15,0)) | Q41: ='08_Premissas_Custos'!$B$16*M41*IF(J41="Sim",1.6,0.55) | R41: ='08_Premissas_Custos'!$B$17*M41*IF(I41="Sim",1.8,0.15) | S41: ='08_Premissas_Custos'!$B$18*M41*(1+IF(I41="Sim",0.15)+IF(L41="Sim",0.10)) | T41: ='08_Premissas_Custos'!$B$19*M41*(1+IF(J41="Sim",0.15)) | U41: ='08_Premissas_Custos'!$B$20*M41*IF(K41="Sim",1.8,0.7) | V41: =SUM(N41:U41) | W41: =V41*(1-H41)*IF(E41="Fase 2",'08_Premissas_Custos'!$F$10,1) | X41: =(N41*'08_Premissas_Custos'!$C$13+O41*'08_Premissas_Custos'!$C$14+P41*'08_Premissas_Custos'!$C$15+Q41*'08_Premissas_Custos'!$C$16+R41*'08_Premissas_Custos'!$C$17+S41*'08_Premissas_Custos'!$C$18+T41*'08_Premissas_Custos'!$C$19+U41*'08_Premissas_Custos'!$C$20)*(1-H41)*IF(E41="Fase 2",'08_Premissas_Custos'!$F$10,1) | Y41: =X41*'08_Premissas_Custos'!$F$7 | Z41: =(X41+Y41)*'08_Premissas_Custos'!$F$6 | AA41: =SUM(X41:Z41) | AB41: Evidências
A42: 37 | B42: CAN | C42: Candidatos & Carreira | D42: Competências e interesses | E42: MVP+1 | F42: Média | H42: 0 | I42: Não | J42: Não | K42: Não | L42: Sim | M42: =IF(F42="Baixa",'08_Premissas_Custos'!$B$6,IF(F42="Média",'08_Premissas_Custos'!$B$7,IF(F42="Alta",'08_Premissas_Custos'!$B$8,'08_Premissas_Custos'!$B$9))) | N42: ='08_Premissas_Custos'!$B$13*M42 | O42: ='08_Premissas_Custos'!$B$14*M42*(1+IF(L42="Sim",0.25,0)) | P42: ='08_Premissas_Custos'!$B$15*M42*(1+IF(I42="Sim",0.20,0)+IF(K42="Sim",0.15,0)) | Q42: ='08_Premissas_Custos'!$B$16*M42*IF(J42="Sim",1.6,0.55) | R42: ='08_Premissas_Custos'!$B$17*M42*IF(I42="Sim",1.8,0.15) | S42: ='08_Premissas_Custos'!$B$18*M42*(1+IF(I42="Sim",0.15)+IF(L42="Sim",0.10)) | T42: ='08_Premissas_Custos'!$B$19*M42*(1+IF(J42="Sim",0.15)) | U42: ='08_Premissas_Custos'!$B$20*M42*IF(K42="Sim",1.8,0.7) | V42: =SUM(N42:U42) | W42: =V42*(1-H42)*IF(E42="Fase 2",'08_Premissas_Custos'!$F$10,1) | X42: =(N42*'08_Premissas_Custos'!$C$13+O42*'08_Premissas_Custos'!$C$14+P42*'08_Premissas_Custos'!$C$15+Q42*'08_Premissas_Custos'!$C$16+R42*'08_Premissas_Custos'!$C$17+S42*'08_Premissas_Custos'!$C$18+T42*'08_Premissas_Custos'!$C$19+U42*'08_Premissas_Custos'!$C$20)*(1-H42)*IF(E42="Fase 2",'08_Premissas_Custos'!$F$10,1) | Y42: =X42*'08_Premissas_Custos'!$F$7 | Z42: =(X42+Y42)*'08_Premissas_Custos'!$F$6 | AA42: =SUM(X42:Z42) | AB42: Skills
A43: 38 | B43: CAN | C43: Candidatos & Carreira | D43: Oportunidades recomendadas | E43: MVP+1 | F43: Alta | H43: 0 | I43: Sim | J43: Não | K43: Não | L43: Sim | M43: =IF(F43="Baixa",'08_Premissas_Custos'!$B$6,IF(F43="Média",'08_Premissas_Custos'!$B$7,IF(F43="Alta",'08_Premissas_Custos'!$B$8,'08_Premissas_Custos'!$B$9))) | N43: ='08_Premissas_Custos'!$B$13*M43 | O43: ='08_Premissas_Custos'!$B$14*M43*(1+IF(L43="Sim",0.25,0)) | P43: ='08_Premissas_Custos'!$B$15*M43*(1+IF(I43="Sim",0.20,0)+IF(K43="Sim",0.15,0)) | Q43: ='08_Premissas_Custos'!$B$16*M43*IF(J43="Sim",1.6,0.55) | R43: ='08_Premissas_Custos'!$B$17*M43*IF(I43="Sim",1.8,0.15) | S43: ='08_Premissas_Custos'!$B$18*M43*(1+IF(I43="Sim",0.15)+IF(L43="Sim",0.10)) | T43: ='08_Premissas_Custos'!$B$19*M43*(1+IF(J43="Sim",0.15)) | U43: ='08_Premissas_Custos'!$B$20*M43*IF(K43="Sim",1.8,0.7) | V43: =SUM(N43:U43) | W43: =V43*(1-H43)*IF(E43="Fase 2",'08_Premissas_Custos'!$F$10,1) | X43: =(N43*'08_Premissas_Custos'!$C$13+O43*'08_Premissas_Custos'!$C$14+P43*'08_Premissas_Custos'!$C$15+Q43*'08_Premissas_Custos'!$C$16+R43*'08_Premissas_Custos'!$C$17+S43*'08_Premissas_Custos'!$C$18+T43*'08_Premissas_Custos'!$C$19+U43*'08_Premissas_Custos'!$C$20)*(1-H43)*IF(E43="Fase 2",'08_Premissas_Custos'!$F$10,1) | Y43: =X43*'08_Premissas_Custos'!$F$7 | Z43: =(X43+Y43)*'08_Premissas_Custos'!$F$6 | AA43: =SUM(X43:Z43) | AB43: Feed
A44: 39 | B44: CAN | C44: Candidatos & Carreira | D44: Detalhe da oportunidade | E44: MVP+1 | F44: Baixa | H44: 0 | I44: Não | J44: Não | K44: Não | L44: Sim | M44: =IF(F44="Baixa",'08_Premissas_Custos'!$B$6,IF(F44="Média",'08_Premissas_Custos'!$B$7,IF(F44="Alta",'08_Premissas_Custos'!$B$8,'08_Premissas_Custos'!$B$9))) | N44: ='08_Premissas_Custos'!$B$13*M44 | O44: ='08_Premissas_Custos'!$B$14*M44*(1+IF(L44="Sim",0.25,0)) | P44: ='08_Premissas_Custos'!$B$15*M44*(1+IF(I44="Sim",0.20,0)+IF(K44="Sim",0.15,0)) | Q44: ='08_Premissas_Custos'!$B$16*M44*IF(J44="Sim",1.6,0.55) | R44: ='08_Premissas_Custos'!$B$17*M44*IF(I44="Sim",1.8,0.15) | S44: ='08_Premissas_Custos'!$B$18*M44*(1+IF(I44="Sim",0.15)+IF(L44="Sim",0.10)) | T44: ='08_Premissas_Custos'!$B$19*M44*(1+IF(J44="Sim",0.15)) | U44: ='08_Premissas_Custos'!$B$20*M44*IF(K44="Sim",1.8,0.7) | V44: =SUM(N44:U44) | W44: =V44*(1-H44)*IF(E44="Fase 2",'08_Premissas_Custos'!$F$10,1) | X44: =(N44*'08_Premissas_Custos'!$C$13+O44*'08_Premissas_Custos'!$C$14+P44*'08_Premissas_Custos'!$C$15+Q44*'08_Premissas_Custos'!$C$16+R44*'08_Premissas_Custos'!$C$17+S44*'08_Premissas_Custos'!$C$18+T44*'08_Premissas_Custos'!$C$19+U44*'08_Premissas_Custos'!$C$20)*(1-H44)*IF(E44="Fase 2",'08_Premissas_Custos'!$F$10,1) | Y44: =X44*'08_Premissas_Custos'!$F$7 | Z44: =(X44+Y44)*'08_Premissas_Custos'!$F$6 | AA44: =SUM(X44:Z44) | AB44: Vaga/projeto
A45: 40 | B45: CAN | C45: Candidatos & Carreira | D45: Candidatura | E45: MVP+1 | F45: Média | H45: 0 | I45: Não | J45: Não | K45: Não | L45: Sim | M45: =IF(F45="Baixa",'08_Premissas_Custos'!$B$6,IF(F45="Média",'08_Premissas_Custos'!$B$7,IF(F45="Alta",'08_Premissas_Custos'!$B$8,'08_Premissas_Custos'!$B$9))) | N45: ='08_Premissas_Custos'!$B$13*M45 | O45: ='08_Premissas_Custos'!$B$14*M45*(1+IF(L45="Sim",0.25,0)) | P45: ='08_Premissas_Custos'!$B$15*M45*(1+IF(I45="Sim",0.20,0)+IF(K45="Sim",0.15,0)) | Q45: ='08_Premissas_Custos'!$B$16*M45*IF(J45="Sim",1.6,0.55) | R45: ='08_Premissas_Custos'!$B$17*M45*IF(I45="Sim",1.8,0.15) | S45: ='08_Premissas_Custos'!$B$18*M45*(1+IF(I45="Sim",0.15)+IF(L45="Sim",0.10)) | T45: ='08_Premissas_Custos'!$B$19*M45*(1+IF(J45="Sim",0.15)) | U45: ='08_Premissas_Custos'!$B$20*M45*IF(K45="Sim",1.8,0.7) | V45: =SUM(N45:U45) | W45: =V45*(1-H45)*IF(E45="Fase 2",'08_Premissas_Custos'!$F$10,1) | X45: =(N45*'08_Premissas_Custos'!$C$13+O45*'08_Premissas_Custos'!$C$14+P45*'08_Premissas_Custos'!$C$15+Q45*'08_Premissas_Custos'!$C$16+R45*'08_Premissas_Custos'!$C$17+S45*'08_Premissas_Custos'!$C$18+T45*'08_Premissas_Custos'!$C$19+U45*'08_Premissas_Custos'!$C$20)*(1-H45)*IF(E45="Fase 2",'08_Premissas_Custos'!$F$10,1) | Y45: =X45*'08_Premissas_Custos'!$F$7 | Z45: =(X45+Y45)*'08_Premissas_Custos'!$F$6 | AA45: =SUM(X45:Z45) | AB45: Aplicação
A46: 41 | B46: CAN | C46: Candidatos & Carreira | D46: Match candidato-vaga | E46: MVP+1 | F46: Muito alta | H46: 0 | I46: Sim | J46: Não | K46: Não | L46: Não | M46: =IF(F46="Baixa",'08_Premissas_Custos'!$B$6,IF(F46="Média",'08_Premissas_Custos'!$B$7,IF(F46="Alta",'08_Premissas_Custos'!$B$8,'08_Premissas_Custos'!$B$9))) | N46: ='08_Premissas_Custos'!$B$13*M46 | O46: ='08_Premissas_Custos'!$B$14*M46*(1+IF(L46="Sim",0.25,0)) | P46: ='08_Premissas_Custos'!$B$15*M46*(1+IF(I46="Sim",0.20,0)+IF(K46="Sim",0.15,0)) | Q46: ='08_Premissas_Custos'!$B$16*M46*IF(J46="Sim",1.6,0.55) | R46: ='08_Premissas_Custos'!$B$17*M46*IF(I46="Sim",1.8,0.15) | S46: ='08_Premissas_Custos'!$B$18*M46*(1+IF(I46="Sim",0.15)+IF(L46="Sim",0.10)) | T46: ='08_Premissas_Custos'!$B$19*M46*(1+IF(J46="Sim",0.15)) | U46: ='08_Premissas_Custos'!$B$20*M46*IF(K46="Sim",1.8,0.7) | V46: =SUM(N46:U46) | W46: =V46*(1-H46)*IF(E46="Fase 2",'08_Premissas_Custos'!$F$10,1) | X46: =(N46*'08_Premissas_Custos'!$C$13+O46*'08_Premissas_Custos'!$C$14+P46*'08_Premissas_Custos'!$C$15+Q46*'08_Premissas_Custos'!$C$16+R46*'08_Premissas_Custos'!$C$17+S46*'08_Premissas_Custos'!$C$18+T46*'08_Premissas_Custos'!$C$19+U46*'08_Premissas_Custos'!$C$20)*(1-H46)*IF(E46="Fase 2",'08_Premissas_Custos'!$F$10,1) | Y46: =X46*'08_Premissas_Custos'!$F$7 | Z46: =(X46+Y46)*'08_Premissas_Custos'!$F$6 | AA46: =SUM(X46:Z46) | AB46: Aderência
A47: 42 | B47: CAN | C47: Candidatos & Carreira | D47: Minha jornada | E47: MVP+1 | F47: Média | H47: 0 | I47: Não | J47: Não | K47: Não | L47: Sim | M47: =IF(F47="Baixa",'08_Premissas_Custos'!$B$6,IF(F47="Média",'08_Premissas_Custos'!$B$7,IF(F47="Alta",'08_Premissas_Custos'!$B$8,'08_Premissas_Custos'!$B$9))) | N47: ='08_Premissas_Custos'!$B$13*M47 | O47: ='08_Premissas_Custos'!$B$14*M47*(1+IF(L47="Sim",0.25,0)) | P47: ='08_Premissas_Custos'!$B$15*M47*(1+IF(I47="Sim",0.20,0)+IF(K47="Sim",0.15,0)) | Q47: ='08_Premissas_Custos'!$B$16*M47*IF(J47="Sim",1.6,0.55) | R47: ='08_Premissas_Custos'!$B$17*M47*IF(I47="Sim",1.8,0.15) | S47: ='08_Premissas_Custos'!$B$18*M47*(1+IF(I47="Sim",0.15)+IF(L47="Sim",0.10)) | T47: ='08_Premissas_Custos'!$B$19*M47*(1+IF(J47="Sim",0.15)) | U47: ='08_Premissas_Custos'!$B$20*M47*IF(K47="Sim",1.8,0.7) | V47: =SUM(N47:U47) | W47: =V47*(1-H47)*IF(E47="Fase 2",'08_Premissas_Custos'!$F$10,1) | X47: =(N47*'08_Premissas_Custos'!$C$13+O47*'08_Premissas_Custos'!$C$14+P47*'08_Premissas_Custos'!$C$15+Q47*'08_Premissas_Custos'!$C$16+R47*'08_Premissas_Custos'!$C$17+S47*'08_Premissas_Custos'!$C$18+T47*'08_Premissas_Custos'!$C$19+U47*'08_Premissas_Custos'!$C$20)*(1-H47)*IF(E47="Fase 2",'08_Premissas_Custos'!$F$10,1) | Y47: =X47*'08_Premissas_Custos'!$F$7 | Z47: =(X47+Y47)*'08_Premissas_Custos'!$F$6 | AA47: =SUM(X47:Z47) | AB47: Progresso
A48: 43 | B48: CAN | C48: Candidatos & Carreira | D48: Capacitação recomendada | E48: MVP+1 | F48: Alta | H48: 0 | I48: Sim | J48: Não | K48: Não | L48: Sim | M48: =IF(F48="Baixa",'08_Premissas_Custos'!$B$6,IF(F48="Média",'08_Premissas_Custos'!$B$7,IF(F48="Alta",'08_Premissas_Custos'!$B$8,'08_Premissas_Custos'!$B$9))) | N48: ='08_Premissas_Custos'!$B$13*M48 | O48: ='08_Premissas_Custos'!$B$14*M48*(1+IF(L48="Sim",0.25,0)) | P48: ='08_Premissas_Custos'!$B$15*M48*(1+IF(I48="Sim",0.20,0)+IF(K48="Sim",0.15,0)) | Q48: ='08_Premissas_Custos'!$B$16*M48*IF(J48="Sim",1.6,0.55) | R48: ='08_Premissas_Custos'!$B$17*M48*IF(I48="Sim",1.8,0.15) | S48: ='08_Premissas_Custos'!$B$18*M48*(1+IF(I48="Sim",0.15)+IF(L48="Sim",0.10)) | T48: ='08_Premissas_Custos'!$B$19*M48*(1+IF(J48="Sim",0.15)) | U48: ='08_Premissas_Custos'!$B$20*M48*IF(K48="Sim",1.8,0.7) | V48: =SUM(N48:U48) | W48: =V48*(1-H48)*IF(E48="Fase 2",'08_Premissas_Custos'!$F$10,1) | X48: =(N48*'08_Premissas_Custos'!$C$13+O48*'08_Premissas_Custos'!$C$14+P48*'08_Premissas_Custos'!$C$15+Q48*'08_Premissas_Custos'!$C$16+R48*'08_Premissas_Custos'!$C$17+S48*'08_Premissas_Custos'!$C$18+T48*'08_Premissas_Custos'!$C$19+U48*'08_Premissas_Custos'!$C$20)*(1-H48)*IF(E48="Fase 2",'08_Premissas_Custos'!$F$10,1) | Y48: =X48*'08_Premissas_Custos'!$F$7 | Z48: =(X48+Y48)*'08_Premissas_Custos'!$F$6 | AA48: =SUM(X48:Z48) | AB48: Gap->trilha
A49: 44 | B49: CAN | C49: Candidatos & Carreira | D49: Mentoria / preparação | E49: MVP+1 | F49: Média | H49: 0 | I49: Não | J49: Não | K49: Não | L49: Sim | M49: =IF(F49="Baixa",'08_Premissas_Custos'!$B$6,IF(F49="Média",'08_Premissas_Custos'!$B$7,IF(F49="Alta",'08_Premissas_Custos'!$B$8,'08_Premissas_Custos'!$B$9))) | N49: ='08_Premissas_Custos'!$B$13*M49 | O49: ='08_Premissas_Custos'!$B$14*M49*(1+IF(L49="Sim",0.25,0)) | P49: ='08_Premissas_Custos'!$B$15*M49*(1+IF(I49="Sim",0.20,0)+IF(K49="Sim",0.15,0)) | Q49: ='08_Premissas_Custos'!$B$16*M49*IF(J49="Sim",1.6,0.55) | R49: ='08_Premissas_Custos'!$B$17*M49*IF(I49="Sim",1.8,0.15) | S49: ='08_Premissas_Custos'!$B$18*M49*(1+IF(I49="Sim",0.15)+IF(L49="Sim",0.10)) | T49: ='08_Premissas_Custos'!$B$19*M49*(1+IF(J49="Sim",0.15)) | U49: ='08_Premissas_Custos'!$B$20*M49*IF(K49="Sim",1.8,0.7) | V49: =SUM(N49:U49) | W49: =V49*(1-H49)*IF(E49="Fase 2",'08_Premissas_Custos'!$F$10,1) | X49: =(N49*'08_Premissas_Custos'!$C$13+O49*'08_Premissas_Custos'!$C$14+P49*'08_Premissas_Custos'!$C$15+Q49*'08_Premissas_Custos'!$C$16+R49*'08_Premissas_Custos'!$C$17+S49*'08_Premissas_Custos'!$C$18+T49*'08_Premissas_Custos'!$C$19+U49*'08_Premissas_Custos'!$C$20)*(1-H49)*IF(E49="Fase 2",'08_Premissas_Custos'!$F$10,1) | Y49: =X49*'08_Premissas_Custos'!$F$7 | Z49: =(X49+Y49)*'08_Premissas_Custos'!$F$6 | AA49: =SUM(X49:Z49) | AB49: Carreira
A50: 45 | B50: CAN | C50: Candidatos & Carreira | D50: Feedbacks do processo | E50: MVP+1 | F50: Média | H50: 0 | I50: Não | J50: Não | K50: Não | L50: Sim | M50: =IF(F50="Baixa",'08_Premissas_Custos'!$B$6,IF(F50="Média",'08_Premissas_Custos'!$B$7,IF(F50="Alta",'08_Premissas_Custos'!$B$8,'08_Premissas_Custos'!$B$9))) | N50: ='08_Premissas_Custos'!$B$13*M50 | O50: ='08_Premissas_Custos'!$B$14*M50*(1+IF(L50="Sim",0.25,0)) | P50: ='08_Premissas_Custos'!$B$15*M50*(1+IF(I50="Sim",0.20,0)+IF(K50="Sim",0.15,0)) | Q50: ='08_Premissas_Custos'!$B$16*M50*IF(J50="Sim",1.6,0.55) | R50: ='08_Premissas_Custos'!$B$17*M50*IF(I50="Sim",1.8,0.15) | S50: ='08_Premissas_Custos'!$B$18*M50*(1+IF(I50="Sim",0.15)+IF(L50="Sim",0.10)) | T50: ='08_Premissas_Custos'!$B$19*M50*(1+IF(J50="Sim",0.15)) | U50: ='08_Premissas_Custos'!$B$20*M50*IF(K50="Sim",1.8,0.7) | V50: =SUM(N50:U50) | W50: =V50*(1-H50)*IF(E50="Fase 2",'08_Premissas_Custos'!$F$10,1) | X50: =(N50*'08_Premissas_Custos'!$C$13+O50*'08_Premissas_Custos'!$C$14+P50*'08_Premissas_Custos'!$C$15+Q50*'08_Premissas_Custos'!$C$16+R50*'08_Premissas_Custos'!$C$17+S50*'08_Premissas_Custos'!$C$18+T50*'08_Premissas_Custos'!$C$19+U50*'08_Premissas_Custos'!$C$20)*(1-H50)*IF(E50="Fase 2",'08_Premissas_Custos'!$F$10,1) | Y50: =X50*'08_Premissas_Custos'!$F$7 | Z50: =(X50+Y50)*'08_Premissas_Custos'!$F$6 | AA50: =SUM(X50:Z50) | AB50: Retorno
A51: 46 | B51: CAN | C51: Candidatos & Carreira | D51: Painel empresa - talentos | E51: MVP+1 | F51: Alta | H51: 0 | I51: Não | J51: Não | K51: Não | L51: Não | M51: =IF(F51="Baixa",'08_Premissas_Custos'!$B$6,IF(F51="Média",'08_Premissas_Custos'!$B$7,IF(F51="Alta",'08_Premissas_Custos'!$B$8,'08_Premissas_Custos'!$B$9))) | N51: ='08_Premissas_Custos'!$B$13*M51 | O51: ='08_Premissas_Custos'!$B$14*M51*(1+IF(L51="Sim",0.25,0)) | P51: ='08_Premissas_Custos'!$B$15*M51*(1+IF(I51="Sim",0.20,0)+IF(K51="Sim",0.15,0)) | Q51: ='08_Premissas_Custos'!$B$16*M51*IF(J51="Sim",1.6,0.55) | R51: ='08_Premissas_Custos'!$B$17*M51*IF(I51="Sim",1.8,0.15) | S51: ='08_Premissas_Custos'!$B$18*M51*(1+IF(I51="Sim",0.15)+IF(L51="Sim",0.10)) | T51: ='08_Premissas_Custos'!$B$19*M51*(1+IF(J51="Sim",0.15)) | U51: ='08_Premissas_Custos'!$B$20*M51*IF(K51="Sim",1.8,0.7) | V51: =SUM(N51:U51) | W51: =V51*(1-H51)*IF(E51="Fase 2",'08_Premissas_Custos'!$F$10,1) | X51: =(N51*'08_Premissas_Custos'!$C$13+O51*'08_Premissas_Custos'!$C$14+P51*'08_Premissas_Custos'!$C$15+Q51*'08_Premissas_Custos'!$C$16+R51*'08_Premissas_Custos'!$C$17+S51*'08_Premissas_Custos'!$C$18+T51*'08_Premissas_Custos'!$C$19+U51*'08_Premissas_Custos'!$C$20)*(1-H51)*IF(E51="Fase 2",'08_Premissas_Custos'!$F$10,1) | Y51: =X51*'08_Premissas_Custos'!$F$7 | Z51: =(X51+Y51)*'08_Premissas_Custos'!$F$6 | AA51: =SUM(X51:Z51) | AB51: Shortlist
A52: 47 | B52: CAN | C52: Candidatos & Carreira | D52: Inteligência de vagas | E52: Fase 2 | F52: Muito alta | H52: 0 | I52: Sim | J52: Não | K52: Não | L52: Não | M52: =IF(F52="Baixa",'08_Premissas_Custos'!$B$6,IF(F52="Média",'08_Premissas_Custos'!$B$7,IF(F52="Alta",'08_Premissas_Custos'!$B$8,'08_Premissas_Custos'!$B$9))) | N52: ='08_Premissas_Custos'!$B$13*M52 | O52: ='08_Premissas_Custos'!$B$14*M52*(1+IF(L52="Sim",0.25,0)) | P52: ='08_Premissas_Custos'!$B$15*M52*(1+IF(I52="Sim",0.20,0)+IF(K52="Sim",0.15,0)) | Q52: ='08_Premissas_Custos'!$B$16*M52*IF(J52="Sim",1.6,0.55) | R52: ='08_Premissas_Custos'!$B$17*M52*IF(I52="Sim",1.8,0.15) | S52: ='08_Premissas_Custos'!$B$18*M52*(1+IF(I52="Sim",0.15)+IF(L52="Sim",0.10)) | T52: ='08_Premissas_Custos'!$B$19*M52*(1+IF(J52="Sim",0.15)) | U52: ='08_Premissas_Custos'!$B$20*M52*IF(K52="Sim",1.8,0.7) | V52: =SUM(N52:U52) | W52: =V52*(1-H52)*IF(E52="Fase 2",'08_Premissas_Custos'!$F$10,1) | X52: =(N52*'08_Premissas_Custos'!$C$13+O52*'08_Premissas_Custos'!$C$14+P52*'08_Premissas_Custos'!$C$15+Q52*'08_Premissas_Custos'!$C$16+R52*'08_Premissas_Custos'!$C$17+S52*'08_Premissas_Custos'!$C$18+T52*'08_Premissas_Custos'!$C$19+U52*'08_Premissas_Custos'!$C$20)*(1-H52)*IF(E52="Fase 2",'08_Premissas_Custos'!$F$10,1) | Y52: =X52*'08_Premissas_Custos'!$F$7 | Z52: =(X52+Y52)*'08_Premissas_Custos'!$F$6 | AA52: =SUM(X52:Z52) | AB52: Requisitos por evidência
A53: 48 | B53: FOR | C53: Fornecedores & Negócios | D53: Perfil do fornecedor | E53: MVP+1 | F53: Média | G53: Perfil do fornecedor | H53: 0.45 | I53: Não | J53: Não | K53: Não | L53: Não | M53: =IF(F53="Baixa",'08_Premissas_Custos'!$B$6,IF(F53="Média",'08_Premissas_Custos'!$B$7,IF(F53="Alta",'08_Premissas_Custos'!$B$8,'08_Premissas_Custos'!$B$9))) | N53: ='08_Premissas_Custos'!$B$13*M53 | O53: ='08_Premissas_Custos'!$B$14*M53*(1+IF(L53="Sim",0.25,0)) | P53: ='08_Premissas_Custos'!$B$15*M53*(1+IF(I53="Sim",0.20,0)+IF(K53="Sim",0.15,0)) | Q53: ='08_Premissas_Custos'!$B$16*M53*IF(J53="Sim",1.6,0.55) | R53: ='08_Premissas_Custos'!$B$17*M53*IF(I53="Sim",1.8,0.15) | S53: ='08_Premissas_Custos'!$B$18*M53*(1+IF(I53="Sim",0.15)+IF(L53="Sim",0.10)) | T53: ='08_Premissas_Custos'!$B$19*M53*(1+IF(J53="Sim",0.15)) | U53: ='08_Premissas_Custos'!$B$20*M53*IF(K53="Sim",1.8,0.7) | V53: =SUM(N53:U53) | W53: =V53*(1-H53)*IF(E53="Fase 2",'08_Premissas_Custos'!$F$10,1) | X53: =(N53*'08_Premissas_Custos'!$C$13+O53*'08_Premissas_Custos'!$C$14+P53*'08_Premissas_Custos'!$C$15+Q53*'08_Premissas_Custos'!$C$16+R53*'08_Premissas_Custos'!$C$17+S53*'08_Premissas_Custos'!$C$18+T53*'08_Premissas_Custos'!$C$19+U53*'08_Premissas_Custos'!$C$20)*(1-H53)*IF(E53="Fase 2",'08_Premissas_Custos'!$F$10,1) | Y53: =X53*'08_Premissas_Custos'!$F$7 | Z53: =(X53+Y53)*'08_Premissas_Custos'!$F$6 | AA53: =SUM(X53:Z53) | AB53: Capacidades
A54: 49 | B54: FOR | C54: Fornecedores & Negócios | D54: Documentos e compliance | E54: MVP+1 | F54: Alta | H54: 0 | I54: Não | J54: Não | K54: Sim | L54: Não | M54: =IF(F54="Baixa",'08_Premissas_Custos'!$B$6,IF(F54="Média",'08_Premissas_Custos'!$B$7,IF(F54="Alta",'08_Premissas_Custos'!$B$8,'08_Premissas_Custos'!$B$9))) | N54: ='08_Premissas_Custos'!$B$13*M54 | O54: ='08_Premissas_Custos'!$B$14*M54*(1+IF(L54="Sim",0.25,0)) | P54: ='08_Premissas_Custos'!$B$15*M54*(1+IF(I54="Sim",0.20,0)+IF(K54="Sim",0.15,0)) | Q54: ='08_Premissas_Custos'!$B$16*M54*IF(J54="Sim",1.6,0.55) | R54: ='08_Premissas_Custos'!$B$17*M54*IF(I54="Sim",1.8,0.15) | S54: ='08_Premissas_Custos'!$B$18*M54*(1+IF(I54="Sim",0.15)+IF(L54="Sim",0.10)) | T54: ='08_Premissas_Custos'!$B$19*M54*(1+IF(J54="Sim",0.15)) | U54: ='08_Premissas_Custos'!$B$20*M54*IF(K54="Sim",1.8,0.7) | V54: =SUM(N54:U54) | W54: =V54*(1-H54)*IF(E54="Fase 2",'08_Premissas_Custos'!$F$10,1) | X54: =(N54*'08_Premissas_Custos'!$C$13+O54*'08_Premissas_Custos'!$C$14+P54*'08_Premissas_Custos'!$C$15+Q54*'08_Premissas_Custos'!$C$16+R54*'08_Premissas_Custos'!$C$17+S54*'08_Premissas_Custos'!$C$18+T54*'08_Premissas_Custos'!$C$19+U54*'08_Premissas_Custos'!$C$20)*(1-H54)*IF(E54="Fase 2",'08_Premissas_Custos'!$F$10,1) | Y54: =X54*'08_Premissas_Custos'!$F$7 | Z54: =(X54+Y54)*'08_Premissas_Custos'!$F$6 | AA54: =SUM(X54:Z54) | AB54: Certificações
A55: 50 | B55: FOR | C55: Fornecedores & Negócios | D55: Maturidade | E55: MVP+1 | F55: Alta | H55: 0 | I55: Não | J55: Não | K55: Não | L55: Não | M55: =IF(F55="Baixa",'08_Premissas_Custos'!$B$6,IF(F55="Média",'08_Premissas_Custos'!$B$7,IF(F55="Alta",'08_Premissas_Custos'!$B$8,'08_Premissas_Custos'!$B$9))) | N55: ='08_Premissas_Custos'!$B$13*M55 | O55: ='08_Premissas_Custos'!$B$14*M55*(1+IF(L55="Sim",0.25,0)) | P55: ='08_Premissas_Custos'!$B$15*M55*(1+IF(I55="Sim",0.20,0)+IF(K55="Sim",0.15,0)) | Q55: ='08_Premissas_Custos'!$B$16*M55*IF(J55="Sim",1.6,0.55) | R55: ='08_Premissas_Custos'!$B$17*M55*IF(I55="Sim",1.8,0.15) | S55: ='08_Premissas_Custos'!$B$18*M55*(1+IF(I55="Sim",0.15)+IF(L55="Sim",0.10)) | T55: ='08_Premissas_Custos'!$B$19*M55*(1+IF(J55="Sim",0.15)) | U55: ='08_Premissas_Custos'!$B$20*M55*IF(K55="Sim",1.8,0.7) | V55: =SUM(N55:U55) | W55: =V55*(1-H55)*IF(E55="Fase 2",'08_Premissas_Custos'!$F$10,1) | X55: =(N55*'08_Premissas_Custos'!$C$13+O55*'08_Premissas_Custos'!$C$14+P55*'08_Premissas_Custos'!$C$15+Q55*'08_Premissas_Custos'!$C$16+R55*'08_Premissas_Custos'!$C$17+S55*'08_Premissas_Custos'!$C$18+T55*'08_Premissas_Custos'!$C$19+U55*'08_Premissas_Custos'!$C$20)*(1-H55)*IF(E55="Fase 2",'08_Premissas_Custos'!$F$10,1) | Y55: =X55*'08_Premissas_Custos'!$F$7 | Z55: =(X55+Y55)*'08_Premissas_Custos'!$F$6 | AA55: =SUM(X55:Z55) | AB55: Diagnóstico
A56: 51 | B56: FOR | C56: Fornecedores & Negócios | D56: Plano de desenvolvimento | E56: MVP+1 | F56: Alta | G56: Plano de desenvolvimento | H56: 0.45 | I56: Não | J56: Não | K56: Não | L56: Não | M56: =IF(F56="Baixa",'08_Premissas_Custos'!$B$6,IF(F56="Média",'08_Premissas_Custos'!$B$7,IF(F56="Alta",'08_Premissas_Custos'!$B$8,'08_Premissas_Custos'!$B$9))) | N56: ='08_Premissas_Custos'!$B$13*M56 | O56: ='08_Premissas_Custos'!$B$14*M56*(1+IF(L56="Sim",0.25,0)) | P56: ='08_Premissas_Custos'!$B$15*M56*(1+IF(I56="Sim",0.20,0)+IF(K56="Sim",0.15,0)) | Q56: ='08_Premissas_Custos'!$B$16*M56*IF(J56="Sim",1.6,0.55) | R56: ='08_Premissas_Custos'!$B$17*M56*IF(I56="Sim",1.8,0.15) | S56: ='08_Premissas_Custos'!$B$18*M56*(1+IF(I56="Sim",0.15)+IF(L56="Sim",0.10)) | T56: ='08_Premissas_Custos'!$B$19*M56*(1+IF(J56="Sim",0.15)) | U56: ='08_Premissas_Custos'!$B$20*M56*IF(K56="Sim",1.8,0.7) | V56: =SUM(N56:U56) | W56: =V56*(1-H56)*IF(E56="Fase 2",'08_Premissas_Custos'!$F$10,1) | X56: =(N56*'08_Premissas_Custos'!$C$13+O56*'08_Premissas_Custos'!$C$14+P56*'08_Premissas_Custos'!$C$15+Q56*'08_Premissas_Custos'!$C$16+R56*'08_Premissas_Custos'!$C$17+S56*'08_Premissas_Custos'!$C$18+T56*'08_Premissas_Custos'!$C$19+U56*'08_Premissas_Custos'!$C$20)*(1-H56)*IF(E56="Fase 2",'08_Premissas_Custos'!$F$10,1) | Y56: =X56*'08_Premissas_Custos'!$F$7 | Z56: =(X56+Y56)*'08_Premissas_Custos'!$F$6 | AA56: =SUM(X56:Z56) | AB56: Gaps
A57: 52 | B57: FOR | C57: Fornecedores & Negócios | D57: Trilhas / apoio | E57: Fase 2 | F57: Média | H57: 0 | I57: Não | J57: Não | K57: Não | L57: Não | M57: =IF(F57="Baixa",'08_Premissas_Custos'!$B$6,IF(F57="Média",'08_Premissas_Custos'!$B$7,IF(F57="Alta",'08_Premissas_Custos'!$B$8,'08_Premissas_Custos'!$B$9))) | N57: ='08_Premissas_Custos'!$B$13*M57 | O57: ='08_Premissas_Custos'!$B$14*M57*(1+IF(L57="Sim",0.25,0)) | P57: ='08_Premissas_Custos'!$B$15*M57*(1+IF(I57="Sim",0.20,0)+IF(K57="Sim",0.15,0)) | Q57: ='08_Premissas_Custos'!$B$16*M57*IF(J57="Sim",1.6,0.55) | R57: ='08_Premissas_Custos'!$B$17*M57*IF(I57="Sim",1.8,0.15) | S57: ='08_Premissas_Custos'!$B$18*M57*(1+IF(I57="Sim",0.15)+IF(L57="Sim",0.10)) | T57: ='08_Premissas_Custos'!$B$19*M57*(1+IF(J57="Sim",0.15)) | U57: ='08_Premissas_Custos'!$B$20*M57*IF(K57="Sim",1.8,0.7) | V57: =SUM(N57:U57) | W57: =V57*(1-H57)*IF(E57="Fase 2",'08_Premissas_Custos'!$F$10,1) | X57: =(N57*'08_Premissas_Custos'!$C$13+O57*'08_Premissas_Custos'!$C$14+P57*'08_Premissas_Custos'!$C$15+Q57*'08_Premissas_Custos'!$C$16+R57*'08_Premissas_Custos'!$C$17+S57*'08_Premissas_Custos'!$C$18+T57*'08_Premissas_Custos'!$C$19+U57*'08_Premissas_Custos'!$C$20)*(1-H57)*IF(E57="Fase 2",'08_Premissas_Custos'!$F$10,1) | Y57: =X57*'08_Premissas_Custos'!$F$7 | Z57: =(X57+Y57)*'08_Premissas_Custos'!$F$6 | AA57: =SUM(X57:Z57) | AB57: Cursos/crédito
A58: 53 | B58: FOR | C58: Fornecedores & Negócios | D58: Oportunidades / demandas | E58: MVP+1 | F58: Média | H58: 0 | I58: Não | J58: Não | K58: Não | L58: Não | M58: =IF(F58="Baixa",'08_Premissas_Custos'!$B$6,IF(F58="Média",'08_Premissas_Custos'!$B$7,IF(F58="Alta",'08_Premissas_Custos'!$B$8,'08_Premissas_Custos'!$B$9))) | N58: ='08_Premissas_Custos'!$B$13*M58 | O58: ='08_Premissas_Custos'!$B$14*M58*(1+IF(L58="Sim",0.25,0)) | P58: ='08_Premissas_Custos'!$B$15*M58*(1+IF(I58="Sim",0.20,0)+IF(K58="Sim",0.15,0)) | Q58: ='08_Premissas_Custos'!$B$16*M58*IF(J58="Sim",1.6,0.55) | R58: ='08_Premissas_Custos'!$B$17*M58*IF(I58="Sim",1.8,0.15) | S58: ='08_Premissas_Custos'!$B$18*M58*(1+IF(I58="Sim",0.15)+IF(L58="Sim",0.10)) | T58: ='08_Premissas_Custos'!$B$19*M58*(1+IF(J58="Sim",0.15)) | U58: ='08_Premissas_Custos'!$B$20*M58*IF(K58="Sim",1.8,0.7) | V58: =SUM(N58:U58) | W58: =V58*(1-H58)*IF(E58="Fase 2",'08_Premissas_Custos'!$F$10,1) | X58: =(N58*'08_Premissas_Custos'!$C$13+O58*'08_Premissas_Custos'!$C$14+P58*'08_Premissas_Custos'!$C$15+Q58*'08_Premissas_Custos'!$C$16+R58*'08_Premissas_Custos'!$C$17+S58*'08_Premissas_Custos'!$C$18+T58*'08_Premissas_Custos'!$C$19+U58*'08_Premissas_Custos'!$C$20)*(1-H58)*IF(E58="Fase 2",'08_Premissas_Custos'!$F$10,1) | Y58: =X58*'08_Premissas_Custos'!$F$7 | Z58: =(X58+Y58)*'08_Premissas_Custos'!$F$6 | AA58: =SUM(X58:Z58) | AB58: Compras
A59: 54 | B59: FOR | C59: Fornecedores & Negócios | D59: Detalhe da demanda | E59: MVP+1 | F59: Baixa | H59: 0 | I59: Não | J59: Não | K59: Não | L59: Não | M59: =IF(F59="Baixa",'08_Premissas_Custos'!$B$6,IF(F59="Média",'08_Premissas_Custos'!$B$7,IF(F59="Alta",'08_Premissas_Custos'!$B$8,'08_Premissas_Custos'!$B$9))) | N59: ='08_Premissas_Custos'!$B$13*M59 | O59: ='08_Premissas_Custos'!$B$14*M59*(1+IF(L59="Sim",0.25,0)) | P59: ='08_Premissas_Custos'!$B$15*M59*(1+IF(I59="Sim",0.20,0)+IF(K59="Sim",0.15,0)) | Q59: ='08_Premissas_Custos'!$B$16*M59*IF(J59="Sim",1.6,0.55) | R59: ='08_Premissas_Custos'!$B$17*M59*IF(I59="Sim",1.8,0.15) | S59: ='08_Premissas_Custos'!$B$18*M59*(1+IF(I59="Sim",0.15)+IF(L59="Sim",0.10)) | T59: ='08_Premissas_Custos'!$B$19*M59*(1+IF(J59="Sim",0.15)) | U59: ='08_Premissas_Custos'!$B$20*M59*IF(K59="Sim",1.8,0.7) | V59: =SUM(N59:U59) | W59: =V59*(1-H59)*IF(E59="Fase 2",'08_Premissas_Custos'!$F$10,1) | X59: =(N59*'08_Premissas_Custos'!$C$13+O59*'08_Premissas_Custos'!$C$14+P59*'08_Premissas_Custos'!$C$15+Q59*'08_Premissas_Custos'!$C$16+R59*'08_Premissas_Custos'!$C$17+S59*'08_Premissas_Custos'!$C$18+T59*'08_Premissas_Custos'!$C$19+U59*'08_Premissas_Custos'!$C$20)*(1-H59)*IF(E59="Fase 2",'08_Premissas_Custos'!$F$10,1) | Y59: =X59*'08_Premissas_Custos'!$F$7 | Z59: =(X59+Y59)*'08_Premissas_Custos'!$F$6 | AA59: =SUM(X59:Z59) | AB59: Critérios
A60: 55 | B60: FOR | C60: Fornecedores & Negócios | D60: Match fornecedor-demanda | E60: MVP+1 | F60: Muito alta | H60: 0 | I60: Sim | J60: Não | K60: Não | L60: Não | M60: =IF(F60="Baixa",'08_Premissas_Custos'!$B$6,IF(F60="Média",'08_Premissas_Custos'!$B$7,IF(F60="Alta",'08_Premissas_Custos'!$B$8,'08_Premissas_Custos'!$B$9))) | N60: ='08_Premissas_Custos'!$B$13*M60 | O60: ='08_Premissas_Custos'!$B$14*M60*(1+IF(L60="Sim",0.25,0)) | P60: ='08_Premissas_Custos'!$B$15*M60*(1+IF(I60="Sim",0.20,0)+IF(K60="Sim",0.15,0)) | Q60: ='08_Premissas_Custos'!$B$16*M60*IF(J60="Sim",1.6,0.55) | R60: ='08_Premissas_Custos'!$B$17*M60*IF(I60="Sim",1.8,0.15) | S60: ='08_Premissas_Custos'!$B$18*M60*(1+IF(I60="Sim",0.15)+IF(L60="Sim",0.10)) | T60: ='08_Premissas_Custos'!$B$19*M60*(1+IF(J60="Sim",0.15)) | U60: ='08_Premissas_Custos'!$B$20*M60*IF(K60="Sim",1.8,0.7) | V60: =SUM(N60:U60) | W60: =V60*(1-H60)*IF(E60="Fase 2",'08_Premissas_Custos'!$F$10,1) | X60: =(N60*'08_Premissas_Custos'!$C$13+O60*'08_Premissas_Custos'!$C$14+P60*'08_Premissas_Custos'!$C$15+Q60*'08_Premissas_Custos'!$C$16+R60*'08_Premissas_Custos'!$C$17+S60*'08_Premissas_Custos'!$C$18+T60*'08_Premissas_Custos'!$C$19+U60*'08_Premissas_Custos'!$C$20)*(1-H60)*IF(E60="Fase 2",'08_Premissas_Custos'!$F$10,1) | Y60: =X60*'08_Premissas_Custos'!$F$7 | Z60: =(X60+Y60)*'08_Premissas_Custos'!$F$6 | AA60: =SUM(X60:Z60) | AB60: Aderência
A61: 56 | B61: FOR | C61: Fornecedores & Negócios | D61: Painel empresa compradora | E61: MVP+1 | F61: Alta | H61: 0 | I61: Não | J61: Não | K61: Não | L61: Não | M61: =IF(F61="Baixa",'08_Premissas_Custos'!$B$6,IF(F61="Média",'08_Premissas_Custos'!$B$7,IF(F61="Alta",'08_Premissas_Custos'!$B$8,'08_Premissas_Custos'!$B$9))) | N61: ='08_Premissas_Custos'!$B$13*M61 | O61: ='08_Premissas_Custos'!$B$14*M61*(1+IF(L61="Sim",0.25,0)) | P61: ='08_Premissas_Custos'!$B$15*M61*(1+IF(I61="Sim",0.20,0)+IF(K61="Sim",0.15,0)) | Q61: ='08_Premissas_Custos'!$B$16*M61*IF(J61="Sim",1.6,0.55) | R61: ='08_Premissas_Custos'!$B$17*M61*IF(I61="Sim",1.8,0.15) | S61: ='08_Premissas_Custos'!$B$18*M61*(1+IF(I61="Sim",0.15)+IF(L61="Sim",0.10)) | T61: ='08_Premissas_Custos'!$B$19*M61*(1+IF(J61="Sim",0.15)) | U61: ='08_Premissas_Custos'!$B$20*M61*IF(K61="Sim",1.8,0.7) | V61: =SUM(N61:U61) | W61: =V61*(1-H61)*IF(E61="Fase 2",'08_Premissas_Custos'!$F$10,1) | X61: =(N61*'08_Premissas_Custos'!$C$13+O61*'08_Premissas_Custos'!$C$14+P61*'08_Premissas_Custos'!$C$15+Q61*'08_Premissas_Custos'!$C$16+R61*'08_Premissas_Custos'!$C$17+S61*'08_Premissas_Custos'!$C$18+T61*'08_Premissas_Custos'!$C$19+U61*'08_Premissas_Custos'!$C$20)*(1-H61)*IF(E61="Fase 2",'08_Premissas_Custos'!$F$10,1) | Y61: =X61*'08_Premissas_Custos'!$F$7 | Z61: =(X61+Y61)*'08_Premissas_Custos'!$F$6 | AA61: =SUM(X61:Z61) | AB61: Criar demanda
A62: 57 | B62: FOR | C62: Fornecedores & Negócios | D62: Reuniões / conexões | E62: MVP+1 | F62: Média | H62: 0 | I62: Não | J62: Não | K62: Não | L62: Não | M62: =IF(F62="Baixa",'08_Premissas_Custos'!$B$6,IF(F62="Média",'08_Premissas_Custos'!$B$7,IF(F62="Alta",'08_Premissas_Custos'!$B$8,'08_Premissas_Custos'!$B$9))) | N62: ='08_Premissas_Custos'!$B$13*M62 | O62: ='08_Premissas_Custos'!$B$14*M62*(1+IF(L62="Sim",0.25,0)) | P62: ='08_Premissas_Custos'!$B$15*M62*(1+IF(I62="Sim",0.20,0)+IF(K62="Sim",0.15,0)) | Q62: ='08_Premissas_Custos'!$B$16*M62*IF(J62="Sim",1.6,0.55) | R62: ='08_Premissas_Custos'!$B$17*M62*IF(I62="Sim",1.8,0.15) | S62: ='08_Premissas_Custos'!$B$18*M62*(1+IF(I62="Sim",0.15)+IF(L62="Sim",0.10)) | T62: ='08_Premissas_Custos'!$B$19*M62*(1+IF(J62="Sim",0.15)) | U62: ='08_Premissas_Custos'!$B$20*M62*IF(K62="Sim",1.8,0.7) | V62: =SUM(N62:U62) | W62: =V62*(1-H62)*IF(E62="Fase 2",'08_Premissas_Custos'!$F$10,1) | X62: =(N62*'08_Premissas_Custos'!$C$13+O62*'08_Premissas_Custos'!$C$14+P62*'08_Premissas_Custos'!$C$15+Q62*'08_Premissas_Custos'!$C$16+R62*'08_Premissas_Custos'!$C$17+S62*'08_Premissas_Custos'!$C$18+T62*'08_Premissas_Custos'!$C$19+U62*'08_Premissas_Custos'!$C$20)*(1-H62)*IF(E62="Fase 2",'08_Premissas_Custos'!$F$10,1) | Y62: =X62*'08_Premissas_Custos'!$F$7 | Z62: =(X62+Y62)*'08_Premissas_Custos'!$F$6 | AA62: =SUM(X62:Z62) | AB62: Agenda
A63: 58 | B63: FOR | C63: Fornecedores & Negócios | D63: Propostas | E63: Fase 2 | F63: Alta | H63: 0 | I63: Não | J63: Não | K63: Não | L63: Não | M63: =IF(F63="Baixa",'08_Premissas_Custos'!$B$6,IF(F63="Média",'08_Premissas_Custos'!$B$7,IF(F63="Alta",'08_Premissas_Custos'!$B$8,'08_Premissas_Custos'!$B$9))) | N63: ='08_Premissas_Custos'!$B$13*M63 | O63: ='08_Premissas_Custos'!$B$14*M63*(1+IF(L63="Sim",0.25,0)) | P63: ='08_Premissas_Custos'!$B$15*M63*(1+IF(I63="Sim",0.20,0)+IF(K63="Sim",0.15,0)) | Q63: ='08_Premissas_Custos'!$B$16*M63*IF(J63="Sim",1.6,0.55) | R63: ='08_Premissas_Custos'!$B$17*M63*IF(I63="Sim",1.8,0.15) | S63: ='08_Premissas_Custos'!$B$18*M63*(1+IF(I63="Sim",0.15)+IF(L63="Sim",0.10)) | T63: ='08_Premissas_Custos'!$B$19*M63*(1+IF(J63="Sim",0.15)) | U63: ='08_Premissas_Custos'!$B$20*M63*IF(K63="Sim",1.8,0.7) | V63: =SUM(N63:U63) | W63: =V63*(1-H63)*IF(E63="Fase 2",'08_Premissas_Custos'!$F$10,1) | X63: =(N63*'08_Premissas_Custos'!$C$13+O63*'08_Premissas_Custos'!$C$14+P63*'08_Premissas_Custos'!$C$15+Q63*'08_Premissas_Custos'!$C$16+R63*'08_Premissas_Custos'!$C$17+S63*'08_Premissas_Custos'!$C$18+T63*'08_Premissas_Custos'!$C$19+U63*'08_Premissas_Custos'!$C$20)*(1-H63)*IF(E63="Fase 2",'08_Premissas_Custos'!$F$10,1) | Y63: =X63*'08_Premissas_Custos'!$F$7 | Z63: =(X63+Y63)*'08_Premissas_Custos'!$F$6 | AA63: =SUM(X63:Z63) | AB63: Pipeline
A64: 59 | B64: FOR | C64: Fornecedores & Negócios | D64: Negociações | E64: Fase 2 | F64: Alta | H64: 0 | I64: Não | J64: Não | K64: Não | L64: Não | M64: =IF(F64="Baixa",'08_Premissas_Custos'!$B$6,IF(F64="Média",'08_Premissas_Custos'!$B$7,IF(F64="Alta",'08_Premissas_Custos'!$B$8,'08_Premissas_Custos'!$B$9))) | N64: ='08_Premissas_Custos'!$B$13*M64 | O64: ='08_Premissas_Custos'!$B$14*M64*(1+IF(L64="Sim",0.25,0)) | P64: ='08_Premissas_Custos'!$B$15*M64*(1+IF(I64="Sim",0.20,0)+IF(K64="Sim",0.15,0)) | Q64: ='08_Premissas_Custos'!$B$16*M64*IF(J64="Sim",1.6,0.55) | R64: ='08_Premissas_Custos'!$B$17*M64*IF(I64="Sim",1.8,0.15) | S64: ='08_Premissas_Custos'!$B$18*M64*(1+IF(I64="Sim",0.15)+IF(L64="Sim",0.10)) | T64: ='08_Premissas_Custos'!$B$19*M64*(1+IF(J64="Sim",0.15)) | U64: ='08_Premissas_Custos'!$B$20*M64*IF(K64="Sim",1.8,0.7) | V64: =SUM(N64:U64) | W64: =V64*(1-H64)*IF(E64="Fase 2",'08_Premissas_Custos'!$F$10,1) | X64: =(N64*'08_Premissas_Custos'!$C$13+O64*'08_Premissas_Custos'!$C$14+P64*'08_Premissas_Custos'!$C$15+Q64*'08_Premissas_Custos'!$C$16+R64*'08_Premissas_Custos'!$C$17+S64*'08_Premissas_Custos'!$C$18+T64*'08_Premissas_Custos'!$C$19+U64*'08_Premissas_Custos'!$C$20)*(1-H64)*IF(E64="Fase 2",'08_Premissas_Custos'!$F$10,1) | Y64: =X64*'08_Premissas_Custos'!$F$7 | Z64: =(X64+Y64)*'08_Premissas_Custos'!$F$6 | AA64: =SUM(X64:Z64) | AB64: Pipeline
A65: 60 | B65: FOR | C65: Fornecedores & Negócios | D65: Contratos / negócios | E65: Fase 2 | F65: Alta | H65: 0 | I65: Não | J65: Não | K65: Não | L65: Não | M65: =IF(F65="Baixa",'08_Premissas_Custos'!$B$6,IF(F65="Média",'08_Premissas_Custos'!$B$7,IF(F65="Alta",'08_Premissas_Custos'!$B$8,'08_Premissas_Custos'!$B$9))) | N65: ='08_Premissas_Custos'!$B$13*M65 | O65: ='08_Premissas_Custos'!$B$14*M65*(1+IF(L65="Sim",0.25,0)) | P65: ='08_Premissas_Custos'!$B$15*M65*(1+IF(I65="Sim",0.20,0)+IF(K65="Sim",0.15,0)) | Q65: ='08_Premissas_Custos'!$B$16*M65*IF(J65="Sim",1.6,0.55) | R65: ='08_Premissas_Custos'!$B$17*M65*IF(I65="Sim",1.8,0.15) | S65: ='08_Premissas_Custos'!$B$18*M65*(1+IF(I65="Sim",0.15)+IF(L65="Sim",0.10)) | T65: ='08_Premissas_Custos'!$B$19*M65*(1+IF(J65="Sim",0.15)) | U65: ='08_Premissas_Custos'!$B$20*M65*IF(K65="Sim",1.8,0.7) | V65: =SUM(N65:U65) | W65: =V65*(1-H65)*IF(E65="Fase 2",'08_Premissas_Custos'!$F$10,1) | X65: =(N65*'08_Premissas_Custos'!$C$13+O65*'08_Premissas_Custos'!$C$14+P65*'08_Premissas_Custos'!$C$15+Q65*'08_Premissas_Custos'!$C$16+R65*'08_Premissas_Custos'!$C$17+S65*'08_Premissas_Custos'!$C$18+T65*'08_Premissas_Custos'!$C$19+U65*'08_Premissas_Custos'!$C$20)*(1-H65)*IF(E65="Fase 2",'08_Premissas_Custos'!$F$10,1) | Y65: =X65*'08_Premissas_Custos'!$F$7 | Z65: =(X65+Y65)*'08_Premissas_Custos'!$F$6 | AA65: =SUM(X65:Z65) | AB65: Conversão
A66: 61 | B66: FOR | C66: Fornecedores & Negócios | D66: Indicadores do ecossistema | E66: MVP+1 | F66: Alta | G66: Indicadores do ecossistema | H66: 0.45 | I66: Não | J66: Sim | K66: Não | L66: Não | M66: =IF(F66="Baixa",'08_Premissas_Custos'!$B$6,IF(F66="Média",'08_Premissas_Custos'!$B$7,IF(F66="Alta",'08_Premissas_Custos'!$B$8,'08_Premissas_Custos'!$B$9))) | N66: ='08_Premissas_Custos'!$B$13*M66 | O66: ='08_Premissas_Custos'!$B$14*M66*(1+IF(L66="Sim",0.25,0)) | P66: ='08_Premissas_Custos'!$B$15*M66*(1+IF(I66="Sim",0.20,0)+IF(K66="Sim",0.15,0)) | Q66: ='08_Premissas_Custos'!$B$16*M66*IF(J66="Sim",1.6,0.55) | R66: ='08_Premissas_Custos'!$B$17*M66*IF(I66="Sim",1.8,0.15) | S66: ='08_Premissas_Custos'!$B$18*M66*(1+IF(I66="Sim",0.15)+IF(L66="Sim",0.10)) | T66: ='08_Premissas_Custos'!$B$19*M66*(1+IF(J66="Sim",0.15)) | U66: ='08_Premissas_Custos'!$B$20*M66*IF(K66="Sim",1.8,0.7) | V66: =SUM(N66:U66) | W66: =V66*(1-H66)*IF(E66="Fase 2",'08_Premissas_Custos'!$F$10,1) | X66: =(N66*'08_Premissas_Custos'!$C$13+O66*'08_Premissas_Custos'!$C$14+P66*'08_Premissas_Custos'!$C$15+Q66*'08_Premissas_Custos'!$C$16+R66*'08_Premissas_Custos'!$C$17+S66*'08_Premissas_Custos'!$C$18+T66*'08_Premissas_Custos'!$C$19+U66*'08_Premissas_Custos'!$C$20)*(1-H66)*IF(E66="Fase 2",'08_Premissas_Custos'!$F$10,1) | Y66: =X66*'08_Premissas_Custos'!$F$7 | Z66: =(X66+Y66)*'08_Premissas_Custos'!$F$6 | AA66: =SUM(X66:Z66) | AB66: Impacto
A67: 62 | B67: ACA | C67: Acadêmico / Universidades | D67: Portal da universidade | E67: Fase 2 | F67: Média | H67: 0 | I67: Não | J67: Não | K67: Não | L67: Não | M67: =IF(F67="Baixa",'08_Premissas_Custos'!$B$6,IF(F67="Média",'08_Premissas_Custos'!$B$7,IF(F67="Alta",'08_Premissas_Custos'!$B$8,'08_Premissas_Custos'!$B$9))) | N67: ='08_Premissas_Custos'!$B$13*M67 | O67: ='08_Premissas_Custos'!$B$14*M67*(1+IF(L67="Sim",0.25,0)) | P67: ='08_Premissas_Custos'!$B$15*M67*(1+IF(I67="Sim",0.20,0)+IF(K67="Sim",0.15,0)) | Q67: ='08_Premissas_Custos'!$B$16*M67*IF(J67="Sim",1.6,0.55) | R67: ='08_Premissas_Custos'!$B$17*M67*IF(I67="Sim",1.8,0.15) | S67: ='08_Premissas_Custos'!$B$18*M67*(1+IF(I67="Sim",0.15)+IF(L67="Sim",0.10)) | T67: ='08_Premissas_Custos'!$B$19*M67*(1+IF(J67="Sim",0.15)) | U67: ='08_Premissas_Custos'!$B$20*M67*IF(K67="Sim",1.8,0.7) | V67: =SUM(N67:U67) | W67: =V67*(1-H67)*IF(E67="Fase 2",'08_Premissas_Custos'!$F$10,1) | X67: =(N67*'08_Premissas_Custos'!$C$13+O67*'08_Premissas_Custos'!$C$14+P67*'08_Premissas_Custos'!$C$15+Q67*'08_Premissas_Custos'!$C$16+R67*'08_Premissas_Custos'!$C$17+S67*'08_Premissas_Custos'!$C$18+T67*'08_Premissas_Custos'!$C$19+U67*'08_Premissas_Custos'!$C$20)*(1-H67)*IF(E67="Fase 2",'08_Premissas_Custos'!$F$10,1) | Y67: =X67*'08_Premissas_Custos'!$F$7 | Z67: =(X67+Y67)*'08_Premissas_Custos'!$F$6 | AA67: =SUM(X67:Z67) | AB67: Institucional
A68: 63 | B68: ACA | C68: Acadêmico / Universidades | D68: Perfil acadêmico do aluno | E68: Fase 2 | F68: Média | G68: Perfil acadêmico do aluno | H68: 0.45 | I68: Não | J68: Não | K68: Não | L68: Sim | M68: =IF(F68="Baixa",'08_Premissas_Custos'!$B$6,IF(F68="Média",'08_Premissas_Custos'!$B$7,IF(F68="Alta",'08_Premissas_Custos'!$B$8,'08_Premissas_Custos'!$B$9))) | N68: ='08_Premissas_Custos'!$B$13*M68 | O68: ='08_Premissas_Custos'!$B$14*M68*(1+IF(L68="Sim",0.25,0)) | P68: ='08_Premissas_Custos'!$B$15*M68*(1+IF(I68="Sim",0.20,0)+IF(K68="Sim",0.15,0)) | Q68: ='08_Premissas_Custos'!$B$16*M68*IF(J68="Sim",1.6,0.55) | R68: ='08_Premissas_Custos'!$B$17*M68*IF(I68="Sim",1.8,0.15) | S68: ='08_Premissas_Custos'!$B$18*M68*(1+IF(I68="Sim",0.15)+IF(L68="Sim",0.10)) | T68: ='08_Premissas_Custos'!$B$19*M68*(1+IF(J68="Sim",0.15)) | U68: ='08_Premissas_Custos'!$B$20*M68*IF(K68="Sim",1.8,0.7) | V68: =SUM(N68:U68) | W68: =V68*(1-H68)*IF(E68="Fase 2",'08_Premissas_Custos'!$F$10,1) | X68: =(N68*'08_Premissas_Custos'!$C$13+O68*'08_Premissas_Custos'!$C$14+P68*'08_Premissas_Custos'!$C$15+Q68*'08_Premissas_Custos'!$C$16+R68*'08_Premissas_Custos'!$C$17+S68*'08_Premissas_Custos'!$C$18+T68*'08_Premissas_Custos'!$C$19+U68*'08_Premissas_Custos'!$C$20)*(1-H68)*IF(E68="Fase 2",'08_Premissas_Custos'!$F$10,1) | Y68: =X68*'08_Premissas_Custos'!$F$7 | Z68: =(X68+Y68)*'08_Premissas_Custos'!$F$6 | AA68: =SUM(X68:Z68) | AB68: Formação
A69: 64 | B69: ACA | C69: Acadêmico / Universidades | D69: Perfil pesquisador/docente | E69: Fase 2 | F69: Média | G69: Perfil pesquisador/docente | H69: 0.45 | I69: Não | J69: Sim | K69: Não | L69: Não | M69: =IF(F69="Baixa",'08_Premissas_Custos'!$B$6,IF(F69="Média",'08_Premissas_Custos'!$B$7,IF(F69="Alta",'08_Premissas_Custos'!$B$8,'08_Premissas_Custos'!$B$9))) | N69: ='08_Premissas_Custos'!$B$13*M69 | O69: ='08_Premissas_Custos'!$B$14*M69*(1+IF(L69="Sim",0.25,0)) | P69: ='08_Premissas_Custos'!$B$15*M69*(1+IF(I69="Sim",0.20,0)+IF(K69="Sim",0.15,0)) | Q69: ='08_Premissas_Custos'!$B$16*M69*IF(J69="Sim",1.6,0.55) | R69: ='08_Premissas_Custos'!$B$17*M69*IF(I69="Sim",1.8,0.15) | S69: ='08_Premissas_Custos'!$B$18*M69*(1+IF(I69="Sim",0.15)+IF(L69="Sim",0.10)) | T69: ='08_Premissas_Custos'!$B$19*M69*(1+IF(J69="Sim",0.15)) | U69: ='08_Premissas_Custos'!$B$20*M69*IF(K69="Sim",1.8,0.7) | V69: =SUM(N69:U69) | W69: =V69*(1-H69)*IF(E69="Fase 2",'08_Premissas_Custos'!$F$10,1) | X69: =(N69*'08_Premissas_Custos'!$C$13+O69*'08_Premissas_Custos'!$C$14+P69*'08_Premissas_Custos'!$C$15+Q69*'08_Premissas_Custos'!$C$16+R69*'08_Premissas_Custos'!$C$17+S69*'08_Premissas_Custos'!$C$18+T69*'08_Premissas_Custos'!$C$19+U69*'08_Premissas_Custos'!$C$20)*(1-H69)*IF(E69="Fase 2",'08_Premissas_Custos'!$F$10,1) | Y69: =X69*'08_Premissas_Custos'!$F$7 | Z69: =(X69+Y69)*'08_Premissas_Custos'!$F$6 | AA69: =SUM(X69:Z69) | AB69: Linhas
A70: 65 | B70: ACA | C70: Acadêmico / Universidades | D70: Oportunidades acadêmicas | E70: Fase 2 | F70: Média | H70: 0 | I70: Não | J70: Não | K70: Não | L70: Sim | M70: =IF(F70="Baixa",'08_Premissas_Custos'!$B$6,IF(F70="Média",'08_Premissas_Custos'!$B$7,IF(F70="Alta",'08_Premissas_Custos'!$B$8,'08_Premissas_Custos'!$B$9))) | N70: ='08_Premissas_Custos'!$B$13*M70 | O70: ='08_Premissas_Custos'!$B$14*M70*(1+IF(L70="Sim",0.25,0)) | P70: ='08_Premissas_Custos'!$B$15*M70*(1+IF(I70="Sim",0.20,0)+IF(K70="Sim",0.15,0)) | Q70: ='08_Premissas_Custos'!$B$16*M70*IF(J70="Sim",1.6,0.55) | R70: ='08_Premissas_Custos'!$B$17*M70*IF(I70="Sim",1.8,0.15) | S70: ='08_Premissas_Custos'!$B$18*M70*(1+IF(I70="Sim",0.15)+IF(L70="Sim",0.10)) | T70: ='08_Premissas_Custos'!$B$19*M70*(1+IF(J70="Sim",0.15)) | U70: ='08_Premissas_Custos'!$B$20*M70*IF(K70="Sim",1.8,0.7) | V70: =SUM(N70:U70) | W70: =V70*(1-H70)*IF(E70="Fase 2",'08_Premissas_Custos'!$F$10,1) | X70: =(N70*'08_Premissas_Custos'!$C$13+O70*'08_Premissas_Custos'!$C$14+P70*'08_Premissas_Custos'!$C$15+Q70*'08_Premissas_Custos'!$C$16+R70*'08_Premissas_Custos'!$C$17+S70*'08_Premissas_Custos'!$C$18+T70*'08_Premissas_Custos'!$C$19+U70*'08_Premissas_Custos'!$C$20)*(1-H70)*IF(E70="Fase 2",'08_Premissas_Custos'!$F$10,1) | Y70: =X70*'08_Premissas_Custos'!$F$7 | Z70: =(X70+Y70)*'08_Premissas_Custos'!$F$6 | AA70: =SUM(X70:Z70) | AB70: Bolsas/projetos
A71: 66 | B71: ACA | C71: Acadêmico / Universidades | D71: Projetos empresa-universidade | E71: Fase 2 | F71: Alta | H71: 0 | I71: Não | J71: Não | K71: Não | L71: Não | M71: =IF(F71="Baixa",'08_Premissas_Custos'!$B$6,IF(F71="Média",'08_Premissas_Custos'!$B$7,IF(F71="Alta",'08_Premissas_Custos'!$B$8,'08_Premissas_Custos'!$B$9))) | N71: ='08_Premissas_Custos'!$B$13*M71 | O71: ='08_Premissas_Custos'!$B$14*M71*(1+IF(L71="Sim",0.25,0)) | P71: ='08_Premissas_Custos'!$B$15*M71*(1+IF(I71="Sim",0.20,0)+IF(K71="Sim",0.15,0)) | Q71: ='08_Premissas_Custos'!$B$16*M71*IF(J71="Sim",1.6,0.55) | R71: ='08_Premissas_Custos'!$B$17*M71*IF(I71="Sim",1.8,0.15) | S71: ='08_Premissas_Custos'!$B$18*M71*(1+IF(I71="Sim",0.15)+IF(L71="Sim",0.10)) | T71: ='08_Premissas_Custos'!$B$19*M71*(1+IF(J71="Sim",0.15)) | U71: ='08_Premissas_Custos'!$B$20*M71*IF(K71="Sim",1.8,0.7) | V71: =SUM(N71:U71) | W71: =V71*(1-H71)*IF(E71="Fase 2",'08_Premissas_Custos'!$F$10,1) | X71: =(N71*'08_Premissas_Custos'!$C$13+O71*'08_Premissas_Custos'!$C$14+P71*'08_Premissas_Custos'!$C$15+Q71*'08_Premissas_Custos'!$C$16+R71*'08_Premissas_Custos'!$C$17+S71*'08_Premissas_Custos'!$C$18+T71*'08_Premissas_Custos'!$C$19+U71*'08_Premissas_Custos'!$C$20)*(1-H71)*IF(E71="Fase 2",'08_Premissas_Custos'!$F$10,1) | Y71: =X71*'08_Premissas_Custos'!$F$7 | Z71: =(X71+Y71)*'08_Premissas_Custos'!$F$6 | AA71: =SUM(X71:Z71) | AB71: Desafios
A72: 67 | B72: ACA | C72: Acadêmico / Universidades | D72: Match aluno-projeto | E72: Fase 2 | F72: Alta | H72: 0 | I72: Sim | J72: Não | K72: Não | L72: Não | M72: =IF(F72="Baixa",'08_Premissas_Custos'!$B$6,IF(F72="Média",'08_Premissas_Custos'!$B$7,IF(F72="Alta",'08_Premissas_Custos'!$B$8,'08_Premissas_Custos'!$B$9))) | N72: ='08_Premissas_Custos'!$B$13*M72 | O72: ='08_Premissas_Custos'!$B$14*M72*(1+IF(L72="Sim",0.25,0)) | P72: ='08_Premissas_Custos'!$B$15*M72*(1+IF(I72="Sim",0.20,0)+IF(K72="Sim",0.15,0)) | Q72: ='08_Premissas_Custos'!$B$16*M72*IF(J72="Sim",1.6,0.55) | R72: ='08_Premissas_Custos'!$B$17*M72*IF(I72="Sim",1.8,0.15) | S72: ='08_Premissas_Custos'!$B$18*M72*(1+IF(I72="Sim",0.15)+IF(L72="Sim",0.10)) | T72: ='08_Premissas_Custos'!$B$19*M72*(1+IF(J72="Sim",0.15)) | U72: ='08_Premissas_Custos'!$B$20*M72*IF(K72="Sim",1.8,0.7) | V72: =SUM(N72:U72) | W72: =V72*(1-H72)*IF(E72="Fase 2",'08_Premissas_Custos'!$F$10,1) | X72: =(N72*'08_Premissas_Custos'!$C$13+O72*'08_Premissas_Custos'!$C$14+P72*'08_Premissas_Custos'!$C$15+Q72*'08_Premissas_Custos'!$C$16+R72*'08_Premissas_Custos'!$C$17+S72*'08_Premissas_Custos'!$C$18+T72*'08_Premissas_Custos'!$C$19+U72*'08_Premissas_Custos'!$C$20)*(1-H72)*IF(E72="Fase 2",'08_Premissas_Custos'!$F$10,1) | Y72: =X72*'08_Premissas_Custos'!$F$7 | Z72: =(X72+Y72)*'08_Premissas_Custos'!$F$6 | AA72: =SUM(X72:Z72) | AB72: Aderência
A73: 68 | B73: ACA | C73: Acadêmico / Universidades | D73: Match pesquisador-empresa | E73: Fase 2 | F73: Muito alta | H73: 0 | I73: Sim | J73: Sim | K73: Não | L73: Não | M73: =IF(F73="Baixa",'08_Premissas_Custos'!$B$6,IF(F73="Média",'08_Premissas_Custos'!$B$7,IF(F73="Alta",'08_Premissas_Custos'!$B$8,'08_Premissas_Custos'!$B$9))) | N73: ='08_Premissas_Custos'!$B$13*M73 | O73: ='08_Premissas_Custos'!$B$14*M73*(1+IF(L73="Sim",0.25,0)) | P73: ='08_Premissas_Custos'!$B$15*M73*(1+IF(I73="Sim",0.20,0)+IF(K73="Sim",0.15,0)) | Q73: ='08_Premissas_Custos'!$B$16*M73*IF(J73="Sim",1.6,0.55) | R73: ='08_Premissas_Custos'!$B$17*M73*IF(I73="Sim",1.8,0.15) | S73: ='08_Premissas_Custos'!$B$18*M73*(1+IF(I73="Sim",0.15)+IF(L73="Sim",0.10)) | T73: ='08_Premissas_Custos'!$B$19*M73*(1+IF(J73="Sim",0.15)) | U73: ='08_Premissas_Custos'!$B$20*M73*IF(K73="Sim",1.8,0.7) | V73: =SUM(N73:U73) | W73: =V73*(1-H73)*IF(E73="Fase 2",'08_Premissas_Custos'!$F$10,1) | X73: =(N73*'08_Premissas_Custos'!$C$13+O73*'08_Premissas_Custos'!$C$14+P73*'08_Premissas_Custos'!$C$15+Q73*'08_Premissas_Custos'!$C$16+R73*'08_Premissas_Custos'!$C$17+S73*'08_Premissas_Custos'!$C$18+T73*'08_Premissas_Custos'!$C$19+U73*'08_Premissas_Custos'!$C$20)*(1-H73)*IF(E73="Fase 2",'08_Premissas_Custos'!$F$10,1) | Y73: =X73*'08_Premissas_Custos'!$F$7 | Z73: =(X73+Y73)*'08_Premissas_Custos'!$F$6 | AA73: =SUM(X73:Z73) | AB73: Pesquisa aplicada
A74: 69 | B74: ACA | C74: Acadêmico / Universidades | D74: Estágios e carreira | E74: Fase 2 | F74: Alta | H74: 0 | I74: Não | J74: Não | K74: Não | L74: Sim | M74: =IF(F74="Baixa",'08_Premissas_Custos'!$B$6,IF(F74="Média",'08_Premissas_Custos'!$B$7,IF(F74="Alta",'08_Premissas_Custos'!$B$8,'08_Premissas_Custos'!$B$9))) | N74: ='08_Premissas_Custos'!$B$13*M74 | O74: ='08_Premissas_Custos'!$B$14*M74*(1+IF(L74="Sim",0.25,0)) | P74: ='08_Premissas_Custos'!$B$15*M74*(1+IF(I74="Sim",0.20,0)+IF(K74="Sim",0.15,0)) | Q74: ='08_Premissas_Custos'!$B$16*M74*IF(J74="Sim",1.6,0.55) | R74: ='08_Premissas_Custos'!$B$17*M74*IF(I74="Sim",1.8,0.15) | S74: ='08_Premissas_Custos'!$B$18*M74*(1+IF(I74="Sim",0.15)+IF(L74="Sim",0.10)) | T74: ='08_Premissas_Custos'!$B$19*M74*(1+IF(J74="Sim",0.15)) | U74: ='08_Premissas_Custos'!$B$20*M74*IF(K74="Sim",1.8,0.7) | V74: =SUM(N74:U74) | W74: =V74*(1-H74)*IF(E74="Fase 2",'08_Premissas_Custos'!$F$10,1) | X74: =(N74*'08_Premissas_Custos'!$C$13+O74*'08_Premissas_Custos'!$C$14+P74*'08_Premissas_Custos'!$C$15+Q74*'08_Premissas_Custos'!$C$16+R74*'08_Premissas_Custos'!$C$17+S74*'08_Premissas_Custos'!$C$18+T74*'08_Premissas_Custos'!$C$19+U74*'08_Premissas_Custos'!$C$20)*(1-H74)*IF(E74="Fase 2",'08_Premissas_Custos'!$F$10,1) | Y74: =X74*'08_Premissas_Custos'!$F$7 | Z74: =(X74+Y74)*'08_Premissas_Custos'!$F$6 | AA74: =SUM(X74:Z74) | AB74: Integra CAN
A75: 70 | B75: ACA | C75: Acadêmico / Universidades | D75: Bolsas corporativas | E75: Fase 2 | F75: Média | H75: 0 | I75: Não | J75: Não | K75: Não | L75: Não | M75: =IF(F75="Baixa",'08_Premissas_Custos'!$B$6,IF(F75="Média",'08_Premissas_Custos'!$B$7,IF(F75="Alta",'08_Premissas_Custos'!$B$8,'08_Premissas_Custos'!$B$9))) | N75: ='08_Premissas_Custos'!$B$13*M75 | O75: ='08_Premissas_Custos'!$B$14*M75*(1+IF(L75="Sim",0.25,0)) | P75: ='08_Premissas_Custos'!$B$15*M75*(1+IF(I75="Sim",0.20,0)+IF(K75="Sim",0.15,0)) | Q75: ='08_Premissas_Custos'!$B$16*M75*IF(J75="Sim",1.6,0.55) | R75: ='08_Premissas_Custos'!$B$17*M75*IF(I75="Sim",1.8,0.15) | S75: ='08_Premissas_Custos'!$B$18*M75*(1+IF(I75="Sim",0.15)+IF(L75="Sim",0.10)) | T75: ='08_Premissas_Custos'!$B$19*M75*(1+IF(J75="Sim",0.15)) | U75: ='08_Premissas_Custos'!$B$20*M75*IF(K75="Sim",1.8,0.7) | V75: =SUM(N75:U75) | W75: =V75*(1-H75)*IF(E75="Fase 2",'08_Premissas_Custos'!$F$10,1) | X75: =(N75*'08_Premissas_Custos'!$C$13+O75*'08_Premissas_Custos'!$C$14+P75*'08_Premissas_Custos'!$C$15+Q75*'08_Premissas_Custos'!$C$16+R75*'08_Premissas_Custos'!$C$17+S75*'08_Premissas_Custos'!$C$18+T75*'08_Premissas_Custos'!$C$19+U75*'08_Premissas_Custos'!$C$20)*(1-H75)*IF(E75="Fase 2",'08_Premissas_Custos'!$F$10,1) | Y75: =X75*'08_Premissas_Custos'!$F$7 | Z75: =(X75+Y75)*'08_Premissas_Custos'!$F$6 | AA75: =SUM(X75:Z75) | AB75: Empresa->aluno
A76: 71 | B76: ACA | C76: Acadêmico / Universidades | D76: Formação / trilhas | E76: Fase 2 | F76: Média | H76: 0 | I76: Não | J76: Não | K76: Não | L76: Sim | M76: =IF(F76="Baixa",'08_Premissas_Custos'!$B$6,IF(F76="Média",'08_Premissas_Custos'!$B$7,IF(F76="Alta",'08_Premissas_Custos'!$B$8,'08_Premissas_Custos'!$B$9))) | N76: ='08_Premissas_Custos'!$B$13*M76 | O76: ='08_Premissas_Custos'!$B$14*M76*(1+IF(L76="Sim",0.25,0)) | P76: ='08_Premissas_Custos'!$B$15*M76*(1+IF(I76="Sim",0.20,0)+IF(K76="Sim",0.15,0)) | Q76: ='08_Premissas_Custos'!$B$16*M76*IF(J76="Sim",1.6,0.55) | R76: ='08_Premissas_Custos'!$B$17*M76*IF(I76="Sim",1.8,0.15) | S76: ='08_Premissas_Custos'!$B$18*M76*(1+IF(I76="Sim",0.15)+IF(L76="Sim",0.10)) | T76: ='08_Premissas_Custos'!$B$19*M76*(1+IF(J76="Sim",0.15)) | U76: ='08_Premissas_Custos'!$B$20*M76*IF(K76="Sim",1.8,0.7) | V76: =SUM(N76:U76) | W76: =V76*(1-H76)*IF(E76="Fase 2",'08_Premissas_Custos'!$F$10,1) | X76: =(N76*'08_Premissas_Custos'!$C$13+O76*'08_Premissas_Custos'!$C$14+P76*'08_Premissas_Custos'!$C$15+Q76*'08_Premissas_Custos'!$C$16+R76*'08_Premissas_Custos'!$C$17+S76*'08_Premissas_Custos'!$C$18+T76*'08_Premissas_Custos'!$C$19+U76*'08_Premissas_Custos'!$C$20)*(1-H76)*IF(E76="Fase 2",'08_Premissas_Custos'!$F$10,1) | Y76: =X76*'08_Premissas_Custos'!$F$7 | Z76: =(X76+Y76)*'08_Premissas_Custos'!$F$6 | AA76: =SUM(X76:Z76) | AB76: Desenvolvimento
A77: 72 | B77: ACA | C77: Acadêmico / Universidades | D77: Acompanhamento de projeto | E77: Fase 2 | F77: Alta | H77: 0 | I77: Não | J77: Não | K77: Não | L77: Não | M77: =IF(F77="Baixa",'08_Premissas_Custos'!$B$6,IF(F77="Média",'08_Premissas_Custos'!$B$7,IF(F77="Alta",'08_Premissas_Custos'!$B$8,'08_Premissas_Custos'!$B$9))) | N77: ='08_Premissas_Custos'!$B$13*M77 | O77: ='08_Premissas_Custos'!$B$14*M77*(1+IF(L77="Sim",0.25,0)) | P77: ='08_Premissas_Custos'!$B$15*M77*(1+IF(I77="Sim",0.20,0)+IF(K77="Sim",0.15,0)) | Q77: ='08_Premissas_Custos'!$B$16*M77*IF(J77="Sim",1.6,0.55) | R77: ='08_Premissas_Custos'!$B$17*M77*IF(I77="Sim",1.8,0.15) | S77: ='08_Premissas_Custos'!$B$18*M77*(1+IF(I77="Sim",0.15)+IF(L77="Sim",0.10)) | T77: ='08_Premissas_Custos'!$B$19*M77*(1+IF(J77="Sim",0.15)) | U77: ='08_Premissas_Custos'!$B$20*M77*IF(K77="Sim",1.8,0.7) | V77: =SUM(N77:U77) | W77: =V77*(1-H77)*IF(E77="Fase 2",'08_Premissas_Custos'!$F$10,1) | X77: =(N77*'08_Premissas_Custos'!$C$13+O77*'08_Premissas_Custos'!$C$14+P77*'08_Premissas_Custos'!$C$15+Q77*'08_Premissas_Custos'!$C$16+R77*'08_Premissas_Custos'!$C$17+S77*'08_Premissas_Custos'!$C$18+T77*'08_Premissas_Custos'!$C$19+U77*'08_Premissas_Custos'!$C$20)*(1-H77)*IF(E77="Fase 2",'08_Premissas_Custos'!$F$10,1) | Y77: =X77*'08_Premissas_Custos'!$F$7 | Z77: =(X77+Y77)*'08_Premissas_Custos'!$F$6 | AA77: =SUM(X77:Z77) | AB77: Entregas
A78: 73 | B78: ACA | C78: Acadêmico / Universidades | D78: Indicadores universidade-mercado | E78: Fase 2 | F78: Alta | G78: Indicadores universidade-mercado | H78: 0.45 | I78: Não | J78: Sim | K78: Não | L78: Não | M78: =IF(F78="Baixa",'08_Premissas_Custos'!$B$6,IF(F78="Média",'08_Premissas_Custos'!$B$7,IF(F78="Alta",'08_Premissas_Custos'!$B$8,'08_Premissas_Custos'!$B$9))) | N78: ='08_Premissas_Custos'!$B$13*M78 | O78: ='08_Premissas_Custos'!$B$14*M78*(1+IF(L78="Sim",0.25,0)) | P78: ='08_Premissas_Custos'!$B$15*M78*(1+IF(I78="Sim",0.20,0)+IF(K78="Sim",0.15,0)) | Q78: ='08_Premissas_Custos'!$B$16*M78*IF(J78="Sim",1.6,0.55) | R78: ='08_Premissas_Custos'!$B$17*M78*IF(I78="Sim",1.8,0.15) | S78: ='08_Premissas_Custos'!$B$18*M78*(1+IF(I78="Sim",0.15)+IF(L78="Sim",0.10)) | T78: ='08_Premissas_Custos'!$B$19*M78*(1+IF(J78="Sim",0.15)) | U78: ='08_Premissas_Custos'!$B$20*M78*IF(K78="Sim",1.8,0.7) | V78: =SUM(N78:U78) | W78: =V78*(1-H78)*IF(E78="Fase 2",'08_Premissas_Custos'!$F$10,1) | X78: =(N78*'08_Premissas_Custos'!$C$13+O78*'08_Premissas_Custos'!$C$14+P78*'08_Premissas_Custos'!$C$15+Q78*'08_Premissas_Custos'!$C$16+R78*'08_Premissas_Custos'!$C$17+S78*'08_Premissas_Custos'!$C$18+T78*'08_Premissas_Custos'!$C$19+U78*'08_Premissas_Custos'!$C$20)*(1-H78)*IF(E78="Fase 2",'08_Premissas_Custos'!$F$10,1) | Y78: =X78*'08_Premissas_Custos'!$F$7 | Z78: =(X78+Y78)*'08_Premissas_Custos'!$F$6 | AA78: =SUM(X78:Z78) | AB78: Impacto
A79: 74 | B79: EVT | C79: Eventos | D79: Visão geral do evento | E79: Fase 2 | F79: Alta | H79: 0 | I79: Não | J79: Não | K79: Não | L79: Não | M79: =IF(F79="Baixa",'08_Premissas_Custos'!$B$6,IF(F79="Média",'08_Premissas_Custos'!$B$7,IF(F79="Alta",'08_Premissas_Custos'!$B$8,'08_Premissas_Custos'!$B$9))) | N79: ='08_Premissas_Custos'!$B$13*M79 | O79: ='08_Premissas_Custos'!$B$14*M79*(1+IF(L79="Sim",0.25,0)) | P79: ='08_Premissas_Custos'!$B$15*M79*(1+IF(I79="Sim",0.20,0)+IF(K79="Sim",0.15,0)) | Q79: ='08_Premissas_Custos'!$B$16*M79*IF(J79="Sim",1.6,0.55) | R79: ='08_Premissas_Custos'!$B$17*M79*IF(I79="Sim",1.8,0.15) | S79: ='08_Premissas_Custos'!$B$18*M79*(1+IF(I79="Sim",0.15)+IF(L79="Sim",0.10)) | T79: ='08_Premissas_Custos'!$B$19*M79*(1+IF(J79="Sim",0.15)) | U79: ='08_Premissas_Custos'!$B$20*M79*IF(K79="Sim",1.8,0.7) | V79: =SUM(N79:U79) | W79: =V79*(1-H79)*IF(E79="Fase 2",'08_Premissas_Custos'!$F$10,1) | X79: =(N79*'08_Premissas_Custos'!$C$13+O79*'08_Premissas_Custos'!$C$14+P79*'08_Premissas_Custos'!$C$15+Q79*'08_Premissas_Custos'!$C$16+R79*'08_Premissas_Custos'!$C$17+S79*'08_Premissas_Custos'!$C$18+T79*'08_Premissas_Custos'!$C$19+U79*'08_Premissas_Custos'!$C$20)*(1-H79)*IF(E79="Fase 2",'08_Premissas_Custos'!$F$10,1) | Y79: =X79*'08_Premissas_Custos'!$F$7 | Z79: =(X79+Y79)*'08_Premissas_Custos'!$F$6 | AA79: =SUM(X79:Z79) | AB79: Dashboard
A80: 75 | B80: EVT | C80: Eventos | D80: Planejamento / metas | E80: Fase 2 | F80: Média | H80: 0 | I80: Não | J80: Não | K80: Não | L80: Não | M80: =IF(F80="Baixa",'08_Premissas_Custos'!$B$6,IF(F80="Média",'08_Premissas_Custos'!$B$7,IF(F80="Alta",'08_Premissas_Custos'!$B$8,'08_Premissas_Custos'!$B$9))) | N80: ='08_Premissas_Custos'!$B$13*M80 | O80: ='08_Premissas_Custos'!$B$14*M80*(1+IF(L80="Sim",0.25,0)) | P80: ='08_Premissas_Custos'!$B$15*M80*(1+IF(I80="Sim",0.20,0)+IF(K80="Sim",0.15,0)) | Q80: ='08_Premissas_Custos'!$B$16*M80*IF(J80="Sim",1.6,0.55) | R80: ='08_Premissas_Custos'!$B$17*M80*IF(I80="Sim",1.8,0.15) | S80: ='08_Premissas_Custos'!$B$18*M80*(1+IF(I80="Sim",0.15)+IF(L80="Sim",0.10)) | T80: ='08_Premissas_Custos'!$B$19*M80*(1+IF(J80="Sim",0.15)) | U80: ='08_Premissas_Custos'!$B$20*M80*IF(K80="Sim",1.8,0.7) | V80: =SUM(N80:U80) | W80: =V80*(1-H80)*IF(E80="Fase 2",'08_Premissas_Custos'!$F$10,1) | X80: =(N80*'08_Premissas_Custos'!$C$13+O80*'08_Premissas_Custos'!$C$14+P80*'08_Premissas_Custos'!$C$15+Q80*'08_Premissas_Custos'!$C$16+R80*'08_Premissas_Custos'!$C$17+S80*'08_Premissas_Custos'!$C$18+T80*'08_Premissas_Custos'!$C$19+U80*'08_Premissas_Custos'!$C$20)*(1-H80)*IF(E80="Fase 2",'08_Premissas_Custos'!$F$10,1) | Y80: =X80*'08_Premissas_Custos'!$F$7 | Z80: =(X80+Y80)*'08_Premissas_Custos'!$F$6 | AA80: =SUM(X80:Z80) | AB80: KPIs
A81: 76 | B81: EVT | C81: Eventos | D81: Talentos / equipes | E81: Fase 2 | F81: Alta | H81: 0 | I81: Não | J81: Não | K81: Não | L81: Não | M81: =IF(F81="Baixa",'08_Premissas_Custos'!$B$6,IF(F81="Média",'08_Premissas_Custos'!$B$7,IF(F81="Alta",'08_Premissas_Custos'!$B$8,'08_Premissas_Custos'!$B$9))) | N81: ='08_Premissas_Custos'!$B$13*M81 | O81: ='08_Premissas_Custos'!$B$14*M81*(1+IF(L81="Sim",0.25,0)) | P81: ='08_Premissas_Custos'!$B$15*M81*(1+IF(I81="Sim",0.20,0)+IF(K81="Sim",0.15,0)) | Q81: ='08_Premissas_Custos'!$B$16*M81*IF(J81="Sim",1.6,0.55) | R81: ='08_Premissas_Custos'!$B$17*M81*IF(I81="Sim",1.8,0.15) | S81: ='08_Premissas_Custos'!$B$18*M81*(1+IF(I81="Sim",0.15)+IF(L81="Sim",0.10)) | T81: ='08_Premissas_Custos'!$B$19*M81*(1+IF(J81="Sim",0.15)) | U81: ='08_Premissas_Custos'!$B$20*M81*IF(K81="Sim",1.8,0.7) | V81: =SUM(N81:U81) | W81: =V81*(1-H81)*IF(E81="Fase 2",'08_Premissas_Custos'!$F$10,1) | X81: =(N81*'08_Premissas_Custos'!$C$13+O81*'08_Premissas_Custos'!$C$14+P81*'08_Premissas_Custos'!$C$15+Q81*'08_Premissas_Custos'!$C$16+R81*'08_Premissas_Custos'!$C$17+S81*'08_Premissas_Custos'!$C$18+T81*'08_Premissas_Custos'!$C$19+U81*'08_Premissas_Custos'!$C$20)*(1-H81)*IF(E81="Fase 2",'08_Premissas_Custos'!$F$10,1) | Y81: =X81*'08_Premissas_Custos'!$F$7 | Z81: =(X81+Y81)*'08_Premissas_Custos'!$F$6 | AA81: =SUM(X81:Z81) | AB81: CAN
A82: 77 | B82: EVT | C82: Eventos | D82: Fornecedores do evento | E82: Fase 2 | F82: Alta | H82: 0 | I82: Não | J82: Não | K82: Não | L82: Não | M82: =IF(F82="Baixa",'08_Premissas_Custos'!$B$6,IF(F82="Média",'08_Premissas_Custos'!$B$7,IF(F82="Alta",'08_Premissas_Custos'!$B$8,'08_Premissas_Custos'!$B$9))) | N82: ='08_Premissas_Custos'!$B$13*M82 | O82: ='08_Premissas_Custos'!$B$14*M82*(1+IF(L82="Sim",0.25,0)) | P82: ='08_Premissas_Custos'!$B$15*M82*(1+IF(I82="Sim",0.20,0)+IF(K82="Sim",0.15,0)) | Q82: ='08_Premissas_Custos'!$B$16*M82*IF(J82="Sim",1.6,0.55) | R82: ='08_Premissas_Custos'!$B$17*M82*IF(I82="Sim",1.8,0.15) | S82: ='08_Premissas_Custos'!$B$18*M82*(1+IF(I82="Sim",0.15)+IF(L82="Sim",0.10)) | T82: ='08_Premissas_Custos'!$B$19*M82*(1+IF(J82="Sim",0.15)) | U82: ='08_Premissas_Custos'!$B$20*M82*IF(K82="Sim",1.8,0.7) | V82: =SUM(N82:U82) | W82: =V82*(1-H82)*IF(E82="Fase 2",'08_Premissas_Custos'!$F$10,1) | X82: =(N82*'08_Premissas_Custos'!$C$13+O82*'08_Premissas_Custos'!$C$14+P82*'08_Premissas_Custos'!$C$15+Q82*'08_Premissas_Custos'!$C$16+R82*'08_Premissas_Custos'!$C$17+S82*'08_Premissas_Custos'!$C$18+T82*'08_Premissas_Custos'!$C$19+U82*'08_Premissas_Custos'!$C$20)*(1-H82)*IF(E82="Fase 2",'08_Premissas_Custos'!$F$10,1) | Y82: =X82*'08_Premissas_Custos'!$F$7 | Z82: =(X82+Y82)*'08_Premissas_Custos'!$F$6 | AA82: =SUM(X82:Z82) | AB82: FOR
A83: 78 | B83: EVT | C83: Eventos | D83: Demandas e contratações | E83: Fase 2 | F83: Alta | H83: 0 | I83: Não | J83: Não | K83: Não | L83: Não | M83: =IF(F83="Baixa",'08_Premissas_Custos'!$B$6,IF(F83="Média",'08_Premissas_Custos'!$B$7,IF(F83="Alta",'08_Premissas_Custos'!$B$8,'08_Premissas_Custos'!$B$9))) | N83: ='08_Premissas_Custos'!$B$13*M83 | O83: ='08_Premissas_Custos'!$B$14*M83*(1+IF(L83="Sim",0.25,0)) | P83: ='08_Premissas_Custos'!$B$15*M83*(1+IF(I83="Sim",0.20,0)+IF(K83="Sim",0.15,0)) | Q83: ='08_Premissas_Custos'!$B$16*M83*IF(J83="Sim",1.6,0.55) | R83: ='08_Premissas_Custos'!$B$17*M83*IF(I83="Sim",1.8,0.15) | S83: ='08_Premissas_Custos'!$B$18*M83*(1+IF(I83="Sim",0.15)+IF(L83="Sim",0.10)) | T83: ='08_Premissas_Custos'!$B$19*M83*(1+IF(J83="Sim",0.15)) | U83: ='08_Premissas_Custos'!$B$20*M83*IF(K83="Sim",1.8,0.7) | V83: =SUM(N83:U83) | W83: =V83*(1-H83)*IF(E83="Fase 2",'08_Premissas_Custos'!$F$10,1) | X83: =(N83*'08_Premissas_Custos'!$C$13+O83*'08_Premissas_Custos'!$C$14+P83*'08_Premissas_Custos'!$C$15+Q83*'08_Premissas_Custos'!$C$16+R83*'08_Premissas_Custos'!$C$17+S83*'08_Premissas_Custos'!$C$18+T83*'08_Premissas_Custos'!$C$19+U83*'08_Premissas_Custos'!$C$20)*(1-H83)*IF(E83="Fase 2",'08_Premissas_Custos'!$F$10,1) | Y83: =X83*'08_Premissas_Custos'!$F$7 | Z83: =(X83+Y83)*'08_Premissas_Custos'!$F$6 | AA83: =SUM(X83:Z83) | AB83: Compras
A84: 79 | B84: EVT | C84: Eventos | D84: Patrocínios / marcas | E84: Fase 2 | F84: Alta | H84: 0 | I84: Não | J84: Não | K84: Não | L84: Não | M84: =IF(F84="Baixa",'08_Premissas_Custos'!$B$6,IF(F84="Média",'08_Premissas_Custos'!$B$7,IF(F84="Alta",'08_Premissas_Custos'!$B$8,'08_Premissas_Custos'!$B$9))) | N84: ='08_Premissas_Custos'!$B$13*M84 | O84: ='08_Premissas_Custos'!$B$14*M84*(1+IF(L84="Sim",0.25,0)) | P84: ='08_Premissas_Custos'!$B$15*M84*(1+IF(I84="Sim",0.20,0)+IF(K84="Sim",0.15,0)) | Q84: ='08_Premissas_Custos'!$B$16*M84*IF(J84="Sim",1.6,0.55) | R84: ='08_Premissas_Custos'!$B$17*M84*IF(I84="Sim",1.8,0.15) | S84: ='08_Premissas_Custos'!$B$18*M84*(1+IF(I84="Sim",0.15)+IF(L84="Sim",0.10)) | T84: ='08_Premissas_Custos'!$B$19*M84*(1+IF(J84="Sim",0.15)) | U84: ='08_Premissas_Custos'!$B$20*M84*IF(K84="Sim",1.8,0.7) | V84: =SUM(N84:U84) | W84: =V84*(1-H84)*IF(E84="Fase 2",'08_Premissas_Custos'!$F$10,1) | X84: =(N84*'08_Premissas_Custos'!$C$13+O84*'08_Premissas_Custos'!$C$14+P84*'08_Premissas_Custos'!$C$15+Q84*'08_Premissas_Custos'!$C$16+R84*'08_Premissas_Custos'!$C$17+S84*'08_Premissas_Custos'!$C$18+T84*'08_Premissas_Custos'!$C$19+U84*'08_Premissas_Custos'!$C$20)*(1-H84)*IF(E84="Fase 2",'08_Premissas_Custos'!$F$10,1) | Y84: =X84*'08_Premissas_Custos'!$F$7 | Z84: =(X84+Y84)*'08_Premissas_Custos'!$F$6 | AA84: =SUM(X84:Z84) | AB84: Retorno
A85: 80 | B85: EVT | C85: Eventos | D85: Artistas / criadores | E85: Fase 2 | F85: Média | H85: 0 | I85: Não | J85: Não | K85: Não | L85: Não | M85: =IF(F85="Baixa",'08_Premissas_Custos'!$B$6,IF(F85="Média",'08_Premissas_Custos'!$B$7,IF(F85="Alta",'08_Premissas_Custos'!$B$8,'08_Premissas_Custos'!$B$9))) | N85: ='08_Premissas_Custos'!$B$13*M85 | O85: ='08_Premissas_Custos'!$B$14*M85*(1+IF(L85="Sim",0.25,0)) | P85: ='08_Premissas_Custos'!$B$15*M85*(1+IF(I85="Sim",0.20,0)+IF(K85="Sim",0.15,0)) | Q85: ='08_Premissas_Custos'!$B$16*M85*IF(J85="Sim",1.6,0.55) | R85: ='08_Premissas_Custos'!$B$17*M85*IF(I85="Sim",1.8,0.15) | S85: ='08_Premissas_Custos'!$B$18*M85*(1+IF(I85="Sim",0.15)+IF(L85="Sim",0.10)) | T85: ='08_Premissas_Custos'!$B$19*M85*(1+IF(J85="Sim",0.15)) | U85: ='08_Premissas_Custos'!$B$20*M85*IF(K85="Sim",1.8,0.7) | V85: =SUM(N85:U85) | W85: =V85*(1-H85)*IF(E85="Fase 2",'08_Premissas_Custos'!$F$10,1) | X85: =(N85*'08_Premissas_Custos'!$C$13+O85*'08_Premissas_Custos'!$C$14+P85*'08_Premissas_Custos'!$C$15+Q85*'08_Premissas_Custos'!$C$16+R85*'08_Premissas_Custos'!$C$17+S85*'08_Premissas_Custos'!$C$18+T85*'08_Premissas_Custos'!$C$19+U85*'08_Premissas_Custos'!$C$20)*(1-H85)*IF(E85="Fase 2",'08_Premissas_Custos'!$F$10,1) | Y85: =X85*'08_Premissas_Custos'!$F$7 | Z85: =(X85+Y85)*'08_Premissas_Custos'!$F$6 | AA85: =SUM(X85:Z85) | AB85: Conexões
A86: 81 | B86: EVT | C86: Eventos | D86: Pesquisa de público / mercado | E86: Fase 2 | F86: Alta | H86: 0 | I86: Não | J86: Sim | K86: Não | L86: Sim | M86: =IF(F86="Baixa",'08_Premissas_Custos'!$B$6,IF(F86="Média",'08_Premissas_Custos'!$B$7,IF(F86="Alta",'08_Premissas_Custos'!$B$8,'08_Premissas_Custos'!$B$9))) | N86: ='08_Premissas_Custos'!$B$13*M86 | O86: ='08_Premissas_Custos'!$B$14*M86*(1+IF(L86="Sim",0.25,0)) | P86: ='08_Premissas_Custos'!$B$15*M86*(1+IF(I86="Sim",0.20,0)+IF(K86="Sim",0.15,0)) | Q86: ='08_Premissas_Custos'!$B$16*M86*IF(J86="Sim",1.6,0.55) | R86: ='08_Premissas_Custos'!$B$17*M86*IF(I86="Sim",1.8,0.15) | S86: ='08_Premissas_Custos'!$B$18*M86*(1+IF(I86="Sim",0.15)+IF(L86="Sim",0.10)) | T86: ='08_Premissas_Custos'!$B$19*M86*(1+IF(J86="Sim",0.15)) | U86: ='08_Premissas_Custos'!$B$20*M86*IF(K86="Sim",1.8,0.7) | V86: =SUM(N86:U86) | W86: =V86*(1-H86)*IF(E86="Fase 2",'08_Premissas_Custos'!$F$10,1) | X86: =(N86*'08_Premissas_Custos'!$C$13+O86*'08_Premissas_Custos'!$C$14+P86*'08_Premissas_Custos'!$C$15+Q86*'08_Premissas_Custos'!$C$16+R86*'08_Premissas_Custos'!$C$17+S86*'08_Premissas_Custos'!$C$18+T86*'08_Premissas_Custos'!$C$19+U86*'08_Premissas_Custos'!$C$20)*(1-H86)*IF(E86="Fase 2",'08_Premissas_Custos'!$F$10,1) | Y86: =X86*'08_Premissas_Custos'!$F$7 | Z86: =(X86+Y86)*'08_Premissas_Custos'!$F$6 | AA86: =SUM(X86:Z86) | AB86: Insights
A87: 82 | B87: EVT | C87: Eventos | D87: Acessibilidade | E87: Fase 2 | F87: Média | H87: 0 | I87: Não | J87: Não | K87: Não | L87: Não | M87: =IF(F87="Baixa",'08_Premissas_Custos'!$B$6,IF(F87="Média",'08_Premissas_Custos'!$B$7,IF(F87="Alta",'08_Premissas_Custos'!$B$8,'08_Premissas_Custos'!$B$9))) | N87: ='08_Premissas_Custos'!$B$13*M87 | O87: ='08_Premissas_Custos'!$B$14*M87*(1+IF(L87="Sim",0.25,0)) | P87: ='08_Premissas_Custos'!$B$15*M87*(1+IF(I87="Sim",0.20,0)+IF(K87="Sim",0.15,0)) | Q87: ='08_Premissas_Custos'!$B$16*M87*IF(J87="Sim",1.6,0.55) | R87: ='08_Premissas_Custos'!$B$17*M87*IF(I87="Sim",1.8,0.15) | S87: ='08_Premissas_Custos'!$B$18*M87*(1+IF(I87="Sim",0.15)+IF(L87="Sim",0.10)) | T87: ='08_Premissas_Custos'!$B$19*M87*(1+IF(J87="Sim",0.15)) | U87: ='08_Premissas_Custos'!$B$20*M87*IF(K87="Sim",1.8,0.7) | V87: =SUM(N87:U87) | W87: =V87*(1-H87)*IF(E87="Fase 2",'08_Premissas_Custos'!$F$10,1) | X87: =(N87*'08_Premissas_Custos'!$C$13+O87*'08_Premissas_Custos'!$C$14+P87*'08_Premissas_Custos'!$C$15+Q87*'08_Premissas_Custos'!$C$16+R87*'08_Premissas_Custos'!$C$17+S87*'08_Premissas_Custos'!$C$18+T87*'08_Premissas_Custos'!$C$19+U87*'08_Premissas_Custos'!$C$20)*(1-H87)*IF(E87="Fase 2",'08_Premissas_Custos'!$F$10,1) | Y87: =X87*'08_Premissas_Custos'!$F$7 | Z87: =(X87+Y87)*'08_Premissas_Custos'!$F$6 | AA87: =SUM(X87:Z87) | AB87: Plano
A88: 83 | B88: EVT | C88: Eventos | D88: Segurança / combate ao assédio | E88: Fase 2 | F88: Alta | H88: 0 | I88: Não | J88: Não | K88: Sim | L88: Sim | M88: =IF(F88="Baixa",'08_Premissas_Custos'!$B$6,IF(F88="Média",'08_Premissas_Custos'!$B$7,IF(F88="Alta",'08_Premissas_Custos'!$B$8,'08_Premissas_Custos'!$B$9))) | N88: ='08_Premissas_Custos'!$B$13*M88 | O88: ='08_Premissas_Custos'!$B$14*M88*(1+IF(L88="Sim",0.25,0)) | P88: ='08_Premissas_Custos'!$B$15*M88*(1+IF(I88="Sim",0.20,0)+IF(K88="Sim",0.15,0)) | Q88: ='08_Premissas_Custos'!$B$16*M88*IF(J88="Sim",1.6,0.55) | R88: ='08_Premissas_Custos'!$B$17*M88*IF(I88="Sim",1.8,0.15) | S88: ='08_Premissas_Custos'!$B$18*M88*(1+IF(I88="Sim",0.15)+IF(L88="Sim",0.10)) | T88: ='08_Premissas_Custos'!$B$19*M88*(1+IF(J88="Sim",0.15)) | U88: ='08_Premissas_Custos'!$B$20*M88*IF(K88="Sim",1.8,0.7) | V88: =SUM(N88:U88) | W88: =V88*(1-H88)*IF(E88="Fase 2",'08_Premissas_Custos'!$F$10,1) | X88: =(N88*'08_Premissas_Custos'!$C$13+O88*'08_Premissas_Custos'!$C$14+P88*'08_Premissas_Custos'!$C$15+Q88*'08_Premissas_Custos'!$C$16+R88*'08_Premissas_Custos'!$C$17+S88*'08_Premissas_Custos'!$C$18+T88*'08_Premissas_Custos'!$C$19+U88*'08_Premissas_Custos'!$C$20)*(1-H88)*IF(E88="Fase 2",'08_Premissas_Custos'!$F$10,1) | Y88: =X88*'08_Premissas_Custos'!$F$7 | Z88: =(X88+Y88)*'08_Premissas_Custos'!$F$6 | AA88: =SUM(X88:Z88) | AB88: Protocolos
A89: 84 | B89: EVT | C89: Eventos | D89: Operação / checklists | E89: Fase 2 | F89: Alta | H89: 0 | I89: Não | J89: Não | K89: Não | L89: Sim | M89: =IF(F89="Baixa",'08_Premissas_Custos'!$B$6,IF(F89="Média",'08_Premissas_Custos'!$B$7,IF(F89="Alta",'08_Premissas_Custos'!$B$8,'08_Premissas_Custos'!$B$9))) | N89: ='08_Premissas_Custos'!$B$13*M89 | O89: ='08_Premissas_Custos'!$B$14*M89*(1+IF(L89="Sim",0.25,0)) | P89: ='08_Premissas_Custos'!$B$15*M89*(1+IF(I89="Sim",0.20,0)+IF(K89="Sim",0.15,0)) | Q89: ='08_Premissas_Custos'!$B$16*M89*IF(J89="Sim",1.6,0.55) | R89: ='08_Premissas_Custos'!$B$17*M89*IF(I89="Sim",1.8,0.15) | S89: ='08_Premissas_Custos'!$B$18*M89*(1+IF(I89="Sim",0.15)+IF(L89="Sim",0.10)) | T89: ='08_Premissas_Custos'!$B$19*M89*(1+IF(J89="Sim",0.15)) | U89: ='08_Premissas_Custos'!$B$20*M89*IF(K89="Sim",1.8,0.7) | V89: =SUM(N89:U89) | W89: =V89*(1-H89)*IF(E89="Fase 2",'08_Premissas_Custos'!$F$10,1) | X89: =(N89*'08_Premissas_Custos'!$C$13+O89*'08_Premissas_Custos'!$C$14+P89*'08_Premissas_Custos'!$C$15+Q89*'08_Premissas_Custos'!$C$16+R89*'08_Premissas_Custos'!$C$17+S89*'08_Premissas_Custos'!$C$18+T89*'08_Premissas_Custos'!$C$19+U89*'08_Premissas_Custos'!$C$20)*(1-H89)*IF(E89="Fase 2",'08_Premissas_Custos'!$F$10,1) | Y89: =X89*'08_Premissas_Custos'!$F$7 | Z89: =(X89+Y89)*'08_Premissas_Custos'!$F$6 | AA89: =SUM(X89:Z89) | AB89: Execução
A90: 85 | B90: EVT | C90: Eventos | D90: Indicadores em tempo real | E90: Fase 2 | F90: Alta | G90: Indicadores em tempo real | H90: 0.45 | I90: Não | J90: Sim | K90: Não | L90: Não | M90: =IF(F90="Baixa",'08_Premissas_Custos'!$B$6,IF(F90="Média",'08_Premissas_Custos'!$B$7,IF(F90="Alta",'08_Premissas_Custos'!$B$8,'08_Premissas_Custos'!$B$9))) | N90: ='08_Premissas_Custos'!$B$13*M90 | O90: ='08_Premissas_Custos'!$B$14*M90*(1+IF(L90="Sim",0.25,0)) | P90: ='08_Premissas_Custos'!$B$15*M90*(1+IF(I90="Sim",0.20,0)+IF(K90="Sim",0.15,0)) | Q90: ='08_Premissas_Custos'!$B$16*M90*IF(J90="Sim",1.6,0.55) | R90: ='08_Premissas_Custos'!$B$17*M90*IF(I90="Sim",1.8,0.15) | S90: ='08_Premissas_Custos'!$B$18*M90*(1+IF(I90="Sim",0.15)+IF(L90="Sim",0.10)) | T90: ='08_Premissas_Custos'!$B$19*M90*(1+IF(J90="Sim",0.15)) | U90: ='08_Premissas_Custos'!$B$20*M90*IF(K90="Sim",1.8,0.7) | V90: =SUM(N90:U90) | W90: =V90*(1-H90)*IF(E90="Fase 2",'08_Premissas_Custos'!$F$10,1) | X90: =(N90*'08_Premissas_Custos'!$C$13+O90*'08_Premissas_Custos'!$C$14+P90*'08_Premissas_Custos'!$C$15+Q90*'08_Premissas_Custos'!$C$16+R90*'08_Premissas_Custos'!$C$17+S90*'08_Premissas_Custos'!$C$18+T90*'08_Premissas_Custos'!$C$19+U90*'08_Premissas_Custos'!$C$20)*(1-H90)*IF(E90="Fase 2",'08_Premissas_Custos'!$F$10,1) | Y90: =X90*'08_Premissas_Custos'!$F$7 | Z90: =(X90+Y90)*'08_Premissas_Custos'!$F$6 | AA90: =SUM(X90:Z90) | AB90: Operação
A91: 86 | B91: EVT | C91: Eventos | D91: ROI / impacto financeiro | E91: Fase 2 | F91: Alta | H91: 0 | I91: Não | J91: Sim | K91: Não | L91: Não | M91: =IF(F91="Baixa",'08_Premissas_Custos'!$B$6,IF(F91="Média",'08_Premissas_Custos'!$B$7,IF(F91="Alta",'08_Premissas_Custos'!$B$8,'08_Premissas_Custos'!$B$9))) | N91: ='08_Premissas_Custos'!$B$13*M91 | O91: ='08_Premissas_Custos'!$B$14*M91*(1+IF(L91="Sim",0.25,0)) | P91: ='08_Premissas_Custos'!$B$15*M91*(1+IF(I91="Sim",0.20,0)+IF(K91="Sim",0.15,0)) | Q91: ='08_Premissas_Custos'!$B$16*M91*IF(J91="Sim",1.6,0.55) | R91: ='08_Premissas_Custos'!$B$17*M91*IF(I91="Sim",1.8,0.15) | S91: ='08_Premissas_Custos'!$B$18*M91*(1+IF(I91="Sim",0.15)+IF(L91="Sim",0.10)) | T91: ='08_Premissas_Custos'!$B$19*M91*(1+IF(J91="Sim",0.15)) | U91: ='08_Premissas_Custos'!$B$20*M91*IF(K91="Sim",1.8,0.7) | V91: =SUM(N91:U91) | W91: =V91*(1-H91)*IF(E91="Fase 2",'08_Premissas_Custos'!$F$10,1) | X91: =(N91*'08_Premissas_Custos'!$C$13+O91*'08_Premissas_Custos'!$C$14+P91*'08_Premissas_Custos'!$C$15+Q91*'08_Premissas_Custos'!$C$16+R91*'08_Premissas_Custos'!$C$17+S91*'08_Premissas_Custos'!$C$18+T91*'08_Premissas_Custos'!$C$19+U91*'08_Premissas_Custos'!$C$20)*(1-H91)*IF(E91="Fase 2",'08_Premissas_Custos'!$F$10,1) | Y91: =X91*'08_Premissas_Custos'!$F$7 | Z91: =(X91+Y91)*'08_Premissas_Custos'!$F$6 | AA91: =SUM(X91:Z91) | AB91: Retorno
A92: 87 | B92: EVT | C92: Eventos | D92: Relatório pós-evento | E92: Fase 2 | F92: Média | H92: 0 | I92: Não | J92: Sim | K92: Não | L92: Não | M92: =IF(F92="Baixa",'08_Premissas_Custos'!$B$6,IF(F92="Média",'08_Premissas_Custos'!$B$7,IF(F92="Alta",'08_Premissas_Custos'!$B$8,'08_Premissas_Custos'!$B$9))) | N92: ='08_Premissas_Custos'!$B$13*M92 | O92: ='08_Premissas_Custos'!$B$14*M92*(1+IF(L92="Sim",0.25,0)) | P92: ='08_Premissas_Custos'!$B$15*M92*(1+IF(I92="Sim",0.20,0)+IF(K92="Sim",0.15,0)) | Q92: ='08_Premissas_Custos'!$B$16*M92*IF(J92="Sim",1.6,0.55) | R92: ='08_Premissas_Custos'!$B$17*M92*IF(I92="Sim",1.8,0.15) | S92: ='08_Premissas_Custos'!$B$18*M92*(1+IF(I92="Sim",0.15)+IF(L92="Sim",0.10)) | T92: ='08_Premissas_Custos'!$B$19*M92*(1+IF(J92="Sim",0.15)) | U92: ='08_Premissas_Custos'!$B$20*M92*IF(K92="Sim",1.8,0.7) | V92: =SUM(N92:U92) | W92: =V92*(1-H92)*IF(E92="Fase 2",'08_Premissas_Custos'!$F$10,1) | X92: =(N92*'08_Premissas_Custos'!$C$13+O92*'08_Premissas_Custos'!$C$14+P92*'08_Premissas_Custos'!$C$15+Q92*'08_Premissas_Custos'!$C$16+R92*'08_Premissas_Custos'!$C$17+S92*'08_Premissas_Custos'!$C$18+T92*'08_Premissas_Custos'!$C$19+U92*'08_Premissas_Custos'!$C$20)*(1-H92)*IF(E92="Fase 2",'08_Premissas_Custos'!$F$10,1) | Y92: =X92*'08_Premissas_Custos'!$F$7 | Z92: =(X92+Y92)*'08_Premissas_Custos'!$F$6 | AA92: =SUM(X92:Z92) | AB92: Resultados
A93: 88 | B93: COM | C93: Comunidades / Eu & Eu / Cultura | D93: Meu perfil | E93: Fase 2 | F93: Baixa | H93: 0 | I93: Não | J93: Não | K93: Não | L93: Sim | M93: =IF(F93="Baixa",'08_Premissas_Custos'!$B$6,IF(F93="Média",'08_Premissas_Custos'!$B$7,IF(F93="Alta",'08_Premissas_Custos'!$B$8,'08_Premissas_Custos'!$B$9))) | N93: ='08_Premissas_Custos'!$B$13*M93 | O93: ='08_Premissas_Custos'!$B$14*M93*(1+IF(L93="Sim",0.25,0)) | P93: ='08_Premissas_Custos'!$B$15*M93*(1+IF(I93="Sim",0.20,0)+IF(K93="Sim",0.15,0)) | Q93: ='08_Premissas_Custos'!$B$16*M93*IF(J93="Sim",1.6,0.55) | R93: ='08_Premissas_Custos'!$B$17*M93*IF(I93="Sim",1.8,0.15) | S93: ='08_Premissas_Custos'!$B$18*M93*(1+IF(I93="Sim",0.15)+IF(L93="Sim",0.10)) | T93: ='08_Premissas_Custos'!$B$19*M93*(1+IF(J93="Sim",0.15)) | U93: ='08_Premissas_Custos'!$B$20*M93*IF(K93="Sim",1.8,0.7) | V93: =SUM(N93:U93) | W93: =V93*(1-H93)*IF(E93="Fase 2",'08_Premissas_Custos'!$F$10,1) | X93: =(N93*'08_Premissas_Custos'!$C$13+O93*'08_Premissas_Custos'!$C$14+P93*'08_Premissas_Custos'!$C$15+Q93*'08_Premissas_Custos'!$C$16+R93*'08_Premissas_Custos'!$C$17+S93*'08_Premissas_Custos'!$C$18+T93*'08_Premissas_Custos'!$C$19+U93*'08_Premissas_Custos'!$C$20)*(1-H93)*IF(E93="Fase 2",'08_Premissas_Custos'!$F$10,1) | Y93: =X93*'08_Premissas_Custos'!$F$7 | Z93: =(X93+Y93)*'08_Premissas_Custos'!$F$6 | AA93: =SUM(X93:Z93) | AB93: Preferências
A94: 89 | B94: COM | C94: Comunidades / Eu & Eu / Cultura | D94: Objetivos | E94: Fase 2 | F94: Média | H94: 0 | I94: Não | J94: Não | K94: Não | L94: Sim | M94: =IF(F94="Baixa",'08_Premissas_Custos'!$B$6,IF(F94="Média",'08_Premissas_Custos'!$B$7,IF(F94="Alta",'08_Premissas_Custos'!$B$8,'08_Premissas_Custos'!$B$9))) | N94: ='08_Premissas_Custos'!$B$13*M94 | O94: ='08_Premissas_Custos'!$B$14*M94*(1+IF(L94="Sim",0.25,0)) | P94: ='08_Premissas_Custos'!$B$15*M94*(1+IF(I94="Sim",0.20,0)+IF(K94="Sim",0.15,0)) | Q94: ='08_Premissas_Custos'!$B$16*M94*IF(J94="Sim",1.6,0.55) | R94: ='08_Premissas_Custos'!$B$17*M94*IF(I94="Sim",1.8,0.15) | S94: ='08_Premissas_Custos'!$B$18*M94*(1+IF(I94="Sim",0.15)+IF(L94="Sim",0.10)) | T94: ='08_Premissas_Custos'!$B$19*M94*(1+IF(J94="Sim",0.15)) | U94: ='08_Premissas_Custos'!$B$20*M94*IF(K94="Sim",1.8,0.7) | V94: =SUM(N94:U94) | W94: =V94*(1-H94)*IF(E94="Fase 2",'08_Premissas_Custos'!$F$10,1) | X94: =(N94*'08_Premissas_Custos'!$C$13+O94*'08_Premissas_Custos'!$C$14+P94*'08_Premissas_Custos'!$C$15+Q94*'08_Premissas_Custos'!$C$16+R94*'08_Premissas_Custos'!$C$17+S94*'08_Premissas_Custos'!$C$18+T94*'08_Premissas_Custos'!$C$19+U94*'08_Premissas_Custos'!$C$20)*(1-H94)*IF(E94="Fase 2",'08_Premissas_Custos'!$F$10,1) | Y94: =X94*'08_Premissas_Custos'!$F$7 | Z94: =(X94+Y94)*'08_Premissas_Custos'!$F$6 | AA94: =SUM(X94:Z94) | AB94: Metas
A95: 90 | B95: COM | C95: Comunidades / Eu & Eu / Cultura | D95: Plano de ação | E95: Fase 2 | F95: Média | H95: 0 | I95: Não | J95: Não | K95: Não | L95: Sim | M95: =IF(F95="Baixa",'08_Premissas_Custos'!$B$6,IF(F95="Média",'08_Premissas_Custos'!$B$7,IF(F95="Alta",'08_Premissas_Custos'!$B$8,'08_Premissas_Custos'!$B$9))) | N95: ='08_Premissas_Custos'!$B$13*M95 | O95: ='08_Premissas_Custos'!$B$14*M95*(1+IF(L95="Sim",0.25,0)) | P95: ='08_Premissas_Custos'!$B$15*M95*(1+IF(I95="Sim",0.20,0)+IF(K95="Sim",0.15,0)) | Q95: ='08_Premissas_Custos'!$B$16*M95*IF(J95="Sim",1.6,0.55) | R95: ='08_Premissas_Custos'!$B$17*M95*IF(I95="Sim",1.8,0.15) | S95: ='08_Premissas_Custos'!$B$18*M95*(1+IF(I95="Sim",0.15)+IF(L95="Sim",0.10)) | T95: ='08_Premissas_Custos'!$B$19*M95*(1+IF(J95="Sim",0.15)) | U95: ='08_Premissas_Custos'!$B$20*M95*IF(K95="Sim",1.8,0.7) | V95: =SUM(N95:U95) | W95: =V95*(1-H95)*IF(E95="Fase 2",'08_Premissas_Custos'!$F$10,1) | X95: =(N95*'08_Premissas_Custos'!$C$13+O95*'08_Premissas_Custos'!$C$14+P95*'08_Premissas_Custos'!$C$15+Q95*'08_Premissas_Custos'!$C$16+R95*'08_Premissas_Custos'!$C$17+S95*'08_Premissas_Custos'!$C$18+T95*'08_Premissas_Custos'!$C$19+U95*'08_Premissas_Custos'!$C$20)*(1-H95)*IF(E95="Fase 2",'08_Premissas_Custos'!$F$10,1) | Y95: =X95*'08_Premissas_Custos'!$F$7 | Z95: =(X95+Y95)*'08_Premissas_Custos'!$F$6 | AA95: =SUM(X95:Z95) | AB95: Passos
A96: 91 | B96: COM | C96: Comunidades / Eu & Eu / Cultura | D96: Preparação / conteúdos | E96: Fase 2 | F96: Média | H96: 0 | I96: Não | J96: Não | K96: Não | L96: Sim | M96: =IF(F96="Baixa",'08_Premissas_Custos'!$B$6,IF(F96="Média",'08_Premissas_Custos'!$B$7,IF(F96="Alta",'08_Premissas_Custos'!$B$8,'08_Premissas_Custos'!$B$9))) | N96: ='08_Premissas_Custos'!$B$13*M96 | O96: ='08_Premissas_Custos'!$B$14*M96*(1+IF(L96="Sim",0.25,0)) | P96: ='08_Premissas_Custos'!$B$15*M96*(1+IF(I96="Sim",0.20,0)+IF(K96="Sim",0.15,0)) | Q96: ='08_Premissas_Custos'!$B$16*M96*IF(J96="Sim",1.6,0.55) | R96: ='08_Premissas_Custos'!$B$17*M96*IF(I96="Sim",1.8,0.15) | S96: ='08_Premissas_Custos'!$B$18*M96*(1+IF(I96="Sim",0.15)+IF(L96="Sim",0.10)) | T96: ='08_Premissas_Custos'!$B$19*M96*(1+IF(J96="Sim",0.15)) | U96: ='08_Premissas_Custos'!$B$20*M96*IF(K96="Sim",1.8,0.7) | V96: =SUM(N96:U96) | W96: =V96*(1-H96)*IF(E96="Fase 2",'08_Premissas_Custos'!$F$10,1) | X96: =(N96*'08_Premissas_Custos'!$C$13+O96*'08_Premissas_Custos'!$C$14+P96*'08_Premissas_Custos'!$C$15+Q96*'08_Premissas_Custos'!$C$16+R96*'08_Premissas_Custos'!$C$17+S96*'08_Premissas_Custos'!$C$18+T96*'08_Premissas_Custos'!$C$19+U96*'08_Premissas_Custos'!$C$20)*(1-H96)*IF(E96="Fase 2",'08_Premissas_Custos'!$F$10,1) | Y96: =X96*'08_Premissas_Custos'!$F$7 | Z96: =(X96+Y96)*'08_Premissas_Custos'!$F$6 | AA96: =SUM(X96:Z96) | AB96: Trilhas
A97: 92 | B97: COM | C97: Comunidades / Eu & Eu / Cultura | D97: Mentoria | E97: Fase 2 | F97: Média | H97: 0 | I97: Não | J97: Não | K97: Não | L97: Sim | M97: =IF(F97="Baixa",'08_Premissas_Custos'!$B$6,IF(F97="Média",'08_Premissas_Custos'!$B$7,IF(F97="Alta",'08_Premissas_Custos'!$B$8,'08_Premissas_Custos'!$B$9))) | N97: ='08_Premissas_Custos'!$B$13*M97 | O97: ='08_Premissas_Custos'!$B$14*M97*(1+IF(L97="Sim",0.25,0)) | P97: ='08_Premissas_Custos'!$B$15*M97*(1+IF(I97="Sim",0.20,0)+IF(K97="Sim",0.15,0)) | Q97: ='08_Premissas_Custos'!$B$16*M97*IF(J97="Sim",1.6,0.55) | R97: ='08_Premissas_Custos'!$B$17*M97*IF(I97="Sim",1.8,0.15) | S97: ='08_Premissas_Custos'!$B$18*M97*(1+IF(I97="Sim",0.15)+IF(L97="Sim",0.10)) | T97: ='08_Premissas_Custos'!$B$19*M97*(1+IF(J97="Sim",0.15)) | U97: ='08_Premissas_Custos'!$B$20*M97*IF(K97="Sim",1.8,0.7) | V97: =SUM(N97:U97) | W97: =V97*(1-H97)*IF(E97="Fase 2",'08_Premissas_Custos'!$F$10,1) | X97: =(N97*'08_Premissas_Custos'!$C$13+O97*'08_Premissas_Custos'!$C$14+P97*'08_Premissas_Custos'!$C$15+Q97*'08_Premissas_Custos'!$C$16+R97*'08_Premissas_Custos'!$C$17+S97*'08_Premissas_Custos'!$C$18+T97*'08_Premissas_Custos'!$C$19+U97*'08_Premissas_Custos'!$C$20)*(1-H97)*IF(E97="Fase 2",'08_Premissas_Custos'!$F$10,1) | Y97: =X97*'08_Premissas_Custos'!$F$7 | Z97: =(X97+Y97)*'08_Premissas_Custos'!$F$6 | AA97: =SUM(X97:Z97) | AB97: Conexões
A98: 93 | B98: COM | C98: Comunidades / Eu & Eu / Cultura | D98: Saúde & cuidado | E98: Fase 2 | F98: Alta | H98: 0 | I98: Não | J98: Sim | K98: Não | L98: Sim | M98: =IF(F98="Baixa",'08_Premissas_Custos'!$B$6,IF(F98="Média",'08_Premissas_Custos'!$B$7,IF(F98="Alta",'08_Premissas_Custos'!$B$8,'08_Premissas_Custos'!$B$9))) | N98: ='08_Premissas_Custos'!$B$13*M98 | O98: ='08_Premissas_Custos'!$B$14*M98*(1+IF(L98="Sim",0.25,0)) | P98: ='08_Premissas_Custos'!$B$15*M98*(1+IF(I98="Sim",0.20,0)+IF(K98="Sim",0.15,0)) | Q98: ='08_Premissas_Custos'!$B$16*M98*IF(J98="Sim",1.6,0.55) | R98: ='08_Premissas_Custos'!$B$17*M98*IF(I98="Sim",1.8,0.15) | S98: ='08_Premissas_Custos'!$B$18*M98*(1+IF(I98="Sim",0.15)+IF(L98="Sim",0.10)) | T98: ='08_Premissas_Custos'!$B$19*M98*(1+IF(J98="Sim",0.15)) | U98: ='08_Premissas_Custos'!$B$20*M98*IF(K98="Sim",1.8,0.7) | V98: =SUM(N98:U98) | W98: =V98*(1-H98)*IF(E98="Fase 2",'08_Premissas_Custos'!$F$10,1) | X98: =(N98*'08_Premissas_Custos'!$C$13+O98*'08_Premissas_Custos'!$C$14+P98*'08_Premissas_Custos'!$C$15+Q98*'08_Premissas_Custos'!$C$16+R98*'08_Premissas_Custos'!$C$17+S98*'08_Premissas_Custos'!$C$18+T98*'08_Premissas_Custos'!$C$19+U98*'08_Premissas_Custos'!$C$20)*(1-H98)*IF(E98="Fase 2",'08_Premissas_Custos'!$F$10,1) | Y98: =X98*'08_Premissas_Custos'!$F$7 | Z98: =(X98+Y98)*'08_Premissas_Custos'!$F$6 | AA98: =SUM(X98:Z98) | AB98: Recursos
A99: 94 | B99: COM | C99: Comunidades / Eu & Eu / Cultura | D99: Eventos da comunidade | E99: Fase 2 | F99: Média | H99: 0 | I99: Não | J99: Não | K99: Não | L99: Sim | M99: =IF(F99="Baixa",'08_Premissas_Custos'!$B$6,IF(F99="Média",'08_Premissas_Custos'!$B$7,IF(F99="Alta",'08_Premissas_Custos'!$B$8,'08_Premissas_Custos'!$B$9))) | N99: ='08_Premissas_Custos'!$B$13*M99 | O99: ='08_Premissas_Custos'!$B$14*M99*(1+IF(L99="Sim",0.25,0)) | P99: ='08_Premissas_Custos'!$B$15*M99*(1+IF(I99="Sim",0.20,0)+IF(K99="Sim",0.15,0)) | Q99: ='08_Premissas_Custos'!$B$16*M99*IF(J99="Sim",1.6,0.55) | R99: ='08_Premissas_Custos'!$B$17*M99*IF(I99="Sim",1.8,0.15) | S99: ='08_Premissas_Custos'!$B$18*M99*(1+IF(I99="Sim",0.15)+IF(L99="Sim",0.10)) | T99: ='08_Premissas_Custos'!$B$19*M99*(1+IF(J99="Sim",0.15)) | U99: ='08_Premissas_Custos'!$B$20*M99*IF(K99="Sim",1.8,0.7) | V99: =SUM(N99:U99) | W99: =V99*(1-H99)*IF(E99="Fase 2",'08_Premissas_Custos'!$F$10,1) | X99: =(N99*'08_Premissas_Custos'!$C$13+O99*'08_Premissas_Custos'!$C$14+P99*'08_Premissas_Custos'!$C$15+Q99*'08_Premissas_Custos'!$C$16+R99*'08_Premissas_Custos'!$C$17+S99*'08_Premissas_Custos'!$C$18+T99*'08_Premissas_Custos'!$C$19+U99*'08_Premissas_Custos'!$C$20)*(1-H99)*IF(E99="Fase 2",'08_Premissas_Custos'!$F$10,1) | Y99: =X99*'08_Premissas_Custos'!$F$7 | Z99: =(X99+Y99)*'08_Premissas_Custos'!$F$6 | AA99: =SUM(X99:Z99) | AB99: Agenda
A100: 95 | B100: COM | C100: Comunidades / Eu & Eu / Cultura | D100: Conexões com empresas | E100: Fase 2 | F100: Alta | H100: 0 | I100: Não | J100: Não | K100: Não | L100: Sim | M100: =IF(F100="Baixa",'08_Premissas_Custos'!$B$6,IF(F100="Média",'08_Premissas_Custos'!$B$7,IF(F100="Alta",'08_Premissas_Custos'!$B$8,'08_Premissas_Custos'!$B$9))) | N100: ='08_Premissas_Custos'!$B$13*M100 | O100: ='08_Premissas_Custos'!$B$14*M100*(1+IF(L100="Sim",0.25,0)) | P100: ='08_Premissas_Custos'!$B$15*M100*(1+IF(I100="Sim",0.20,0)+IF(K100="Sim",0.15,0)) | Q100: ='08_Premissas_Custos'!$B$16*M100*IF(J100="Sim",1.6,0.55) | R100: ='08_Premissas_Custos'!$B$17*M100*IF(I100="Sim",1.8,0.15) | S100: ='08_Premissas_Custos'!$B$18*M100*(1+IF(I100="Sim",0.15)+IF(L100="Sim",0.10)) | T100: ='08_Premissas_Custos'!$B$19*M100*(1+IF(J100="Sim",0.15)) | U100: ='08_Premissas_Custos'!$B$20*M100*IF(K100="Sim",1.8,0.7) | V100: =SUM(N100:U100) | W100: =V100*(1-H100)*IF(E100="Fase 2",'08_Premissas_Custos'!$F$10,1) | X100: =(N100*'08_Premissas_Custos'!$C$13+O100*'08_Premissas_Custos'!$C$14+P100*'08_Premissas_Custos'!$C$15+Q100*'08_Premissas_Custos'!$C$16+R100*'08_Premissas_Custos'!$C$17+S100*'08_Premissas_Custos'!$C$18+T100*'08_Premissas_Custos'!$C$19+U100*'08_Premissas_Custos'!$C$20)*(1-H100)*IF(E100="Fase 2",'08_Premissas_Custos'!$F$10,1) | Y100: =X100*'08_Premissas_Custos'!$F$7 | Z100: =(X100+Y100)*'08_Premissas_Custos'!$F$6 | AA100: =SUM(X100:Z100) | AB100: Oportunidades
A101: 96 | B101: COM | C101: Comunidades / Eu & Eu / Cultura | D101: Acadêmico | E101: Fase 2 | F101: Média | H101: 0 | I101: Não | J101: Não | K101: Não | L101: Sim | M101: =IF(F101="Baixa",'08_Premissas_Custos'!$B$6,IF(F101="Média",'08_Premissas_Custos'!$B$7,IF(F101="Alta",'08_Premissas_Custos'!$B$8,'08_Premissas_Custos'!$B$9))) | N101: ='08_Premissas_Custos'!$B$13*M101 | O101: ='08_Premissas_Custos'!$B$14*M101*(1+IF(L101="Sim",0.25,0)) | P101: ='08_Premissas_Custos'!$B$15*M101*(1+IF(I101="Sim",0.20,0)+IF(K101="Sim",0.15,0)) | Q101: ='08_Premissas_Custos'!$B$16*M101*IF(J101="Sim",1.6,0.55) | R101: ='08_Premissas_Custos'!$B$17*M101*IF(I101="Sim",1.8,0.15) | S101: ='08_Premissas_Custos'!$B$18*M101*(1+IF(I101="Sim",0.15)+IF(L101="Sim",0.10)) | T101: ='08_Premissas_Custos'!$B$19*M101*(1+IF(J101="Sim",0.15)) | U101: ='08_Premissas_Custos'!$B$20*M101*IF(K101="Sim",1.8,0.7) | V101: =SUM(N101:U101) | W101: =V101*(1-H101)*IF(E101="Fase 2",'08_Premissas_Custos'!$F$10,1) | X101: =(N101*'08_Premissas_Custos'!$C$13+O101*'08_Premissas_Custos'!$C$14+P101*'08_Premissas_Custos'!$C$15+Q101*'08_Premissas_Custos'!$C$16+R101*'08_Premissas_Custos'!$C$17+S101*'08_Premissas_Custos'!$C$18+T101*'08_Premissas_Custos'!$C$19+U101*'08_Premissas_Custos'!$C$20)*(1-H101)*IF(E101="Fase 2",'08_Premissas_Custos'!$F$10,1) | Y101: =X101*'08_Premissas_Custos'!$F$7 | Z101: =(X101+Y101)*'08_Premissas_Custos'!$F$6 | AA101: =SUM(X101:Z101) | AB101: Formação
A102: 97 | B102: ED | C102: Estratégia & Dados | D102: Catálogo e versionamento de KPIs | E102: MVP | F102: Alta | H102: 0 | I102: Não | J102: Sim | K102: Não | L102: Não | M102: =IF(F102="Baixa",'08_Premissas_Custos'!$B$6,IF(F102="Média",'08_Premissas_Custos'!$B$7,IF(F102="Alta",'08_Premissas_Custos'!$B$8,'08_Premissas_Custos'!$B$9))) | N102: ='08_Premissas_Custos'!$B$13*M102 | O102: ='08_Premissas_Custos'!$B$14*M102*(1+IF(L102="Sim",0.25,0)) | P102: ='08_Premissas_Custos'!$B$15*M102*(1+IF(I102="Sim",0.20,0)+IF(K102="Sim",0.15,0)) | Q102: ='08_Premissas_Custos'!$B$16*M102*IF(J102="Sim",1.6,0.55) | R102: ='08_Premissas_Custos'!$B$17*M102*IF(I102="Sim",1.8,0.15) | S102: ='08_Premissas_Custos'!$B$18*M102*(1+IF(I102="Sim",0.15)+IF(L102="Sim",0.10)) | T102: ='08_Premissas_Custos'!$B$19*M102*(1+IF(J102="Sim",0.15)) | U102: ='08_Premissas_Custos'!$B$20*M102*IF(K102="Sim",1.8,0.7) | V102: =SUM(N102:U102) | W102: =V102*(1-H102)*IF(E102="Fase 2",'08_Premissas_Custos'!$F$10,1) | X102: =(N102*'08_Premissas_Custos'!$C$13+O102*'08_Premissas_Custos'!$C$14+P102*'08_Premissas_Custos'!$C$15+Q102*'08_Premissas_Custos'!$C$16+R102*'08_Premissas_Custos'!$C$17+S102*'08_Premissas_Custos'!$C$18+T102*'08_Premissas_Custos'!$C$19+U102*'08_Premissas_Custos'!$C$20)*(1-H102)*IF(E102="Fase 2",'08_Premissas_Custos'!$F$10,1) | Y102: =X102*'08_Premissas_Custos'!$F$7 | Z102: =(X102+Y102)*'08_Premissas_Custos'!$F$6 | AA102: =SUM(X102:Z102) | AB102: Fórmula, owner, aprovação
...

Sheet 10_CAPEX_por_Modulo
A1: CAPEX E CUSTO INCREMENTAL POR MÓDULO
A3: O custo incremental exclui o Core compartilhado. Isso permite precificar cada vertical sem cobrar novamente a infraestrutura-base já construída.
A5: Código | B5: Módulo | C5: Telas | D5: MVP | E5: Fase 2 | F5: Horas líquidas | G5: CAPEX total | H5: CAPEX MVP | I5: CAPEX Fase 2 | J5: Core alocado | K5: Custo incremental | L5: % do CAPEX | M5: Complexas | N5: Leitura comercial | O5: MVP+1 | P5: CAPEX MVP+1
A6: CORE | B6: Core / Plataforma | C6: =COUNTIF('09_Estimativa_96_Telas'!$B$6:$B$200,A6) | D6: =COUNTIFS('09_Estimativa_96_Telas'!$B$6:$B$200,A6,'09_Estimativa_96_Telas'!$E$6:$E$200,"MVP") | E6: =COUNTIFS('09_Estimativa_96_Telas'!$B$6:$B$200,A6,'09_Estimativa_96_Telas'!$E$6:$E$200,"Fase 2") | F6: =SUMIF('09_Estimativa_96_Telas'!$B$6:$B$200,A6,'09_Estimativa_96_Telas'!$W$6:$W$200) | G6: =SUMIF('09_Estimativa_96_Telas'!$B$6:$B$200,A6,'09_Estimativa_96_Telas'!$AA$6:$AA$200) | H6: =SUMIFS('09_Estimativa_96_Telas'!$AA$6:$AA$200,'09_Estimativa_96_Telas'!$B$6:$B$200,A6,'09_Estimativa_96_Telas'!$E$6:$E$200,"MVP") | I6: =SUMIFS('09_Estimativa_96_Telas'!$AA$6:$AA$200,'09_Estimativa_96_Telas'!$B$6:$B$200,A6,'09_Estimativa_96_Telas'!$E$6:$E$200,"Fase 2") | J6: =IF(A6="CORE",G6,$G$6/8) | K6: =IF(A6="CORE",G6,G6) | L6: =G6/SUM($G$6:$G$14) | M6: =COUNTIFS('02_Inventario_Paginas'!$B$6:$B$200,A6,'02_Inventario_Paginas'!$G$6:$G$200,"Alta")+COUNTIFS('02_Inventario_Paginas'!$B$6:$B$200,A6,'02_Inventario_Paginas'!$G$6:$G$200,"Muito alta") | N6: Base compartilhada | O6: =COUNTIFS('09_Estimativa_96_Telas'!$B$6:$B$200,A6,'09_Estimativa_96_Telas'!$E$6:$E$200,"MVP+1") | P6: =SUMIFS('09_Estimativa_96_Telas'!$AA$6:$AA$200,'09_Estimativa_96_Telas'!$B$6:$B$200,A6,'09_Estimativa_96_Telas'!$E$6:$E$200,"MVP+1")
A7: ED | B7: Estratégia & Dados | C7: =COUNTIF('09_Estimativa_96_Telas'!$B$6:$B$200,A7) | D7: =COUNTIFS('09_Estimativa_96_Telas'!$B$6:$B$200,A7,'09_Estimativa_96_Telas'!$E$6:$E$200,"MVP") | E7: =COUNTIFS('09_Estimativa_96_Telas'!$B$6:$B$200,A7,'09_Estimativa_96_Telas'!$E$6:$E$200,"Fase 2") | F7: =SUMIF('09_Estimativa_96_Telas'!$B$6:$B$200,A7,'09_Estimativa_96_Telas'!$W$6:$W$200) | G7: =SUMIF('09_Estimativa_96_Telas'!$B$6:$B$200,A7,'09_Estimativa_96_Telas'!$AA$6:$AA$200) | H7: =SUMIFS('09_Estimativa_96_Telas'!$AA$6:$AA$200,'09_Estimativa_96_Telas'!$B$6:$B$200,A7,'09_Estimativa_96_Telas'!$E$6:$E$200,"MVP") | I7: =SUMIFS('09_Estimativa_96_Telas'!$AA$6:$AA$200,'09_Estimativa_96_Telas'!$B$6:$B$200,A7,'09_Estimativa_96_Telas'!$E$6:$E$200,"Fase 2") | J7: =IF(A7="CORE",G7,$G$6/8) | K7: =IF(A7="CORE",G7,G7) | L7: =G7/SUM($G$6:$G$14) | M7: =COUNTIFS('02_Inventario_Paginas'!$B$6:$B$200,A7,'02_Inventario_Paginas'!$G$6:$G$200,"Alta")+COUNTIFS('02_Inventario_Paginas'!$B$6:$B$200,A7,'02_Inventario_Paginas'!$G$6:$G$200,"Muito alta") | N7: Preço do módulo = incremental + parcela de Core + implantação/integrações específicas do cliente | O7: =COUNTIFS('09_Estimativa_96_Telas'!$B$6:$B$200,A7,'09_Estimativa_96_Telas'!$E$6:$E$200,"MVP+1") | P7: =SUMIFS('09_Estimativa_96_Telas'!$AA$6:$AA$200,'09_Estimativa_96_Telas'!$B$6:$B$200,A7,'09_Estimativa_96_Telas'!$E$6:$E$200,"MVP+1")
A8: COL | B8: Colaboradores / Meu Time | C8: =COUNTIF('09_Estimativa_96_Telas'!$B$6:$B$200,A8) | D8: =COUNTIFS('09_Estimativa_96_Telas'!$B$6:$B$200,A8,'09_Estimativa_96_Telas'!$E$6:$E$200,"MVP") | E8: =COUNTIFS('09_Estimativa_96_Telas'!$B$6:$B$200,A8,'09_Estimativa_96_Telas'!$E$6:$E$200,"Fase 2") | F8: =SUMIF('09_Estimativa_96_Telas'!$B$6:$B$200,A8,'09_Estimativa_96_Telas'!$W$6:$W$200) | G8: =SUMIF('09_Estimativa_96_Telas'!$B$6:$B$200,A8,'09_Estimativa_96_Telas'!$AA$6:$AA$200) | H8: =SUMIFS('09_Estimativa_96_Telas'!$AA$6:$AA$200,'09_Estimativa_96_Telas'!$B$6:$B$200,A8,'09_Estimativa_96_Telas'!$E$6:$E$200,"MVP") | I8: =SUMIFS('09_Estimativa_96_Telas'!$AA$6:$AA$200,'09_Estimativa_96_Telas'!$B$6:$B$200,A8,'09_Estimativa_96_Telas'!$E$6:$E$200,"Fase 2") | J8: =IF(A8="CORE",G8,$G$6/8) | K8: =IF(A8="CORE",G8,G8) | L8: =G8/SUM($G$6:$G$14) | M8: =COUNTIFS('02_Inventario_Paginas'!$B$6:$B$200,A8,'02_Inventario_Paginas'!$G$6:$G$200,"Alta")+COUNTIFS('02_Inventario_Paginas'!$B$6:$B$200,A8,'02_Inventario_Paginas'!$G$6:$G$200,"Muito alta") | N8: Preço do módulo = incremental + parcela de Core + implantação/integrações específicas do cliente | O8: =COUNTIFS('09_Estimativa_96_Telas'!$B$6:$B$200,A8,'09_Estimativa_96_Telas'!$E$6:$E$200,"MVP+1") | P8: =SUMIFS('09_Estimativa_96_Telas'!$AA$6:$AA$200,'09_Estimativa_96_Telas'!$B$6:$B$200,A8,'09_Estimativa_96_Telas'!$E$6:$E$200,"MVP+1")
A9: CAN | B9: Candidatos & Carreira | C9: =COUNTIF('09_Estimativa_96_Telas'!$B$6:$B$200,A9) | D9: =COUNTIFS('09_Estimativa_96_Telas'!$B$6:$B$200,A9,'09_Estimativa_96_Telas'!$E$6:$E$200,"MVP") | E9: =COUNTIFS('09_Estimativa_96_Telas'!$B$6:$B$200,A9,'09_Estimativa_96_Telas'!$E$6:$E$200,"Fase 2") | F9: =SUMIF('09_Estimativa_96_Telas'!$B$6:$B$200,A9,'09_Estimativa_96_Telas'!$W$6:$W$200) | G9: =SUMIF('09_Estimativa_96_Telas'!$B$6:$B$200,A9,'09_Estimativa_96_Telas'!$AA$6:$AA$200) | H9: =SUMIFS('09_Estimativa_96_Telas'!$AA$6:$AA$200,'09_Estimativa_96_Telas'!$B$6:$B$200,A9,'09_Estimativa_96_Telas'!$E$6:$E$200,"MVP") | I9: =SUMIFS('09_Estimativa_96_Telas'!$AA$6:$AA$200,'09_Estimativa_96_Telas'!$B$6:$B$200,A9,'09_Estimativa_96_Telas'!$E$6:$E$200,"Fase 2") | J9: =IF(A9="CORE",G9,$G$6/8) | K9: =IF(A9="CORE",G9,G9) | L9: =G9/SUM($G$6:$G$14) | M9: =COUNTIFS('02_Inventario_Paginas'!$B$6:$B$200,A9,'02_Inventario_Paginas'!$G$6:$G$200,"Alta")+COUNTIFS('02_Inventario_Paginas'!$B$6:$B$200,A9,'02_Inventario_Paginas'!$G$6:$G$200,"Muito alta") | N9: Preço do módulo = incremental + parcela de Core + implantação/integrações específicas do cliente | O9: =COUNTIFS('09_Estimativa_96_Telas'!$B$6:$B$200,A9,'09_Estimativa_96_Telas'!$E$6:$E$200,"MVP+1") | P9: =SUMIFS('09_Estimativa_96_Telas'!$AA$6:$AA$200,'09_Estimativa_96_Telas'!$B$6:$B$200,A9,'09_Estimativa_96_Telas'!$E$6:$E$200,"MVP+1")
A10: FOR | B10: Fornecedores & Negócios | C10: =COUNTIF('09_Estimativa_96_Telas'!$B$6:$B$200,A10) | D10: =COUNTIFS('09_Estimativa_96_Telas'!$B$6:$B$200,A10,'09_Estimativa_96_Telas'!$E$6:$E$200,"MVP") | E10: =COUNTIFS('09_Estimativa_96_Telas'!$B$6:$B$200,A10,'09_Estimativa_96_Telas'!$E$6:$E$200,"Fase 2") | F10: =SUMIF('09_Estimativa_96_Telas'!$B$6:$B$200,A10,'09_Estimativa_96_Telas'!$W$6:$W$200) | G10: =SUMIF('09_Estimativa_96_Telas'!$B$6:$B$200,A10,'09_Estimativa_96_Telas'!$AA$6:$AA$200) | H10: =SUMIFS('09_Estimativa_96_Telas'!$AA$6:$AA$200,'09_Estimativa_96_Telas'!$B$6:$B$200,A10,'09_Estimativa_96_Telas'!$E$6:$E$200,"MVP") | I10: =SUMIFS('09_Estimativa_96_Telas'!$AA$6:$AA$200,'09_Estimativa_96_Telas'!$B$6:$B$200,A10,'09_Estimativa_96_Telas'!$E$6:$E$200,"Fase 2") | J10: =IF(A10="CORE",G10,$G$6/8) | K10: =IF(A10="CORE",G10,G10) | L10: =G10/SUM($G$6:$G$14) | M10: =COUNTIFS('02_Inventario_Paginas'!$B$6:$B$200,A10,'02_Inventario_Paginas'!$G$6:$G$200,"Alta")+COUNTIFS('02_Inventario_Paginas'!$B$6:$B$200,A10,'02_Inventario_Paginas'!$G$6:$G$200,"Muito alta") | N10: Preço do módulo = incremental + parcela de Core + implantação/integrações específicas do cliente | O10: =COUNTIFS('09_Estimativa_96_Telas'!$B$6:$B$200,A10,'09_Estimativa_96_Telas'!$E$6:$E$200,"MVP+1") | P10: =SUMIFS('09_Estimativa_96_Telas'!$AA$6:$AA$200,'09_Estimativa_96_Telas'!$B$6:$B$200,A10,'09_Estimativa_96_Telas'!$E$6:$E$200,"MVP+1")
A11: ACA | B11: Acadêmico / Universidades | C11: =COUNTIF('09_Estimativa_96_Telas'!$B$6:$B$200,A11) | D11: =COUNTIFS('09_Estimativa_96_Telas'!$B$6:$B$200,A11,'09_Estimativa_96_Telas'!$E$6:$E$200,"MVP") | E11: =COUNTIFS('09_Estimativa_96_Telas'!$B$6:$B$200,A11,'09_Estimativa_96_Telas'!$E$6:$E$200,"Fase 2") | F11: =SUMIF('09_Estimativa_96_Telas'!$B$6:$B$200,A11,'09_Estimativa_96_Telas'!$W$6:$W$200) | G11: =SUMIF('09_Estimativa_96_Telas'!$B$6:$B$200,A11,'09_Estimativa_96_Telas'!$AA$6:$AA$200) | H11: =SUMIFS('09_Estimativa_96_Telas'!$AA$6:$AA$200,'09_Estimativa_96_Telas'!$B$6:$B$200,A11,'09_Estimativa_96_Telas'!$E$6:$E$200,"MVP") | I11: =SUMIFS('09_Estimativa_96_Telas'!$AA$6:$AA$200,'09_Estimativa_96_Telas'!$B$6:$B$200,A11,'09_Estimativa_96_Telas'!$E$6:$E$200,"Fase 2") | J11: =IF(A11="CORE",G11,$G$6/8) | K11: =IF(A11="CORE",G11,G11) | L11: =G11/SUM($G$6:$G$14) | M11: =COUNTIFS('02_Inventario_Paginas'!$B$6:$B$200,A11,'02_Inventario_Paginas'!$G$6:$G$200,"Alta")+COUNTIFS('02_Inventario_Paginas'!$B$6:$B$200,A11,'02_Inventario_Paginas'!$G$6:$G$200,"Muito alta") | N11: Preço do módulo = incremental + parcela de Core + implantação/integrações específicas do cliente | O11: =COUNTIFS('09_Estimativa_96_Telas'!$B$6:$B$200,A11,'09_Estimativa_96_Telas'!$E$6:$E$200,"MVP+1") | P11: =SUMIFS('09_Estimativa_96_Telas'!$AA$6:$AA$200,'09_Estimativa_96_Telas'!$B$6:$B$200,A11,'09_Estimativa_96_Telas'!$E$6:$E$200,"MVP+1")
A12: EVT | B12: Eventos | C12: =COUNTIF('09_Estimativa_96_Telas'!$B$6:$B$200,A12) | D12: =COUNTIFS('09_Estimativa_96_Telas'!$B$6:$B$200,A12,'09_Estimativa_96_Telas'!$E$6:$E$200,"MVP") | E12: =COUNTIFS('09_Estimativa_96_Telas'!$B$6:$B$200,A12,'09_Estimativa_96_Telas'!$E$6:$E$200,"Fase 2") | F12: =SUMIF('09_Estimativa_96_Telas'!$B$6:$B$200,A12,'09_Estimativa_96_Telas'!$W$6:$W$200) | G12: =SUMIF('09_Estimativa_96_Telas'!$B$6:$B$200,A12,'09_Estimativa_96_Telas'!$AA$6:$AA$200) | H12: =SUMIFS('09_Estimativa_96_Telas'!$AA$6:$AA$200,'09_Estimativa_96_Telas'!$B$6:$B$200,A12,'09_Estimativa_96_Telas'!$E$6:$E$200,"MVP") | I12: =SUMIFS('09_Estimativa_96_Telas'!$AA$6:$AA$200,'09_Estimativa_96_Telas'!$B$6:$B$200,A12,'09_Estimativa_96_Telas'!$E$6:$E$200,"Fase 2") | J12: =IF(A12="CORE",G12,$G$6/8) | K12: =IF(A12="CORE",G12,G12) | L12: =G12/SUM($G$6:$G$14) | M12: =COUNTIFS('02_Inventario_Paginas'!$B$6:$B$200,A12,'02_Inventario_Paginas'!$G$6:$G$200,"Alta")+COUNTIFS('02_Inventario_Paginas'!$B$6:$B$200,A12,'02_Inventario_Paginas'!$G$6:$G$200,"Muito alta") | N12: Preço do módulo = incremental + parcela de Core + implantação/integrações específicas do cliente | O12: =COUNTIFS('09_Estimativa_96_Telas'!$B$6:$B$200,A12,'09_Estimativa_96_Telas'!$E$6:$E$200,"MVP+1") | P12: =SUMIFS('09_Estimativa_96_Telas'!$AA$6:$AA$200,'09_Estimativa_96_Telas'!$B$6:$B$200,A12,'09_Estimativa_96_Telas'!$E$6:$E$200,"MVP+1")
A13: COM | B13: Comunidades | C13: =COUNTIF('09_Estimativa_96_Telas'!$B$6:$B$200,A13) | D13: =COUNTIFS('09_Estimativa_96_Telas'!$B$6:$B$200,A13,'09_Estimativa_96_Telas'!$E$6:$E$200,"MVP") | E13: =COUNTIFS('09_Estimativa_96_Telas'!$B$6:$B$200,A13,'09_Estimativa_96_Telas'!$E$6:$E$200,"Fase 2") | F13: =SUMIF('09_Estimativa_96_Telas'!$B$6:$B$200,A13,'09_Estimativa_96_Telas'!$W$6:$W$200) | G13: =SUMIF('09_Estimativa_96_Telas'!$B$6:$B$200,A13,'09_Estimativa_96_Telas'!$AA$6:$AA$200) | H13: =SUMIFS('09_Estimativa_96_Telas'!$AA$6:$AA$200,'09_Estimativa_96_Telas'!$B$6:$B$200,A13,'09_Estimativa_96_Telas'!$E$6:$E$200,"MVP") | I13: =SUMIFS('09_Estimativa_96_Telas'!$AA$6:$AA$200,'09_Estimativa_96_Telas'!$B$6:$B$200,A13,'09_Estimativa_96_Telas'!$E$6:$E$200,"Fase 2") | J13: =IF(A13="CORE",G13,$G$6/8) | K13: =IF(A13="CORE",G13,G13) | L13: =G13/SUM($G$6:$G$14) | M13: =COUNTIFS('02_Inventario_Paginas'!$B$6:$B$200,A13,'02_Inventario_Paginas'!$G$6:$G$200,"Alta")+COUNTIFS('02_Inventario_Paginas'!$B$6:$B$200,A13,'02_Inventario_Paginas'!$G$6:$G$200,"Muito alta") | N13: Preço do módulo = incremental + parcela de Core + implantação/integrações específicas do cliente | O13: =COUNTIFS('09_Estimativa_96_Telas'!$B$6:$B$200,A13,'09_Estimativa_96_Telas'!$E$6:$E$200,"MVP+1") | P13: =SUMIFS('09_Estimativa_96_Telas'!$AA$6:$AA$200,'09_Estimativa_96_Telas'!$B$6:$B$200,A13,'09_Estimativa_96_Telas'!$E$6:$E$200,"MVP+1")
A14: CUST | B14: Clientes & Receita | C14: =COUNTIF('09_Estimativa_96_Telas'!$B$6:$B$200,A14) | D14: =COUNTIFS('09_Estimativa_96_Telas'!$B$6:$B$200,A14,'09_Estimativa_96_Telas'!$E$6:$E$200,"MVP") | E14: =COUNTIFS('09_Estimativa_96_Telas'!$B$6:$B$200,A14,'09_Estimativa_96_Telas'!$E$6:$E$200,"Fase 2") | F14: =SUMIF('09_Estimativa_96_Telas'!$B$6:$B$200,A14,'09_Estimativa_96_Telas'!$W$6:$W$200) | G14: =SUMIF('09_Estimativa_96_Telas'!$B$6:$B$200,A14,'09_Estimativa_96_Telas'!$AA$6:$AA$200) | H14: =SUMIFS('09_Estimativa_96_Telas'!$AA$6:$AA$200,'09_Estimativa_96_Telas'!$B$6:$B$200,A14,'09_Estimativa_96_Telas'!$E$6:$E$200,"MVP") | I14: =SUMIFS('09_Estimativa_96_Telas'!$AA$6:$AA$200,'09_Estimativa_96_Telas'!$B$6:$B$200,A14,'09_Estimativa_96_Telas'!$E$6:$E$200,"Fase 2") | J14: =IF(A14="CORE",G14,$G$6/8) | K14: =IF(A14="CORE",G14,G14) | L14: =G14/SUM($G$6:$G$14) | M14: =COUNTIFS('02_Inventario_Paginas'!$B$6:$B$200,A14,'02_Inventario_Paginas'!$G$6:$G$200,"Alta")+COUNTIFS('02_Inventario_Paginas'!$B$6:$B$200,A14,'02_Inventario_Paginas'!$G$6:$G$200,"Muito alta") | N14: Novo — MOD-04 Tecnica (MVP). | O14: =COUNTIFS('09_Estimativa_96_Telas'!$B$6:$B$200,A14,'09_Estimativa_96_Telas'!$E$6:$E$200,"MVP+1") | P14: =SUMIFS('09_Estimativa_96_Telas'!$AA$6:$AA$200,'09_Estimativa_96_Telas'!$B$6:$B$200,A14,'09_Estimativa_96_Telas'!$E$6:$E$200,"MVP+1")
A15: CAPEX TOTAL DA PLATAFORMA (sem duplicação de telas compartilhadas) | G15: =SUM(G6:G14)

Sheet 11_OPEX_Mensal
A1: OPEX MENSAL — PLATAFORMA E MÓDULOS
A5: Componente | B5: Base mensal R$ | C5: Core % | D5: Vertical % | E5: Core mensal | F5: Pool verticais | G5: Observação | H5: Premissa | J5: Código | K5: Módulo | L5: Peso de complexidade | M5: OPEX incremental/mês | N5: Core rateado/mês | O5: OPEX fully-loaded/mês
A6: ='08_Premissas_Custos'!A24 | B6: ='08_Premissas_Custos'!B24 | C6: 0.75 | D6: =1-C6 | E6: =B6*C6 | F6: =B6*D6 | G6: ='08_Premissas_Custos'!D24 | H6: Editável | J6: ED | K6: Estratégia & Dados | L6: ='10_CAPEX_por_Modulo'!G7/SUM('10_CAPEX_por_Modulo'!$G$7:$G$14) | M6: =SUM($F$6:$F$13)*L6 | N6: =SUM($E$6:$E$13)/8 | O6: =M6+N6
A7: ='08_Premissas_Custos'!A25 | B7: ='08_Premissas_Custos'!B25 | C7: 0.55 | D7: =1-C7 | E7: =B7*C7 | F7: =B7*D7 | G7: ='08_Premissas_Custos'!D25 | H7: Editável | J7: COL | K7: Colaboradores / Meu Time | L7: ='10_CAPEX_por_Modulo'!G8/SUM('10_CAPEX_por_Modulo'!$G$7:$G$14) | M7: =SUM($F$6:$F$13)*L7 | N7: =SUM($E$6:$E$13)/8 | O7: =M7+N7
A8: ='08_Premissas_Custos'!A26 | B8: ='08_Premissas_Custos'!B26 | C8: 0.35 | D8: =1-C8 | E8: =B8*C8 | F8: =B8*D8 | G8: ='08_Premissas_Custos'!D26 | H8: Editável | J8: CAN | K8: Candidatos & Carreira | L8: ='10_CAPEX_por_Modulo'!G9/SUM('10_CAPEX_por_Modulo'!$G$7:$G$14) | M8: =SUM($F$6:$F$13)*L8 | N8: =SUM($E$6:$E$13)/8 | O8: =M8+N8
A9: ='08_Premissas_Custos'!A27 | B9: ='08_Premissas_Custos'!B27 | C9: 0.3 | D9: =1-C9 | E9: =B9*C9 | F9: =B9*D9 | G9: ='08_Premissas_Custos'!D27 | H9: Editável | J9: FOR | K9: Fornecedores & Negócios | L9: ='10_CAPEX_por_Modulo'!G10/SUM('10_CAPEX_por_Modulo'!$G$7:$G$14) | M9: =SUM($F$6:$F$13)*L9 | N9: =SUM($E$6:$E$13)/8 | O9: =M9+N9
A10: ='08_Premissas_Custos'!A28 | B10: ='08_Premissas_Custos'!B28 | C10: 0.7 | D10: =1-C10 | E10: =B10*C10 | F10: =B10*D10 | G10: ='08_Premissas_Custos'!D28 | H10: Editável | J10: ACA | K10: Acadêmico / Universidades | L10: ='10_CAPEX_por_Modulo'!G11/SUM('10_CAPEX_por_Modulo'!$G$7:$G$14) | M10: =SUM($F$6:$F$13)*L10 | N10: =SUM($E$6:$E$13)/8 | O10: =M10+N10
A11: ='08_Premissas_Custos'!A29 | B11: ='08_Premissas_Custos'!B29 | C11: 0.35 | D11: =1-C11 | E11: =B11*C11 | F11: =B11*D11 | G11: ='08_Premissas_Custos'!D29 | H11: Editável | J11: EVT | K11: Eventos | L11: ='10_CAPEX_por_Modulo'!G12/SUM('10_CAPEX_por_Modulo'!$G$7:$G$14) | M11: =SUM($F$6:$F$13)*L11 | N11: =SUM($E$6:$E$13)/8 | O11: =M11+N11
A12: ='08_Premissas_Custos'!A30 | B12: ='08_Premissas_Custos'!B30 | C12: 0.45 | D12: =1-C12 | E12: =B12*C12 | F12: =B12*D12 | G12: ='08_Premissas_Custos'!D30 | H12: Editável | J12: COM | K12: Comunidades | L12: ='10_CAPEX_por_Modulo'!G13/SUM('10_CAPEX_por_Modulo'!$G$7:$G$14) | M12: =SUM($F$6:$F$13)*L12 | N12: =SUM($E$6:$E$13)/8 | O12: =M12+N12
A13: ='08_Premissas_Custos'!A31 | B13: ='08_Premissas_Custos'!B31 | C13: 0.25 | D13: =1-C13 | E13: =B13*C13 | F13: =B13*D13 | G13: ='08_Premissas_Custos'!D31 | H13: Editável | J13: CUST | K13: Clientes & Receita | L13: ='10_CAPEX_por_Modulo'!G14/SUM('10_CAPEX_por_Modulo'!$G$7:$G$14) | M13: =SUM($F$6:$F$13)*L13 | N13: =SUM($E$6:$E$13)/8 | O13: =M13+N13
A15: OPEX BASE TOTAL / MÊS | E15: =SUM(B6:B13)

Sheet 12_Dashboard_Custos
A1: HUB — VISÃO EXECUTIVA DE CUSTO DA PLATAFORMA
A3: Modelo inicial para decisão: o valor final deve ser calibrado com arquitetura técnica escolhida, volume de usuários/dados, integrações por cliente e cotações de equipe/fornecedores.
A5: CAPEX TOTAL | D5: CAPEX CORE | G5: OPEX BASE / MÊS | I5: TELAS MAPEADAS
A6: ='10_CAPEX_por_Modulo'!G15 | D6: ='10_CAPEX_por_Modulo'!G6 | G6: ='11_OPEX_Mensal'!E15 | I6: =COUNTA('02_Inventario_Paginas'!A6:A200)
A10: Código | B10: Módulo | C10: CAPEX incremental | D10: OPEX fully-loaded/mês | E10: Telas | F10: Observação
A11: ED | B11: Estratégia & Dados | C11: ='10_CAPEX_por_Modulo'!K7 | D11: ='11_OPEX_Mensal'!O6 | E11: ='10_CAPEX_por_Modulo'!C7 | F11: Core não é cobrado novamente; alocar implantação e integrações específicas à parte.
A12: COL | B12: Colaboradores / Meu Time | C12: ='10_CAPEX_por_Modulo'!K8 | D12: ='11_OPEX_Mensal'!O7 | E12: ='10_CAPEX_por_Modulo'!C8 | F12: Core não é cobrado novamente; alocar implantação e integrações específicas à parte.
A13: CAN | B13: Candidatos & Carreira | C13: ='10_CAPEX_por_Modulo'!K9 | D13: ='11_OPEX_Mensal'!O8 | E13: ='10_CAPEX_por_Modulo'!C9 | F13: Core não é cobrado novamente; alocar implantação e integrações específicas à parte.
A14: FOR | B14: Fornecedores & Negócios | C14: ='10_CAPEX_por_Modulo'!K10 | D14: ='11_OPEX_Mensal'!O9 | E14: ='10_CAPEX_por_Modulo'!C10 | F14: Core não é cobrado novamente; alocar implantação e integrações específicas à parte.
A15: ACA | B15: Acadêmico / Universidades | C15: ='10_CAPEX_por_Modulo'!K11 | D15: ='11_OPEX_Mensal'!O10 | E15: ='10_CAPEX_por_Modulo'!C11 | F15: Core não é cobrado novamente; alocar implantação e integrações específicas à parte.
A16: EVT | B16: Eventos | C16: ='10_CAPEX_por_Modulo'!K12 | D16: ='11_OPEX_Mensal'!O11 | E16: ='10_CAPEX_por_Modulo'!C12 | F16: Core não é cobrado novamente; alocar implantação e integrações específicas à parte.
A17: COM | B17: Comunidades | C17: ='10_CAPEX_por_Modulo'!K13 | D17: ='11_OPEX_Mensal'!O12 | E17: ='10_CAPEX_por_Modulo'!C13 | F17: Core não é cobrado novamente; alocar implantação e integrações específicas à parte.
A18: CUST | B18: Clientes & Receita | C18: ='10_CAPEX_por_Modulo'!K14 | D18: ='11_OPEX_Mensal'!O13 | E18: ='10_CAPEX_por_Modulo'!C14 | F18: Core não é cobrado novamente; alocar implantação e integrações específicas à parte.
